Workbook
Name BasicPrice: 假设及结论!$P$15
Name CapitalRatio: 假设及结论!$Q$30
Name CirculatingFund: 假设及结论!$B$33
Name circulatingRate: 假设及结论!$N$30
Name CirculatingRatio: 假设及结论!$N$30
Name ConstructPeriod: 假设及结论!$G$13
Name CPI: 假设及结论!$K$33
Name DebtPeriod: 假设及结论!$O$30
Name DebtRate: 假设及结论!$P$30
Name DebtRatio: 1-假设及结论!$Q$30
Name DeprecitionPeriod: 假设及结论!$G$33
Name DiscountRate: WACC!$C$19
Name FixedAssets: 假设及结论!$C$33
Name OperationPeriod: 假设及结论!$H$13
Name SubsidyLossMonths: "="
Name type: 假设及结论!$D$13
Name WACC: WACC!$C$19
Name InstalledCapacity: 假设及结论!$F$13
Name TotalInvestment: 假设及结论!$B$13

Sheet 储能投资明细
B3: 100M/200MWh獨立儲能電站的投資構成明細 | E3: 汇率 | F3: 7.02
B4: 明细 | C4: 单价 | D4: 单位 | E4: 数量 | F4: 小计
B5: 硬體成本 | F5: =SUM(F7:F21) -> 34880000 | G5: =F5*$F$3 -> 244857600
B6: 儲能設備（BatteryEnergyStorageSystem,BESS）
B7: 電池儲能系統（Battery） | C7: 1800 | D7: 美元/个 | E7: 13500 | F7: =C7*E7 -> 24300000 | G7: =F7*$F$3 -> 170586000
B8: 變壓器（Transformer） | C8: 70000 | D8: 美元/个 | E8: 3 | F8: =C8*E8 -> 210000 | G8: =F8*$F$3 -> 1474200
B9: 逆變器（Inverter） | C9: 40000 | D9: 美元/个 | E9: 15 | F9: =C9*E9 -> 600000 | G9: =F9*$F$3 -> 4212000
B10: 控制系統（ControlSystem） | C10: 70000 | D10: 套 | E10: 1 | F10: =C10*E10 -> 70000 | G10: =F10*$F$3 -> 491400
B11: 電力轉換設備 | F11: =C11*E11 -> 0
B12: 變壓器（Transformer） | C12: 800000 | D12: 美元/个 | E12: 2 | F12: =C12*E12 -> 1600000 | G12: =F12*$F$3 -> 11232000
B13: 逆變器（Inverter） | C13: 500000 | D13: 美元/个 | E13: 10 | F13: =C13*E13 -> 5000000 | G13: =F13*$F$3 -> 35100000
B14: 配電設備（Distribution equipment） | C14: 500000 | D14: 批 | E14: 1 | F14: =C14*E14 -> 500000
B15: 監控系統 | F15: =C15*E15 -> 0
B16: 感測器（Sensor） | C16: 200000 | D16: 批 | E16: 1 | F16: =C16*E16 -> 200000 | G16: =F16*$F$3 -> 1404000
B17: 基礎設施 | F17: =C17*E17 -> 0
B18: 土地購置或租賃 | C18: 5000 | D18: 美元/亩 | E18: 100 | F18: =C18*E18 -> 500000 | G18: =F18*$F$3 -> 3510000
B19: 建築物（如控制室、維護室） | C19: 600 | D19: 美元/平米 | E19: 1500 | F19: =C19*E19 -> 900000
B20: 冷卻系統 | C20: 800000 | D20: 項 | E20: 1 | F20: =C20*E20 -> 800000
B21: 消防係統 | C21: 200000 | D21: 項 | E21: 1 | F21: =C21*E21 -> 200000 | G21: =F19*$F$3 -> 6318000
B22: 軟體成本 | F22: =SUM(F24:F27) -> 1310000 | G22: =F22*$F$3 -> 9196200
B23: 控制系統軟體 | F23: =C23*E23 -> 0
B24: 儲能控制系統（EnergyStorageManagementSystem） | C24: 1000000 | D24: 套 | E24: 1 | F24: =C24*E24 -> 1000000 | G24: =F24*$F$3 -> 7020000
B25: 監控軟體 | F25: =C25*E25 -> 0
B26: SCADA系統 | C26: 300000 | D26: 套 | E26: 1 | F26: =C26*E26 -> 300000 | G26: =F26*$F$3 -> 2106000
B27: 數據分析軟體（DataAnalytics） | C27: 10000 | D27: 套 | E27: 1 | F27: =C27*E27 -> 10000 | G27: =F27*$F$3 -> 70200
B28: 工程成本 | F28: =SUM(F29:F36) -> 6310000 | G28: =F28*$F$3 -> 44296200
B29: 設計與規劃 | F29: =C29*E29 -> 0
B30: 工程師費用（EngineeringFee） | C30: 120000 | D30: 项 | E30: 1 | F30: =C30*E30 -> 120000 | G30: =F30*$F$3 -> 842400
B31: 設計軟體費用（DesignSoftwareFee） | C31: 120000 | D31: 项 | E31: 1 | F31: =C31*E31 -> 120000 | G31: =F31*$F$3 -> 842400
B32: 建築安裝 | F32: =C32*E32 -> 0
B33: 施工費用（ConstructionFee） | C33: 6000000 | D33: 项 | E33: 1 | F33: =C33*E33 -> 6000000 | G33: =F33*$F$3 -> 42120000
B34: 測試與驗證 | F34: =C34*E34 -> 0
B35: 測試設備費用（TestingEquipmentFee） | C35: 35000 | D35: 项 | E35: 1 | F35: =C35*E35 -> 35000 | G35: =F35*$F$3 -> 245700
B36: 測試人員費用（TestingPersonnelFee） | C36: 35000 | D36: 项 | E36: 1 | F36: =C36*E36 -> 35000 | G36: =F36*$F$3 -> 245700
B37: 工程成本總計
B38: 營運成本 | F38: =SUM(F39:F47) -> 760000 | G38: =F38*$F$3 -> 5335200
B39: 維護費用 | F39: =C39*E39 -> 0
B40: 定期維護費用（RegularMaintenanceFee） | C40: 120000 | D40: 项 | E40: 1 | F40: =C40*E40 -> 120000 | G40: =F40*$F$3 -> 842400
B41: 非預期維護費用（UnplannedMaintenanceFee） | C41: 30000 | D41: 项 | E41: 1 | F41: =C41*E41 -> 30000 | G41: =F41*$F$3 -> 210600
B42: 人工成本 | F42: =C42*E42 -> 0
B43: 員工薪資（EmployeeSalary） | C43: 110000 | D43: 美元/人 | E43: 4 | F43: =C43*E43 -> 440000 | G43: =F43*$F$3 -> 3088800
B44: 訓練費用（TrainingFee） | C44: 10000 | D44: 项 | E44: 4 | F44: =C44*E44 -> 40000 | G44: =F44*$F$3 -> 280800
B45: 保險費用 | F45: =C45*E45 -> 0
B46: 儲能設備保險（EquipmentInsurance） | C46: 500 | D46: 美元/mWh | E46: 200 | F46: =C46*E46 -> 100000 | G46: =F46*$F$3 -> 702000
B47: 公眾責任保險（PublicLiabilityInsurance） | C47: 150 | D47: 美元/mWh | E47: 200 | F47: =C47*E47 -> 30000 | G47: =F47*$F$3 -> 210600
B48: 100M/200MWh獨立儲能電站的總投資成本約為 | F48: =SUM(F49:F52) -> 43260000 | G48: =F48*$F$3 -> 303685200 | H48: =G5/G48 -> 0.80628756
B49: 硬體成本 | D49: 美元 | F49: =F5 -> 34880000 | G49: =F49*$F$3 -> 244857600
B50: 軟體成本 | D50: 美元 | F50: =F22 -> 1310000 | G50: =F50*$F$3 -> 9196200
B51: 工程成本 | D51: 美元 | F51: =F28 -> 6310000 | G51: =F51*$F$3 -> 44296200
B52: 營運成本（首年） | D52: 美元 | F52: =F38 -> 760000 | G52: =F52*$F$3 -> 5335200

Sheet Sheet2
B3: 手续清单
B4: 序号 | C4: 许可文件 | D4: 主管部门 | E4: 备注
B5: 1 | C5: 公司注册 | D5: 乌兹别克斯坦共和国司法部国家服务局 | E5: 业主需求，需当地缴纳税费，开具增值税法发票
B6: 2 | C6: 税务登记 | D6: 国家税务委员会税务检查机关
B7: 3 | C7: 临时土地使用权证（如适用） | D7: 乌兹别克斯坦共和国国土资源、大地测量、制图和地籍委员会 | E7: 不需要。
B8: 4 | C8: 建筑规划任务书（如适用） | D8: 乌兹别克斯坦共和国建设部 | E8: 不需要，由业主办理完国家能源部项目批复及内务府开具的总统令即可
B9: 5 | C9: 项目施工许可证（如适用） | D9: 乌兹别克斯坦共和国建设部 | E9: 不需要，由业主办理完国家能源部项目批复及内务府开具的总统令即可
B10: 6 | C10: 环境影响评估报告 | D10: 乌兹别克斯坦共和国环境专业技术中心 | E10: 需要，可以委托纳曼干项目塔什干ABREST公司办理
B11: 7 | C11: 危险生产设施工及运营项目许可证 | D11: 乌兹别克斯坦共和国建设部 | E11: 不需要
B12: 8 | C12: 无人驾驶民用航空器（无人机）使用许可证（如适用） | D12: 乌兹别克斯坦共和国国家飞行安全监察局 | E12: 不需要
B13: 9 | C13: 项目文档许可(PD)（如适用） | D13: 乌兹别克斯坦共和国建设部城市（地区）建设局建筑委员会 | E13: 不需要
B14: 10 | C14: 工业安全规范符合确认书（如适用） | D14: 认证机构 | E14: 不需要
B15: 11 | C15: 危险设备安装和使用许可证（如适用） | D15: 乌兹别克斯坦共和国国家工业安全委员会 | E15: 不需要
B16: 12 | C16: 国家项目验收（如适用） | D16: 乌兹别克斯坦共和国建设部 | E16: 需要，可以委托纳曼干项目塔什干ABREST公司办理
B17: 13 | C17: 并网、消纳报告批复 | D17: 国家电网NEGU | E17: 只需要电网批复报告即可，可以委托纳曼干项目塔什干ABREST公司办理
B18: 14 | C18: 外国分包、当地分包单位各等级（类别）电力、工程施工资质 | D18: 国家电网、建设部 | E18: 调试，安装，土建等分包需要资质，我司合作的分包具备以上条件
... B29: 26 | C29: EIF、开关站征地令 | D29: 纳沃依州纳沃依市市政府、区政府 | E29: 需要，由核工业金华勘测设计有限公司将测绘坐标及线路批复上报至纳沃伊市 KARMANI 区政府进行申请，7个工作日公示完成，完成后进行土地租赁
B30: 27 | C30: EIF、开关站征地补偿以及缴费证明
B31: 28 | C31: 乌兹别克斯坦共和国建设部颁发的高空作业和维修的许可证 | D31: 建设部 | E31: 不需要
B32: 29 | C32: 乌兹别克斯坦共和国国家地质和矿产资源委员会下属的水文地质组织颁布水文结论。 | D32: 国家地质矿产委员会 | E32: 不需要
B33: 30 | C33: 特殊用水许可证（如适用） | D33: 乌兹别克斯坦共和国国家生态与环境保护委员会（天然水源区取水）、乌兹别克斯坦共和国国家地质与矿产资源委员会（地下水源区取水）及乌兹别克斯坦共和国水资源管理部（人工储水区取水）各地区部门（不用打井，不用办） | E33: 我司在当地已有打井合作公司，可以办理相关许可
B34: 31 | C34: 与当地天然气供应公司签署合同并获取天然气技术接入条件、使用许可 | D34: 乌兹天然气输送公司 | E34: 不需要
B35: 32 | C35: 与当地电力供应商签订合同并获取技术条件 | D35: 地区电网局 | E35: 不需要
B36: 33 | C36: 对外贷款协议登记（如适用） | D36: 乌兹别克斯坦共和国中央银行 | E36: 本地服务银行通知，不需要
B37: 34 | C37: 取得特定货物进出口许可证 | D37: 乌兹别克斯坦共和国内阁对外贸易发展、产业、地区出口潜力信息与分析部 | E37: 不需要
B38: 35 | C38: 乌兹别克斯坦进口设备免征关税与增值税（免税清单） | D38: 国家税务委员会税务检查机关 | E38: 需要，需咨询海关免税政策，免税清单。
B39: 36 | C39: 进口货物证明书 | D39: 乌兹别克斯坦标准认证中心 | E39: 需要，或授权认证机构，厂家出货时提供
B40: 37 | C40: 外籍工人工作签证与就业许可证 | D40: 外籍劳工移民局 | E40: 签证要商务签，当地公司成立后与公司签订劳务合同，建议和劳务公司签订，手续费用低。
B41: 38 | C41: 与当地法规相关的其他文件 | D41: 乌兹别克斯坦国家电网股份公司等 | E41: 需要，可委托纳曼甘项目现合作的JURU设计院上报电网
B42: 39 | C42: 项目建筑物不动产权登记证（项目建成后） | D42: 州地籍委员会 | E42: 业主来办
... B45: 42 | C45: 发电许可证 | D45: 乌兹别克斯坦国家电网股份公司 | E45: 只要并网许可证，塔什干ABREST公司可以办理
B46: 43 | C46: 其他 | D46: 与本项目投资、建设与运营相关，包含但不限于上述范围的其他许可及政府批准。

Sheet 11院概算
B3: 序号 | C3: 工程和费用名称 | D3: 费率 | E3: 建筑工程 | F3: 设备购置费 | G3: 安装工程费 | H3: 其他费用 | I3: 总值 | J3: 占固定资产投资（%）
E5: a | F5: b | G5: c
B6: 1 | C6: 工程费用 | E6: =E7+E11 -> 122140 | F6: =F7+F11 -> 76042 | G6: =G7+G11 -> 55160 | H6: =H7+H11 -> 0 | I6: =I7+I11 -> 253342 | J6: =I6/$I$31 -> 0.89317691
B7: 1.1 | C7: 设备费 | E7: =SUM(E8:E10) -> 0 | F7: =SUM(F8:F10) -> 76042 | G7: =SUM(G8:G10) -> 55160 | H7: =SUM(H8:H10) -> 0 | I7: =SUM(I8:I10) -> 131202
B8: 1.1.1 | C8: 光伏设备及安装工程 | F8: 76042 | G8: 39400 | I8: =SUM(E8:H8) -> 115442
B9: 1.1.2 | C9: 电缆线路及安装工程 | G9: 11820 | I9: =SUM(E9:H9) -> 11820
B10: 1.1.3 | C10: 其他设备及安装工程 | G10: 3940 | I10: =SUM(E10:H10) -> 3940
B11: 1.2 | C11: 建筑工程 | E11: =E12 -> 122140 | F11: =F12 -> 0 | G11: =G12 -> 0 | H11: =H12 -> 0 | I11: =I12 -> 122140
B12: 1.2.1 | C12: 发电场基础工程 | E12: 122140 | I12: =SUM(E12:H12) -> 122140
B13: 2 | C13: 工程建设其他费用 | E13: =E14+E15+E25+E26 -> 0 | F13: =F14+F15+F25+F26 -> 0 | G13: =G14+G15+G25+G26 -> 0 | H13: =H14+H15+H25+H26 -> 11783.475 | I13: =I14+I15+I25+I26 -> 11783.475 | J13: =I13/$I$31 -> 0.041543556
B14: 2.1 | C14: 项目建设用地费 | H14: 50 | I14: =SUM(E14:H14) -> 50
B15: 2.2 | C15: 项目建设管理费 | E15: =SUM(E16:E24) -> 0 | F15: =SUM(F16:F24) -> 0 | G15: =SUM(G16:G24) -> 0 | H15: =SUM(H16:H24) -> 9372.1146 | I15: =SUM(I16:I24) -> 9372.1146
B16: 2.2.1 | C16: 工程前期费 | H16: 2658 | I16: =SUM(E16:H16) -> 2658
B17: 2.2.2 | C17: 工程建设管理费（Based：a+b+c) | D17: 0.0117 | H17: =($E$6+$F$6+$G$6)*D17 -> 2964.1014 | I17: =SUM(E17:H17) -> 2964.1014
B18: 2.2.3 | C18: 工程建设监理费（Based：a+b+c) | D18: 0.0043 | H18: =($E$6+$F$6+$G$6)*D18 -> 1089.3706 | I18: =SUM(E18:H18) -> 1089.3706
B19: 2.2.4 | C19: 咨询服务费（Based：a+b+c) | D19: 0.0026 | H19: =($E$6+$F$6+$G$6)*D19 -> 658.6892 | I19: =SUM(E19:H19) -> 658.6892
B20: 2.2.5 | C20: 项目技术经济评审费（Based：a+b+c) | D20: 0.0015 | H20: =($E$6+$F$6+$G$6)*D20 -> 380.013 | I20: =SUM(E20:H20) -> 380.013
B21: 2.2.6 | C21: 工程质量检查检测费（Based：a+c) | D21: 0.0011 | H21: =($E$6+$G$6)*D21 -> 195.03 | I21: =SUM(E21:H21) -> 195.03
B22: 2.2.7 | C22: 项目验收费（Based：a+b+c) | D22: 0.0034 | H22: =($E$6+$F$6+$G$6)*D22 -> 861.3628 | I22: =SUM(E22:H22) -> 861.3628
B23: 2.2.8 | C23: 工程保险费（Based：a+b+c) | D23: 0.0021 | H23: =($E$6+$F$6+$G$6)*D23 -> 532.0182 | I23: =SUM(E23:H23) -> 532.0182
B24: 2.2.9 | C24: 土地补偿款 | H24: =假设及结论!K21 -> 33.52944 | I24: =SUM(E24:H24) -> 33.52944
B25: 2.3 | C25: 生产准备费（Based：b) | D25: 0.0054 | H25: =($F$6)*D25 -> 410.6268 | I25: =SUM(E25:H25) -> 410.6268
B26: 2.4 | C26: 勘察费设计费（Based：a+b+c) | D26: 0.0077 | H26: =($E$6+$F$6+$G$6)*D26 -> 1950.7334 | I26: =SUM(E26:H26) -> 1950.7334
B27: 3 | C27: 预备费 | H27: =H28 -> 15200.52 | I27: =I28 -> 15200.52 | J27: =I27/$I$31 -> 0.053590615
B28: 3.1 | C28: 基本预备费（Based：a+b+c) | D28: 0.06 | H28: =($E$6+$F$6+$G$6)*D28 -> 15200.52 | I28: =SUM(E28:H28) -> 15200.52
B29: 4 | C29: 建设投资合计 | E29: =E6+E13+E27 -> 122140 | F29: =F6+F13+F27 -> 76042 | G29: =G6+G13+G27 -> 55160 | H29: =H6+H13+H27 -> 26983.995 | I29: =I6+I13+I27 -> 280325.99
B30: 5 | C30: 建设期利息 | H30: =假设及结论!L7 -> 3315.4619 | I30: =SUM(E30:H30) -> 3315.4619 | J30: =I30/$I$31 -> 0.011688919
B31: 6 | C31: 固定资产投资合计 | E31: =E29+E30 -> 122140 | F31: =F29+F30 -> 76042 | G31: =G29+G30 -> 55160 | H31: =H29+H30 -> 30299.457 | I31: =I29+I30 -> 283641.46 | J31: =I31/$I$31 -> 1
C32: 单位千瓦的静态投资（元/千瓦） | I32: =I29/假设及结论!$F$13 -> 3737.6799
C33: 单位千瓦的动态投资（元/千瓦） | I33: =I31/假设及结论!$F$13 -> 3781.8861
B34: 7 | C34: 流动资金 | H34: =假设及结论!B33 -> 1500 | I34: =SUM(E34:H34) -> 1500
B35: 8 | C35: 总投资合计 | E35: =E31+E34 -> 122140 | F35: =F31+F34 -> 76042 | G35: =G31+G34 -> 55160 | H35: =H31+H34 -> 31799.457 | I35: =I31+I34 -> 285141.46
C36: 比例(%) | E36: =E35/$I$35 -> 0.4283488 | F36: =F35/$I$35 -> 0.26668167 | G36: =G35/$I$35 -> 0.19344784 | H36: =H35/$I$35 -> 0.11152169 | I36: =SUM(E36:H36) -> 1

Sheet Sheet1
B2: 光伏设备购置费明细
B3: 序号 | C3: 设备名称 | D3: 数量/规格 | E3: 单价（元/单位） | F3: 总价（元） | G3: 备注
B4: 1 | C4: 光伏组件 | D4: ="光伏组件（共 "&TEXT(ROUNDUP(假设及结论!F13*10^7/MID(G4,7,3),0),"###,#0")&" 块）" -> 光伏组件（共 1,041,667 块） | E4: 576 | F4: =INT(MID(D4,7,11))*E4 -> 600000192 | G4: 单块组件功率720W
B5: 2 | C5: 逆变器 | D5: 100 台（8MW） | E5: 1000000 | F5: 100000000 | G5: 单台逆变器容量8MW
B6: 3 | C6: 汇流箱 | D6: 400 个（2MW） | E6: 200000 | F6: 80000000 | G6: 单个汇流箱容量2MW
B7: 4 | C7: 支架 | D7: 1083334 | E7: 143 | F7: =D7*E7 -> 154916762 | G7: 包括地梁、立柱、横梁等
B8: 5 | C8: 监控系统 | D8: 10 | E8: 100000 | F8: =D8*E8 -> 1000000 | G8: 包括摄像头、数据采集器等
B9: 6 | C9: 避雷系统 | D9: 400 | E9: 5000 | F9: =D9*E9 -> 2000000 | G9: 包括避雷针、避雷带等
B10: 7 | C10: 并网设备 | D10: 1 | E10: 500000 | F10: 500000 | G10: 包括并网箱、断路器等
B11: 8 | C11: 电缆 | D11: 500000 | E11: 100 | F11: 50000000 | G11: 包括直埋电缆、桥架电缆等
B12: 合计 | C12: - | D12: - | E12: - | F12: =SUM(F4:F11) -> 988416954 | G12: -
B14: 500kV升压站设备购置费明细
B15: 序号 | C15: 设备名称 | D15: 数量/规格 | E15: 单价（元/单位） | F15: 总价（元） | G15: 备注
B16: 1 | C16: 主变压器（500kV） | D16: 2台 | E16: 15,000,000.00 元/台 | F16: 30000000 | G16: 500kV主变压器
B17: 2 | C17: 高压断路器 | D17: 4台 | E17: 1,500,000.00 元/台 | F17: 6000000 | G17: 500kV高压断路器
B18: 3 | C18: 隔离开关 | D18: 8台 | E18: 500,000.00 元/台 | F18: 4000000 | G18: 500kV隔离开关
B19: 4 | C19: 避雷器 | D19: 10个 | E19: 200,000.00 元/个 | F19: 2000000 | G19: 500kV避雷器
B20: 5 | C20: 互感器 | D20: 10个 | E20: 300,000.00 元/个 | F20: 3000000 | G20: 500kV电流/电压互感器
B21: 6 | C21: 保护装置 | D21: 1套 | E21: 2,000,000.00 元/套 | F21: 2000000 | G21: 500kV保护装置
B22: 7 | C22: 控制系统 | D22: 1套 | E22: 1,500,000.00 元/套 | F22: 1500000 | G22: 500kV控制系统
B23: 8 | C23: 监控系统 | D23: 1套 | E23: 1,000,000.00 元/套 | F23: 1000000 | G23: 500kV监控系统
B24: 9 | C24: 消防系统 | D24: 1套 | E24: 500,000.00 元/套 | F24: 500000 | G24: 500kV消防系统
B25: 10 | C25: 通信系统 | D25: 1套 | E25: 800,000.00 元/套 | F25: 800000 | G25: 500kV通信系统
B26: 合计 | C26: - | D26: - | E26: - | F26: =SUM(F16:F25) -> 50800000 | G26: -
B29: 土建工程概算明细
B30: 序号 | C30: 工程内容 | D30: 数量/规格 | E30: 单价（元/单位） | F30: 总价（元） | G30: 备注
B31: 1 | C31: 场地平整 | D31: 12,327,000 m² | E31: 15.00 元/m² | F31: 184905000 | G31: 包括清理杂物、平整土地等
B32: 2 | C32: 基础工程 | D32: 1,083,334 个桩基础 | E32: 800.00 元/个 | F32: 866667200 | G32: 包括混凝土、钢筋等材料
B33: 3 | C33: 道路硬化 | D33: 500,000 m² | E33: 120.00 元/m² | F33: 60000000 | G33: 包括场内道路、硬化面积等
B34: 4 | C34: 围栏工程 | D34: 50,000 m | E34: 150.00 元/m | F34: 7500000 | G34: 包括围栏材料、安装费用等
B35: 5 | C35: 排水系统 | D35: 10,000 m 排水沟 | E35: 200.00 元/m | F35: 2000000 | G35: 包括排水管道、雨水收集系统等
B36: 6 | C36: 监控室建设 | D36: 1 间（50 m²） | E36: 3,000.00 元/间 | F36: 3000 | G36: 包括建筑、防水处理等
B37: 7 | C37: 500kV升压站建设 | D37: 1 座 | E37: 50,000,000.00 元/座 | F37: =F26 -> 50800000 | G37: 包括升压站房屋、设备安装等
B38: 8 | C38: 接入线路建设 | D38: 8公里 | E38: 10,000,000.00 元/公里 | F38: 80000000 | G38: 包括线路杆塔、电缆敷设等
B39: 9 | C39: 其他辅助设施 | D39: - | E39: - | F39: 50000 | G39: 包括消防设施、照明系统等
B40: 合计 | C40: - | D40: - | E40: - | F40: =SUM(F31:F39) -> 1251925200 | G40: -
B43: 3. 安装工程概算明细
B44: 序号 | C44: 工程内容 | D44: 数量/规格 | E44: 单价（元/单位） | F44: 总价（元） | G44: 备注
B45: 1 | C45: 光伏组件安装 | D45: 1,083,334 块组件 | E45: 300.00 元/块 | F45: 325000200 | G45: 包括组件固定、接线盒安装等
B46: 2 | C46: 支架安装 | D46: 1,083,334 套支架 | E46: 1,500.00 元/套 | F46: 1625001100 | G46: 包括地梁、立柱、横梁等
B47: 3 | C47: 逆变器安装 | D47: 100 台逆变器 | E47: 50,000.00 元/台 | F47: 5000000 | G47: 包括逆变器固定、接线等
B48: 4 | C48: 汇流箱安装 | D48: 400 个汇流箱 | E48: 10,000.00 元/个 | F48: 4000000 | G48: 包括汇流箱固定、接线等
B49: 5 | C49: 电缆敷设 | D49: 500,000 m 电缆 | E49: 50.00 元/m | F49: 25000000 | G49: 包括直埋电缆、桥架电缆等
B50: 6 | C50: 监控系统安装 | D50: 10 套监控设备 | E50: 5,000.00 元/套 | F50: 50000 | G50: 包括摄像头、数据采集器等
B51: 7 | C51: 避雷系统安装 | D51: 400 个避雷器 | E51: 2,000.00 元/个 | F51: 800000 | G51: 包括避雷针、避雷带等
B52: 8 | C52: 并网设备安装 | D52: 1 套并网箱 | E52: 50,000.00 元/套 | F52: 50000 | G52: 包括并网箱、断路器等
B53: 9 | C53: 其他辅助设备安装 | D53: - | E53: - | F53: 50000 | G53: 包括消防设施、照明系统等
B54: 合计 | C54: - | D54: - | E54: - | F54: =SUM(F45:F53) -> 1984951300 | G54: -
B59: 500kV升压站工程明细
B60: 序号 | C60: 工程内容 | D60: 数量/规格 | E60: 单价（元/单位） | F60: 总价（元） | G60: 备注
B61: 1 | C61: 升压站房屋建设 | D61: 1座（1,000 m²） | E61: 5,000.00 元/m² | F61: 5000000 | G61: 包括主控楼、变电房等
B62: 2 | C62: 基础工程 | D62: 20个基础 | E62: 500,000.00 元/个 | F62: 10000000 | G62: 主变压器、断路器等基础
B63: 3 | C63: 设备安装 | D63: - | E63: - | F63: 15000000 | G63: 包括主变压器、断路器等安装
B64: 4 | C64: 电缆敷设 | D64: 10,000 m | E64: 100.00 元/m | F64: 1000000 | G64: 包括高压电缆、控制电缆等
B65: 5 | C65: 接地系统 | D65: 1套 | E65: 500,000.00 元/套 | F65: 500000 | G65: 500kV接地系统
B66: 6 | C66: 防雷系统 | D66: 1套 | E66: 800,000.00 元/套 | F66: 800000 | G66: 500kV防雷系统
B67: 7 | C67: 消防系统 | D67: 1套 | E67: 500,000.00 元/套 | F67: 500000 | G67: 500kV消防系统
B68: 8 | C68: 通信系统 | D68: 1套 | E68: 800,000.00 元/套 | F68: 800000 | G68: 500kV通信系统
B69: 9 | C69: 其他辅助设施 | D69: - | E69: - | F69: 1000000 | G69: 包括照明系统、围栏等
B70: 合计 | C70: - | D70: - | E70: - | F70: =SUM(F61:F69) -> 34600000
B73: 500kV升压站安装明细
B74: 序号 | C74: 安装内容 | D74: 数量/规格 | E74: 单价（元/单位） | F74: 总价（元） | G74: 备注
B75: 1 | C75: 主变压器安装 | D75: 2台 | E75: 2,000,000.00 元/台 | F75: 4000000 | G75: 500kV主变压器安装
B76: 2 | C76: 高压断路器安装 | D76: 4台 | E76: 500,000.00 元/台 | F76: 2000000 | G76: 500kV高压断路器安装
B77: 3 | C77: 隔离开关安装 | D77: 8台 | E77: 200,000.00 元/台 | F77: 1600000 | G77: 500kV隔离开关安装
B78: 4 | C78: 避雷器安装 | D78: 10个 | E78: 100,000.00 元/个 | F78: 1000000 | G78: 500kV避雷器安装
B79: 5 | C79: 互感器安装 | D79: 10个 | E79: 150,000.00 元/个 | F79: 1500000 | G79: 500kV电流/电压互感器安装
B80: 6 | C80: 保护装置安装 | D80: 1套 | E80: 500,000.00 元/套 | F80: 500000 | G80: 500kV保护装置安装
B81: 7 | C81: 控制系统安装 | D81: 1套 | E81: 500,000.00 元/套 | F81: 500000 | G81: 500kV控制系统安装
B82: 8 | C82: 监控系统安装 | D82: 1套 | E82: 300,000.00 元/套 | F82: 300000 | G82: 500kV监控系统安装
B83: 9 | C83: 消防系统安装 | D83: 1套 | E83: 200,000.00 元/套 | F83: 200000 | G83: 500kV消防系统安装
B84: 10 | C84: 通信系统安装 | D84: 1套 | E84: 300,000.00 元/套 | F84: 300000 | G84: 500kV通信系统安装
B85: 合计 | C85: - | D85: - | E85: - | F85: =SUM(F75:F84) -> 11900000 | G85: -

Sheet 投资构成
C4: 此色块为参数设定 | D4: 吉尔吉斯斯坦780MW/600MW光伏电站投资构成（含500kv变电站） | J4: 运费(1500公里，4300元/吨) | L4: 准备 | M4: 空间
C5: 项目类别 | D5: 项目名称 | E5: 单位 | F5: 数量 | G5: 单价（元） | H5: 总价（万元） | I5: 备注 | J5: 重量(吨) | K5: 运费 | M5: 单价上浮 | N5: 金额(万)
M6: 当地成立公司采购
C7: 发电设备 | D7: ="光伏组件（共 "&TEXT(ROUNDUP($F$7/MID($I$7,7,3),0),"###,#0")&" 块）" -> 光伏组件（共 1,083,334 块） | E7: W | F7: 780000000 | G7: 0.75 | H7: =F7*G7/10000 -> 58500 | I7: 单块组件功率720W | J7: 500 | K7: =MID($J$4,11,4)*J7*$F$7/1000000/10/10000 -> 16770 | L7: 2024市场价 | M7: 0.08 | N7: =M7*F7/10000 -> 6240
D8: 逆变器(共台) | E8: W | F8: 780000000 | G8: 0.13 | H8: =F8*G8/10000 -> 10140 | I8: 单台8.8MW和6.6MW | J8: 25 | K8: =MID($J$4,11,3)*J8*$F$7/1000000/10/10000 -> 83.85 | L8: 2024市场价 | M8: 0.02 | N8: =M8*F8/10000 -> 1560
D9: 支架系统 | E9: W | F9: 780000000 | G9: 0.24 | H9: =F9*G9/10000 -> 18720 | J9: 400 | K9: =MID($J$4,11,3)*J9*$F$7/1000000/10/10000 -> 1341.6 | L9: 2024市场价 | M9: 0.03 | N9: =M9*F9/10000 -> 2340 | P9: =156000000/1083334 -> 143.99991
D10: 汇流箱 | E10: 台 | F10: 7800 | G10: 3000 | H10: =F10*G10/10000 -> 2340 | J10: 4 | K10: =MID($J$4,11,3)*J10*$F$7/1000000/10/10000 -> 13.416 | L10: 2024电网参考价 | M10: 500 | N10: =M10*F10/10000 -> 390
D11: 变压器 | E11: 台 | F11: 78 | G11: 580000 | H11: =F11*G11/10000 -> 4524 | J11: 32 | K11: =MID($J$4,11,3)*J11*$F$7/1000000/10/10000 -> 107.328 | L11: 2024电网参考价 | M11: 40000 | N11: =M11*F11/10000 -> 312
D12: 配电柜及配电装置 | E12: 台 | F12: 78 | G12: 100000 | H12: =F12*G12/10000 -> 780 | J12: 10 | K12: =MID($J$4,11,3)*J12*$F$7/1000000/10/10000 -> 33.54 | L12: 2024电网参考价 | M12: 20000 | N12: =M12*F12/10000 -> 156
D13: 通讯及监控系统 | E13: 套 | F13: 30 | G13: 287000 | H13: =F13*G13/10000 -> 861 | J13: 2 | K13: =MID($J$4,11,3)*J13*$F$7/1000000/10/10000 -> 6.708 | L13: 2024电网参考价 | M13: 150000 | N13: =M13*F13/10000 -> 450
D14: 避雷系统 | E14: 套 | F14: 10 | G14: 287000 | H14: =F14*G14/10000 -> 287 | J14: 2 | K14: =MID($J$4,11,3)*J14*$F$7/1000000/10/10000 -> 6.708
D15: 电缆及附件 | E15: km | F15: 500 | G15: 358000 | H15: =F15*G15/10000 -> 17900 | J15: 55 | K15: =MID($J$4,11,3)*J15*$F$7/1000000/10/10000 -> 184.47 | M15: 10000 | N15: =M15*F15/10000 -> 500
D16: 发电设备小计 | E16: 万元 | H16: =SUM(H7:H15) -> 114052 | K16: =SUM(K7:K15) -> 18547.62 | M16: 合计 | N16: =SUM(N7:N15) -> 11948
C18: 发电场工程 | D18: 土建工程 | E18: W | F18: 780000000 | G18: 0.1 | H18: =F18*G18/10000 -> 7800 | L18: 单价暂定 | M18: 0.03 | N18: =M18*F18/10000 -> 2340
D19: 安装工程 | E19: W | F19: 780000000 | G19: =H19*10000/F19 -> 0.23833335 | H19: =H20+H21+H23 -> 18590.001 | M19: 0.03 | N19: =M19*F19/10000 -> 2340
D20: 组件安装 | E20: 块 | F20: =TEXT(ROUNDUP($F$7*10/MID($I$7,7,3),0),"###,#0") -> 10,833,334 | G20: 15 | H20: =F20*G20/10000 -> 16250.001 | L20: 单价暂定 | M20: 10 | N20: =F20*M20/10000 -> 10833.334
D21: 电气安装 | E21: MW | F21: =F7/1000000 -> 780 | G21: 18000 | H21: =F21*G21/10000 -> 1404 | L21: 单价暂定 | M21: 3000 | N21: =F21*M21/10000 -> 234
D22: 支架安装 | E22: 套 | F22: =TEXT(ROUNDUP($F$7*10/MID($I$7,7,3),0),"###,#0") -> 10,833,334 | G22: 15 | H22: =F22*G22/10000 -> 16250.001
D23: 调试和测试 | E23: MW | F23: =F7/1000000 -> 780 | G23: 12000 | H23: =F23*G23/10000 -> 936 | L23: 单价暂定 | M23: 3000 | N23: =F23*M23/10000 -> 234
D24: 场地平整 | E24: 亩 | F24: =假设及结论!G21*10000/666 -> 18509.009 | G24: 2000 | H24: =F24*G24/10000 -> 3701.8018 | L24: 单价暂定 | M24: 500 | N24: =M24*F24/10000 -> 925.45045
D25: 道路建设 | E25: km | F25: 120 | G25: 500000 | H25: =F25*G25/10000 -> 6000 | L25: 单价暂定 | M25: 300000 | N25: =F25*M25/10000 -> 3600
D26: 发电场工程小计 | E26: 万元 | H26: =SUM(H18:H25)-SUM(H20:H23) -> 36091.803 | M26: 合计 | N26: =SUM(N18:N25) -> 20506.784
J27: 吨/套（台）
C28: 500kv变电站设备 | D28: 500kV主变压器（1000MVA） | E28: 台 | F28: 2 | G28: 32000000 | H28: =F28*G28/10000 -> 6400 | J28: 300 | K28: =F28*J28*MID($J$4,11,4)/10000 -> 258 | L28: 2024电网参考价
D29: 500kV GIS组合电器 | E29: 套 | F29: 1 | G29: =H29*10000 -> 45000000 | H29: =SUM(H30:H34) -> 4500 | J29: {=SUMPRODUCT(F30:F34*J30:J34)} -> 156 | K29: =F29*J29*MID($J$4,11,4)/10000 -> 67.08 | L29: 2024电网参考价
D30: 500kV 断路器 | E30: 台 | F30: 6 | G30: 4000000 | H30: =F30*G30/10000 -> 2400 | J30: 8 | K30: =F30*J30*MID($J$4,11,4)/10000 -> 20.64 | L30: 2024电网参考价
D31: 500kV 隔离开关 | E31: 组 | F31: 12 | G31: 800000 | H31: =F31*G31/10000 -> 960 | J31: 5 | K31: =F31*J31*MID($J$4,11,4)/10000 -> 25.8 | L31: 2024电网参考价
D32: 500kV 电流互感器 | E32: 组 | F32: 6 | G32: 600000 | H32: =F32*G32/10000 -> 360 | J32: 3 | K32: =F32*J32*MID($J$4,11,4)/10000 -> 7.74 | L32: 2024电网参考价
D33: 500kV 电压互感器 | E33: 组 | F33: 6 | G33: 800000 | H33: =F33*G33/10000 -> 480 | J33: 4 | K33: =F33*J33*MID($J$4,11,4)/10000 -> 10.32 | L33: 2024电网参考价
D34: 500kV 避雷器 | E34: 组 | F34: 6 | G34: 500000 | H34: =F34*G34/10000 -> 300 | J34: 1 | K34: =F34*J34*MID($J$4,11,4)/10000 -> 2.58 | L34: 2024电网参考价
D35: 500kV 母线及支持设备 | E35: 套 | F35: 1 | G35: 5000000 | H35: =F35*G35/10000 -> 500 | J35: 30 | K35: =F35*J35*MID($J$4,11,4)/10000 -> 12.9 | L35: 2024电网参考价
D36: 无功补偿装置（SVC/STATCOM） | E36: 套 | F36: 1 | G36: 30000000 | H36: =F36*G36/10000 -> 3000 | J36: 100 | K36: =F36*J36*MID($J$4,11,4)/10000 -> 43 | L36: 2024电网参考价
D37: 220kV 配电设备（断路器、母线等） | E37: 套 | F37: 1 | G37: 25000000 | H37: =F37*G37/10000 -> 2500 | J37: 25 | K37: =F37*J37*MID($J$4,11,4)/10000 -> 10.75 | L37: 2024电网参考价
D38: 110kV 配电设备（断路器、母线等） | E38: 套 | F38: 1 | G38: 15000000 | H38: =F38*G38/10000 -> 1500 | J38: 15 | K38: =F38*J38*MID($J$4,11,4)/10000 -> 6.45 | L38: 2024电网参考价
D39: 变电站继电保护系统 | E39: 套 | F39: 1 | G39: 200000 | H39: =F39*G39/10000 -> 20 | J39: 8 | K39: =F39*J39*MID($J$4,11,4)/10000 -> 3.44 | L39: 2024电网参考价
D40: 自动化控制系统 | E40: 套 | F40: 1 | G40: 10000000 | H40: =F40*G40/10000 -> 1000 | J40: 5 | K40: =F40*J40*MID($J$4,11,4)/10000 -> 2.15 | L40: 2024电网参考价
D41: 变电站消防系统 | E41: 套 | F41: 1 | G41: 5000000 | H41: =F41*G41/10000 -> 500 | J41: 4 | K41: =F41*J41*MID($J$4,11,4)/10000 -> 1.72 | L41: 2024电网参考价
D42: 站用变压器（35kV/10kV） | E42: 台 | F42: 2 | G42: 2000000 | H42: =F42*G42/10000 -> 400 | J42: 12 | K42: =F42*J42*MID($J$4,11,4)/10000 -> 10.32 | L42: 2024电网参考价
D43: 升压站设备小计 | E43: 万元 | H43: =SUM(H28:H42)-H29 -> 20320 | K43: =SUM(K28:K42)-K29 -> 415.81
C45: 500kv变电站土建工程 | D45: 变电站建筑工程 | E45: 平方米 | F45: 8000 | G45: 7000 | H45: =F45*G45/10000 -> 5600 | L45: 单价暂定 | M45: 2000 | N45: =M45*F45/10000 -> 1600
D46: 设备基础 | E46: 套 | F46: 1 | G46: 20000000 | H46: =F46*G46/10000 -> 2000 | L46: 单价暂定 | M46: 5000000 | N46: =M46*F46/10000 -> 500
D47: 站区道路及排水 | E47: 套 | F47: 1 | G47: 10000000 | H47: =F47*G47/10000 -> 1000 | L47: 单价暂定 | M47: 2000000 | N47: =M47*F47/10000 -> 200
D48: 站区围墙及安保设施 | E48: 套 | F48: 1 | G48: 5000000 | H48: =F48*G48/10000 -> 500 | L48: 单价暂定 | M48: 1000000 | N48: =M48*F48/10000 -> 100
D49: 电缆沟及电缆敷设 | E49: 套 | F49: 1 | G49: 8000000 | H49: =F49*G49/10000 -> 800 | L49: 单价暂定 | M49: 2000000 | N49: =M49*F49/10000 -> 200
D50: 变电站土建工程小计 | E50: 万元 | H50: =SUM(H45:H49) -> 9900 | M50: 合计： | N50: =SUM(N45:N49) -> 2600
C52: 500kv变电站送出工程 | D52: 500kV 输电线路（架空线） | E52: 公里 | F52: 5 | G52: 5100000 | H52: =F52*G52/10000 -> 2550 | L52: 2024电网参考价 | M52: 500000 | N52: =M52*F52/10000 -> 250
D53: 铁塔及基础 | E53: 基 | F53: 28 | G53: 1500000 | H53: =F53*G53/10000 -> 4200 | L53: 2024电网参考价 | M53: 300000 | N53: =M53*F53/10000 -> 840
D54: 导线（双回路） | E54: 公里 | F54: 14 | G54: 800000 | H54: =F54*G54/10000 -> 1120 | L54: 2024电网参考价 | M54: 50000 | N54: =M54*F54/10000 -> 70
D55: 光缆及通信系统 | E55: 公里 | F55: 7 | G55: 300000 | H55: =F55*G55/10000 -> 210 | L55: 2024电网参考价 | M55: 40000 | N55: =M55*F55/10000 -> 28
D56: 施工及安装费用 | E56: 套 | F56: 1 | G56: 2000000 | H56: =F56*G56/10000 -> 200 | L56: 2024电网参考价 | M56: 400000 | N56: =M56*F56/10000 -> 40
D57: 变电站送出工程小计 | E57: 万元 | H57: =SUM(H52:H56) -> 8280 | M57: 合计： | N57: =SUM(N52:N56) -> 1228
C59: 其他 | D59: 并网费用 | E59: 项 | F59: 1 | G59: 10000000 | H59: =F59*G59/10000 -> 1000
D60: 建设期保险费用 | E60: 年 | F60: 2 | G60: 800000 | H60: =F60*G60/10000 -> 160
D61: 不可预见费 | E61: 项 | F61: 1 | G61: 20000000 | H61: =F61*G61/10000 -> 2000
H62: =F62*G62/10000 -> 0
D63: 其他小计 | E63: 万元 | H63: =SUM(H59:H62) -> 3160
C65: 前期费用 | D65: 可行性研究 | E65: 项 | F65: 1 | G65: 1400000 | H65: =F65*G65/10000 -> 140 | L65: 委托协议 | M65: 原单价已考虑
D66: 环境评估 | E66: 项 | F66: 1 | G66: 1000000 | H66: =F66*G66/10000 -> 100 | L66: 委托协议 | M66: 原单价已考虑
D67: 项目审批 | E67: 项 | F67: 1 | G67: 400000 | H67: =F67*G67/10000 -> 40 | L67: 委托协议 | M67: 原单价已考虑
D68: 设计及咨询 | E68: 项 | F68: 1 | G68: 30000000 | H68: =F68*G68/10000 -> 3000 | L68: 委托协议 | M68: 原单价已考虑
D69: 前期费用小计 | E69: 万元 | H69: =SUM(H65:H68) -> 3280
C71: 建设管理费
D72: 项目建设用地费 | E72: 项 | F72: 1 | G72: 50
D73: 项目建设管理费 | E73: w | F73: 780000000 | G73: 0.17 | H73: =G73*$F$84/10000 -> 13260
D74: 工程前期费 | G74: 2658
D75: 工程建设管理费 | G75: 2957
D76: 工程建设监理费 | G76: 1088
D77: 咨询服务费 | G77: 648
D78: 项目技术经济评审费 | G78: 382
D79: 工程质量检查检测费 | G79: 277
D80: 项目验收费 | G80: 868
D81: 工程保险费 | G81: 541
D82: 土地补偿款 | E82: 万元 | F82: 1 | G82: =假设及结论!K21*10000 -> 335294.4 | H82: =F82*G82/10000 -> 33.52944
E83: 万元 | H83: =H70+H73 -> 13260
C84: 开发服务费/咨询费 | D84: 开发服务费/咨询服务 | E84: w | F84: 780000000 | G84: 0.2 | H84: =G84*$F$84/10000 -> 15600 | L84: 资源方开发协议， 与投资人沟通形式
D85: 管理服务协议 | E85: w | G85: 0.05 | H85: =G85*$F$84/10000 -> 3900 | L85: 管理服务协议，与投资人沟通形式
D86: 开发服务费/咨询服务小计 | E86: 万元 | H86: =H84+H85 -> 19500
C88: 合计 | D88: 总投资(含运费) | E88: =H88+K88 -> #REF! | G88: 总投资(不含运费) | H88: =#REF!+H16+H26+H43+H50+H57+H63+H69+H83+H86 -> #REF! | J88: 运费合计 | K88: =K16+K43 -> 18963.43 | M88: 总计空间 | N88: =#REF!+N16+N26+N43+N50+N57+N63+N69+N72+N86 -> #REF!
C99: 建筑工程费
C100: 安装工程费
C101: 设备购置费

Sheet 600MW管理总包造价
B2: 吉尔吉斯斯坦巴特肯州巴特肯区阿克塔特尔600兆瓦光伏发电项目管理型总承包报价表 The Quotation for EPCM for 600MW Photovoltaic Power Generation Projectin Aktatyr, Batken District, Batken Region the Kyrgyz Republic
B3: 序号 No. | C3: 项目名称 Item Name | D3: 型号规格 Model / Specification | E3: 单位 Unit | F3: 数量 Quantity | G3: 单价 (人民币:元) Unit Price (RMB: yuan) | H3: 合价 (人民币:万元) Combined price (RMB10K Yuan) | I3: 税金 (tax)
B4: 一 I | C4: Akyraan Energy Corporation Limited
B5: 1 | C5: PPA手续办理、电力接入办理 PPA procedure handling, power access handling | D5: 600MW/750MWp | E5: Wp | F5: 750000000 | G5: 0.02 | H5: =F5*G5/10000 -> 1500 | I5: 所有税金(境内境外)、报关费、管理费、利润均包含在单价和合价之内。 Al1 taxes (domestic and overseas), customs clearance fees, management fees, and profits are in the unit price and total price.
B6: 2 | C6: 项目所需征林征地费用(包含临建、管理人员宿舍、料场等项目建设期问所需占用红线外的土地的协调及租赁)，项目红线内的场地清理平整与征林征(草)地，及附着物的清赔。项目红线内障碍物的迁移及赔偿。 The expenses required for forest and land acquisition for the project (including oordination and leasing of land outside the red line required for temporary construction, material storage, and other project construction during the project period),site clearance and leveling within the project red line, forest (grass) landacquisition, and compensation for attachments. Relocation and compensation for obstacles within the project boundary line. | D6: 600MW/750MWp | E6: Wp | F6: 750000000 | G6: 0.1 | H6: =F6*G6/10000 -> 7500
B7: 3 | C7: 施工许可办理 Handling of construction permits | D7: 600MW/750MWp | E7: Wp | F7: 750000000 | G7: 0.005 | H7: =F7*G7/10000 -> 375
B8: 4 | C8: 并网发电手续办理，并网发电通过审批。整个电站所有调试试验费用(同时满足中国及本地验收标准) Handling procedures for grid-connected power generation, and obtaining approval for grid-connected power generation. All commissioning and testing expenses for the entire power station (meeting both Chinese and local acceptance standards) | D8: 600MW/750MWp | E8: Wp | F8: 750000000 | G8: 0.01 | H8: =F8*G8/10000 -> 750
B9: 5 | C9: 项目验收手续办理，消防验收手续办理，综合楼房产证办理 Handling of project acceptance procedures, handling of fire safety acceptance procedures, and handling of property ownership certificate for the complex building | D9: 600MW/750MWp | E9: Wp | F9: 750000000 | G9: 0.005 | H9: =F9*G9/10000 -> 375
B10: 6 | C10: 用工合规性手续办理，无人驾驶民用航空器(无人机)使用许可证 Handling of employment compliance rocedures, and obtaining a usage license for unmanned civil aircraft (drones) | D10: 600MW/750MWp | E10: Wp | F10: 750000000 | G10: 0.005 | H10: =F10*G10/10000 -> 375
B11: 7 | C11: 对端电站的设计及改造 Design and renovation of the opposite-end ower station | D11: 600MW/750MWp | E11: Wp | F11: 750000000 | G11: 0.02 | H11: =F11*G11/10000 -> 1500
B12: 8 | C12: 项目必需的所有道路建设，进场道路于续办理 All necessary road construction for the project,Handling of access road procedures | D12: 600MW/750MWp | E12: Wp | F12: 750000000 | G12: 0.01 | H12: =F12*G12/10000 -> 750
B13: 9 | C13: 项目红线内的水保设施建设 Construction of water and soil conservation facilities within the project boundary | D13: 600MW/750MWp | E13: Wp | F13: 750000000 | G13: 0.01 | H13: =F13*G13/10000 -> 750
B14: 10 | C14: 其他项目所需的所有上述未列明的政府手续办理 Handling all the aforementioned government procedures not listed, which are required for other projects | D14: 600MW/750MWp | E14: Wp | F14: 750000000 | G14: 0.01 | H14: =F14*G14/10000 -> 750
B15: 11 | C15: 交通费等 Transportation fees,etc | F15: 750000000 | G15: 0.005 | H15: =F15*G15/10000 -> 375
B16: 12 | C16: 小计(一) Total (1) | H16: =SUM(H5:H15) -> 15000
B17: 二 II | C17: Kyrgyzstan New Energy Co.ltd
B18: 1 | C18: 项目防洪设施 Flood control facilities withinthe project | D18: 600MW/750MWp | E18: Wp | F18: 750000000 | G18: 0.03 | H18: =F18*G18/10000 -> 2250 | I18: 所有税金(境内境外)、报关费、管理费、利润均包含在单价和合价之内。 Al1 taxes (domestic and overseas), customs clearance fees, management fees, and profits are in the unit price and total price.
B19: 2 | C19: 项目红线范围内(外)的供水设施及6处清洗用水设施 Water supply facilities within (and outside) the project boundary line, as well as six water storage facilities for cleaning purposes | D19: 600MW/750MWp | E19: Wp | F19: 750000000 | G19: 0.02 | H19: =F19*G19/10000 -> 1500
B20: 3 | C20: 光伏场区围栏 Fence of photovoltaic field area | D20: 600MW/750MWp | E20: Wp | F20: 750000000 | G20: 0.02 | H20: =F20*G20/10000 -> 1500
B21: 4 | C21: 光伏支架桩打桩及箱逆变一体机基础打桩 Pile driving for photovoltaic support and foundation piling for box-type inverter ntegrated machine | D21: 600MW/750MWp，抗15级强风，GPS高精度自动定位打桩系统 Anti level 15 strong wind, GPS high-precision automatic positioning pile driving system | E21: Wp | F21: 750000000 | G21: 0.1 | H21: =F21*G21/10000 -> 7500
B22: 5 | C22: 升压站土建工程、装饰装修工程 Civil engineering and decoration works for the booster station | D22: 600MW/750MWp，管理楼、电控 楼及所有设备基础等 Management building, electrical control building, and all equipment foundations, etc | E22: Wp | F22: 750000000 | G22: 0.03 | H22: =F22*G22/10000 -> 2250
B23: 6 | C23: 储能站土建工程、装饰装修工程(包含储能预留区域的场平及砂石覆盖) Civil engineering and decoration works for the energy storage station (including site leveling and sand and gravel covering for the reserved energy storage area) | D23: 180MW/360MWh+180MW/360MWH | E23: Wp | F23: 750000000 | G23: 0.02 | H23: =F23*G23/10000 -> 1500
B24: 7 | C24: 消防水池、隔油池工程 Fire pool and oil separator project | D24: 600MW/750MWp，360MW/360MWH | E24: Wp | F24: 750000000 | G24: 0.01 | H24: =F24*G24/10000 -> 750
B25: 8 | C25: 升压站、储能站外围工程 Peripheral works of booster station and energy storage station | D25: 600MW/750MWp，360MW/360MWH ，场平、道路、围墙、大门等 Field leveling, roads, walls, gates, etc | E25: Wp | F25: 750000000 | G25: 0.01 | H25: =F25*G25/10000 -> 750
B26: 9 | C26: 外线塔基工程(含征地) External line tower foundation project (including land acquisition) | D26: 600MW/750MWp | E26: Wp | F26: 750000000 | G26: 0.02 | H26: =F26*G26/10000 -> 1500
B27: 10 | C27: 运维车辆、施工辅助机械、备品备件 Operation and maintenance vehicles, construction auxiliary machinery, spare parts | D27: 600MW/750MWp | E27: Wp | F27: 750000000 | G27: 0.02 | H27: =F27*G27/10000 -> 1500
B28: 11 | C28: 临水临电、临建、管理人员宿舍、办公网络工程 Temporary water and electricity supply, temporary construction, and office network engineering | D28: 600MW/750MWp | E28: Wp | F28: 750000000 | G28: 0.01 | H28: =F28*G28/10000 -> 750
B29: 12 | C29: 35KV首批并网发电接入工程 The first batch of 35KV grid-connected power generation access project | D29: 600MW/750MWp | E29: Wp | F29: 750000000 | G29: 0.03 | H29: =F29*G29/10000 -> 2250
B30: 13 | C30: 1MWp样板区建设 Construction of 1MWp demonstration area | D30: 600MW/750MWp | E30: Wp | F30: 750000000 | G30: 0.005 | H30: =F30*G30/10000 -> 375
... B33: 16 | C33: 全项目用工合规性手续办理 Handling of compliance procedures for the entire project's employment | D33: 600MW/750MWp | E33: Wp | F33: 750000000 | G33: 0.02 | H33: =F33*G33/10000 -> 1500
B34: 17 | C34: 运费 Freight | E34: Wp | F34: 750000000 | G34: 0.01 | H34: =F34*G34/10000 -> 750
B35: 18 | C35: 现场管理费 Management fee | E35: Wp | F35: 750000000 | G35: 0.02 | H35: =F35*G35/10000 -> 1500
B36: 19 | C36: 交通费等 Transportation fees, etc | E36: Wp | F36: 750000000 | G36: 0.01 | H36: =F36*G36/10000 -> 750
B37: 20 | C37: 合计(二) Total(II) | H37: =SUM(H18:H36) -> 38625
B38: 三 III | C38: 华松电力集团股份有限公司
B39: 1 | C39: 主变压器(包括但不限于中性点成套装置、排油注氮灭火装置等附属配置) Main transformer (including but not limited to auxiliary configurations such as neutral point complete equipment, oil discharge and nitrogen injection fire extinguishing device, etc.) | D39: 600MW/750MWp，500KV | E39: Wp | F39: 750000000 | G39: 0.037 | H39: =F39*G39/10000 -> 2775 | I39: 所有税金(境内境外)、报关费、管理费、利润均包含在单价和合价之内。 Al1 taxes (domestic and overseas), customs clearance fees, management fees, and profits are in the unit price and total price.
B40: 2 | C40: SVG系统(成套装置) SVG system(Complete equipment) | D40: 600MW/750MWp，500KV | F40: 750000000 | G40: 0.011 | H40: =F40*G40/10000 -> 825
B41: 3 | C41: GIS系统(或AIS系统)(包括但不限于附属的出线套管支撑件、旁路隔离开关支撑件、汇控柜槽盒、避雷器支架、基础等等) GIS system (or AIS system)(Including but not limited to supporting components such as auxiliary outgoing conduit, bypass isolation switch, control cabinet tray, lightning arrester bracket, foundation, etc) | D41: 600MW/750MWp，500KV | E41: Wp | F41: 750000000 | G41: 0.015 | H41: =F41*G41/10000 -> 1125
B42: 4 | C42: 钢构架及避雷针 Steel frame and lightning rod | D42: 600MW/750MWp，500KV | E42: Wp | F42: 750000000 | G42: 0.004 | H42: =F42*G42/10000 -> 300
B43: 5 | C43: 高压系统(包括但不限于氧化锌避雷器、电压互感器、电流互感器、耦合电容器、阻波器、隔离开关、接地开关、高压开关、35kV开关柜、预制舱室、接地变及小电阻成套装置、母线、导体和导线(线缆)、金具、套管、支柱绝缘子、防雷接地系统、防孤岛保护装置、备品备件等等) High voltage system(including but not limited to zinc oxide lightning arresters, voltage transformers, current transformers, coupling capacitors, wave blockers, isolating switches, high voltage switches,35kV switchgear, prefabricated cabins, grounding transformers and small resistance complete sets of equipment, busbars, conductors and wires, fittings, lightning protection grounding systems, etc.) | D43: 600MW/750MWp，500KV | E43: Wp | F43: 750000000 | G43: 0.02 | H43: =F43*G43/10000 -> 1500
B44: 6 | C44: 中压开关及配电箱(柜)(包括但不限于氧化锌避雷器、电压互感器、电流互感器、耦合电容器、阻波器、隔离开关、接地开关、高压开关、35kV开关柜、预制舱室、接地变及小电阻成套装置、母线、导体和导线(线缆)、金具、套管、支柱绝缘子、夹具、防雷接地系统、防孤岛保护装置、备品备件等等) Medium voltage switch and distribution box (cabinet).(including but not limited to zinc oxide lightning arresters, voltage transformers, current transformers, coupling capacitors, wave blockers, isolating switches, high voltage switches, 35kV switchgear, prefabricated cabins, grounding transformers and small resistance complete sets of equipment, busbars, conductors and wires, fittings, lightning protection grounding systems, etc.) | D44: 600MW/750MWp，35KV | E44: Wp | F44: 750000000 | G44: 0.013 | H44: =F44*G44/10000 -> 975
B45: 7 | C45: 站用变系统(包括但不限于:站用变、400V交流屏柜、柴油发电机、双电源切换装置，对应线缆、桥架、防雷接地等等) Station transformer system (including but not limited to: station transformer,400V AC cabinet, diesel generator, dualpower switching device,corresponding cable tray, etc.) | D45: 600MW/750MWp，35KV/400V | E45: Wp | F45: 750000000 | G45: 0.008 | H45: =F45*G45/10000 -> 600
B46: 8 | C46: 二次系统(包括但不限于二次仓、符合当地国家电网要求的各种综合保护系统 、监控系统，满足电网验收要求的调度 、通讯、自动化系统;以及当地电力部门要求的其他相关内容。上述系统所需的各种设备、材料包括但不限于各种装置(如ECA 设备等)、仪表、电源、服务器、线缆、工作站、软件等等。 Secondary equipment (including but not limited to secondary warehouses, various omprehensive protection systems that meet the requirements of the local national power grid, dispatch, comunication, and automation systems that meet the acceptance requirements of the power grid; and other related content required by the local power department) | D46: 600MW/750MWp，500KV/35KV | E46: Wp | F46: 750000000 | G46: 0.035 | H46: =F46*G46/10000 -> 2625
B47: 9 | C47: 送出线路(包括但不限于塔材、塔材附件、导线、电缆、通讯线(如1OPGW光缆等)、各种金具、绝缘子、夹具、监测装置、测温装置、防雷接地(含塔体基础部分)等等材料设备的采购安装、调试、测试、验收等) Send out the line (Including but not limited to the procurement, installation, commissioning, testing, and acceptance of materials and equipment such as tower mterials, tower accessories, wiren, cables, communication linen (such as OPGW optical cablen), various fittings, insulators,fixtures, monitoring devices, temperature measuring devices, lightning protection and grounding (including tower foundation parts), etc) | D47: 600MW/750MWp，500KV | E47: Wp | F47: 750000000 | G47: 0.0267 | H47: =F47*G47/10000 -> 2002.5
B48: 10 | C48: 光伏区35kV集电线路 10 Current collection line in photovoltaic area | D48: 600MW/750MWp，35KV | E48: Wp | F48: 750000000 | G48: 0.03 | H48: =F48*G48/10000 -> 2250
B49: 11 | C49: 升压站及送出工程的全部勘察设计，图纸翻译，包含中国具有资质的第三方设计咨询单位审图并审图合格及设计图纸的公证 All survey and design of the booster station and transmission project, translation of drawings, including review and approval of drawings by qualified third-party design consulting firms in China, and notarization of design drawings | D49: 600MW/750MWp | E49: Wp | F49: 750000000 | G49: 0.011 | H49: =F49*G49/10000 -> 825
B50: 12 | C50: 通信工程 Communication Engineering | D50: 600MW/750MWp，500KV | E50: Wp | F50: 750000000 | G50: 0.013 | H50: =F50*G50/10000 -> 975
B51: 13 | C51: 变电站站内所有安装工程(含材料) All installation works (including materials) within the substation | D51: 600MW/750MWp | E51: Wp | F51: 750000000 | G51: 0.033 | H51: =F51*G51/10000 -> 2475
B52: 14 | C52: 送出线路所有安装工程(含材料) All installation works (including materials) for the transmission line | D52: 600MW/750MWp | E52: Wp | F52: 750000000 | G52: 0.008 | H52: =F52*G52/10000 -> 600
... B60: 21 | C60: 满足并网发电验收条件的其他工程(包括但不限于国内工厂监造及材料出厂试验) Other projects that meet the acceptance criteria for grid connected power generation (Includi ng but not limited to domestic factory upervision and material factory testing) | D60: 600MW/750MWp | E60: Wp | F60: 750000000 | G60: 0.013 | H60: =F60*G60/10000 -> 975
B61: 22 | C61: 运费 Freight | E61: Wp | F61: 750000000 | G61: 0.027 | H61: =F61*G61/10000 -> 2025
B62: 23 | C62: 现场管理费 Management fee | E62: Wp | F62: 750000000 | G62: 0.01 | H62: =F62*G62/10000 -> 750
B63: 24 | C63: 签证费、交通费等 Visa fees, transportation fees, etc | E63: Wp | F63: 750000000 | G63: 0.008 | H63: =F63*G63/10000 -> 600
B64: 25 | C64: 合计(三) Total(III) | H64: =SUM(H39:H63) -> 28005
B65: 四 IV | C65: 天津十一中际科技有限公司
B66: 1 | C66: 组件(损耗率按1%计算) Photovoltaic modules (The loss rate is calculated at 1%) | D66: 720Wp双面双玻单晶硅光伏组 件、满足IEC标准/TUV认证。 720Wp double-sided double glass monocrystalline silicon photovoltaic module, meeting IEC standards/TUV certification. | E66: Wp | F66: 202000000 | G66: 0.7 | H66: =F66*G66/10000 -> 14140 | I66: 所有税金(境内境外)、报关费、管理费、利润均包含在单价和合价之内。 Al1 taxes (domestic and overseas), customs clearance fees, management fees, and profits are in the unit price and total price.
B67: 2 | C67: 下部支架桩基础采购(损耗率按1%计算) The bottom bracket pile foundation (The loss rate is calculated at 1%) | D67: 下部支架钢管桩基础采购 The bottom bracket steel pile foundation | E67: Wp | F67: 757500000 | G67: 0.1 | H67: =F67*G67/10000 -> 7575
B68: 3 | C68: 上部支架(损耗率按1%计算) The top bracket (The loss rate is calculated at 1%) | E68: Wp | F68: 202000000 | G68: 0.22 | H68: =F68*G68/10000 -> 4444
B69: 4 | C69: 线缆(损耗率按1%计算) Cables (The loss rate is calculated at 1%) | D69: 光伏电缆(铜1*4mm)、低压直流(铝合金)、高压电缆(铝合金)、光纤 Photovoltaic cable (copper 1*4mm2)， low voltage DC (aluminum alloy), high voltage cable (aluminum alloy),optical fiber | E69: Wp | F69: 202000000 | G69: 0.16 | H69: =F69*G69/10000 -> 3232
B70: 5 | C70: 汇流箱(损耗率按1%计算) Combiner box (The loss rate is calculated at2%) | D70: 智能防雷汇流箱 Intelligent lightning protection combiner box | E70: Wp | F70: 202000000 | G70: 0.02 | H70: =F70*G70/10000 -> 404
B71: 6 | C71: 箱逆变一体机 Integrated box-type transformer and inverter | D71: 35kV、IP65、效率大于99%、满足IEC标准/TUV认证 35kV，IP65, with efficiency greater than 99%, meeting the IEC standard /TUV certification | E71: Wp | F71: 200000000 | G71: 0.2 | H71: =F71*G71/10000 -> 4000
B72: 7 | C72: 储能设备采购费 Energy storage equipment fee | D72: 180MW/360MWh | E72: MWh | F72: 360 | G72: 600000 | H72: =F72*G72/10000 -> 21600
B73: 8 | C73: 运费 Freight | E73: Wp | F73: 202000000 | G73: 0.09 | H73: =F73*G73/10000 -> 1818
B74: 9 | C74: 储能设备运输 Energy storage equipment Freight fee | D74: 180MW/360MWh | E74: MWh | F74: 360 | G74: 22000 | H74: =F74*G74/10000 -> 792
B75: 10 | C75: 合计(四) Total(IV) | H75: 58005
B76: 五 V | C76: 中国地质工程集团有限公司
B77: 1 | C77: 组件(损耗率按1%计算) Photovoltaic modules (The loss rate is calculated at 1%) | D77: 720Wp双面双玻单晶硅光伏组件、满足IEC标准/TUV认证。 720Wp double-sided double glass monocrystalline silicon photovoltaic module, meeting IEC standards/TUV certification. | E77: Wp | F77: 171700000 | G77: 0.7 | H77: =F77*G77/10000 -> 12019 | I77: 所有税金 境内境外) 、报关费、管理费、和 润均包含在 单价和合价 之内. All taxes (domestic and overseas), customs clearance fees, management fees, and profits are included in the unit price and total price
B78: 2 | C78: 上部支架(损耗率按1%计算) The top bracket (The loss rate is calculated at 1%) | E78: Wp | F78: 171700000 | G78: 0.22 | H78: =F78*G78/10000 -> 3777.4
B79: 3 | C79: 线缆(损耗率按1%计算) Cables (The loss rate is calculated at 1%) | D79: 光伏电缆(铜1*4mm)、低压直流(铝合金)、高压电缆(铝合金)、光纤 Photovoltaic cable (copper 1*4mm2)， 1ow voltage DC (aluminum alloy), high voltage cable (aluminum alloy),optical fiber | E79: Wp | F79: 171700000 | G79: 0.16 | H79: =F79*G79/10000 -> 2747.2
B80: 4 | C80: 汇流箱(损耗率按1%计算) Combiner box (The loss rate is calculated at 1%) | D80: 智能防雷汇流箱 Intelligent lightning protection combiner box | E80: Wp | F80: 171700000 | G80: 0.02 | H80: =F80*G80/10000 -> 343.4
B81: 5 | C81: 箱逆变一体机 Integrated box-type transformer and inverter | D81: 35kV、IP65、效率大于99%、满足IEC标准/TUV认证 35kV,IP65, with efficiency greater than 99%, meeting the IEC standard /TUV certification | E81: Wp | F81: 170000000 | G81: 0.2 | H81: =F81*G81/10000 -> 3400
B82: 6 | C82: 运费 Freight | E82: Wp | F82: 171700000 | G82: 0.09 | H82: =F82*G82/10000 -> 1545.3
B83: 7 | C83: 合计(五) Total(V) | H83: =SUM(H77:H82) -> 23832.3
B84: 六 VI | C84: 中材节能股份有限公司
B85: 1 | C85: 组件(损耗率按1%计算) Photovoltaic modules (The loss rate is calculated at 1%) | D85: 720Wp双面双玻单晶硅光伏组件、满足IEC标准/TUV认证。 720Wp double-sided double glass monocrystalline silicon photovoltaic module, meeting IEC standards/TUV certification. | E85: Wp | F85: 383800000 | G85: 0.7 | H85: =F85*G85/10000 -> 26866 | I85: 所有税金(境内境外)、报关费、管理费、利润均包含在单价和合价之内。 Al1 taxes (domestic and overseas), customs clearance fees, management fees, and profits are in the unit price and total price.
B86: 2 | C86: 上部支架(损耗率按1%计算) The top bracket (The loss rate is calculated at 1%) | E86: Wp | F86: 383800000 | G86: 0.22 | H86: =F86*G86/10000 -> 8443.6
B87: 3 | C87: 线缆(损耗率按1%计算) Cables (The loss rate is calculated at 1%) | D87: 光伏电缆(铜1*4mm2)、低压直流(铝合金)、高压电缆(铝合金)、光纤 Photovoltaic cable (copper 1*4mm2), low voltage DC (aluminum alloy),high voltage cable (aluminum alloy), optical fiber | E87: Wp | F87: 383800000 | G87: 0.16 | H87: =F87*G87/10000 -> 6140.8
B88: 4 | C88: 汇流箱(损耗率按1%计算) Combiner box (The loss rate is calculated at 1%) | D88: 智能防雷汇流箱 Intelligent lightning protection combiner box | E88: Wp | F88: 383800000 | G88: 0.02 | H88: =F88*G88/10000 -> 767.6
B89: 5 | C89: 箱逆变一体机 Integrated box-type transformer and inverter | D89: 35kV、IP65、效率大于99%、满足IEC标准/TUV认证 35kV，IP65, with efficiency greater than 99%, meeting the IEC standard /TUV certification | E89: Wp | F89: 380000000 | G89: 0.2 | H89: =F89*G89/10000 -> 7600
B90: 6 | C90: 运费 Freight | E90: Wp | F90: 383800000 | G90: 0.09 | H90: =F90*G90/10000 -> 3454.2
B91: 7 | C91: 合计(六) Total (VI) | H91: =SUM(H85:H90) -> 53272.2
B92: 七 VII | C92: 信息产业电子第十一设计研究院科技工程股份有限公司
B93: 1 | C93: 主要设备材料采购费 Purchase cost of major equipment and materials | I93: 所有税金(境内境外)、报关费、管理费、利润均包含在单价和合价之内。 Al1 taxes (domestic and overseas), customs clearance fees, management fees, and profits are in the unit price and total price.
B94: 1.1 | C94: 箱逆变钢平台 Transformer&inverter steel platform | E94: Wp | F94: 750000000 | G94: 0.01 | H94: =F94*G94/10000 -> 750
B95: 1.2 | C95: 视频监控系统 Communication and video monitoring in PV area | E95: Wp | F95: 750000000 | G95: 0.01 | H95: =F95*G95/10000 -> 750
B96: 2 | C96: 安装工程 Construction of PV area
B97: 2.1 | C97: 下部支架桩调校 Alignment adjustment of lower support piles | E97: Wp | F97: 750000000 | G97: 0.03 | H97: =F97*G97/10000 -> 2250
B98: 2.2 | C98: 上部支架安装 Bracket installation | E98: Wp | F98: 750000000 | G98: 0.16 | H98: =F98*G98/10000 -> 12000
B99: 2.3 | C99: 组件安装 Modules installation | E99: Wp | F99: 750000000 | G99: 0.145 | H99: =F99*G99/10000 -> 10875
B100: 2.4 | C100: 汇流箱安装 Combiner box installation | E100: Wp | F100: 750000000 | G100: 0.02 | H100: =F100*G100/10000 -> 1500
B101: 2.5 | C101: 箱逆变一体机安装 Box transformer and inverter integrated machine installation | E101: Wp | F101: 750000000 | G101: 0.02 | H101: =F101*G101/10000 -> 1500
B102: 2.6 | C102: 电气安装 Electric installation | D102: 电缆敷设、接地系统等 Cable laying and grounding system etc. | E102: Wp | F102: 750000000 | G102: 0.17 | H102: =F102*G102/10000 -> 12750
B103: 2.7 | C103: 视频监控系统安装调试 Communication and video monitoring in PV area, Installation and commissioning | D103: 安装及调试 Installation and commissioning | E103: Wp | F103: 750000000 | G103: 0.006 | H103: =F103*G103/10000 -> 450
B104: 2.8 | C104: 设备材料的卸货和二次倒运 Unloading and secondary transportation of equipment and materials | E104: Wp | F104: 750000000 | G104: 0.01 | H104: =F104*G104/10000 -> 750
B105: 2.9 | C105: 现场安保管理及翻译 On site security management and translation | E105: Wp | F105: 750000000 | G105: 0.01 | H105: =F105*G105/10000 -> 750
B106: 2.1 | C106: 海关监管库 Customs Supervision Warehouse | E106: 项 Item | F106: 1 | G106: 5000000 | H106: =F106*G106/10000 -> 500
B107: 2.11 | C107: 箱逆变设备基础 Equipment foundation | E107: Wp | F107: 750000000 | G107: 0.01 | H107: =F107*G107/10000 -> 750
B108: 2.12 | C108: 施工辅材 Construction auxiliary material | D108: 桥架、线管、防火泥、防火封堵等 Cable Tray, line pipe, fire mud, fire sealing, etc. | E108: Wp | F108: 750000000 | G108: 0.05 | H108: =F108*G108/10000 -> 3750
B109: 2.13 | C109: 光伏区事故油池 Accident oil pool of photovoltaic area | E109: Wp | F109: 750000000 | G109: 0.01 | H109: =F109*G109/10000 -> 750
B110: 2.14 | C110: 安全文明措施费 Safety and civilization measures expense | E110: Wp | F110: 750000000 | G110: 0.01 | H110: =F110*G110/10000 -> 750
...

Sheet 边界条件
B2: 参数汇总表（不含储能投资）
B3: 序号 | C3: 项目 | D3: 单位 | E3: 数值 | F3: 备注
B4: 一 | C4: 工程概况
B5: 1 | C5: 光伏系统容量 | D5: MW | E5: =假设及结论!F13*10 -> 750 | F5: 直流侧容量
B6: 2 | C6: 工期 | D6: 月 | E6: 12
B7: 3 | C7: 项目运行期 | D7: 年 | E7: =假设及结论!H13 -> 25
B8: 二 | C8: 投资类参数
B9: 1 | C9: 单位千瓦静态投资 | D9: 元/kW | E9: =(假设及结论!C13-资金筹措!C8)/假设及结论!F13 -> 3311.1218 | F9: 不含储能
B10: 2 | C10: 静态投资 | D10: 万元 | E10: =假设及结论!C15 -> 247200 | F10: 不含储能
B11: 3 | C11: 动态投资 | D11: 万元 | E11: =假设及结论!C13 -> 251649.6 | F11: 不含储能
B12: 4 | C12: 资本金比例 | D12: % | E12: =假设及结论!Q30*100 -> 30
B13: 5 | C13: 可抵扣税金 | D13: 万元 | E13: =销售收入!C38 -> 0
B14: 6 | C14: 流动资金单位千瓦指标 | D14: 元/kW | E14: =MID(假设及结论!$B$32,18,2) -> 20
B15: 三 | C15: 成本类参数
B16: 1 | C16: 贷款情况
B17: 1.1 | C17: 银行1还款期限 | D17: 年 | E17: =假设及结论!O30 -> 15
C18: 还本付息方式 | E18: 等额还本利息照付
C19: 长期贷款利率 | D19: % | E19: =假设及结论!P30*100 -> 3.6
B20: 1.2 | C20: 流动资金贷款利率 | D20: % | E20: =假设及结论!N30*100 -> 3.45
B21: 2 | C21: 折旧
B22: 2.1 | C22: 光伏系统折旧年限 | D22: 年 | E22: =假设及结论!G33 -> 25 | F22: 税法规定
B23: 2.2 | C23: 光伏系统残值率 | D23: % | E23: =假设及结论!H33*100 -> 5
B24: 3 | C24: 光伏系统修理费 | D24: 元/kW | E24: =假设及结论!O24 -> 9.2
B25: 4 | C25: 光伏系统保险费 | D25: % | E25: 0 | F25: 运维已包含，暂未单独考虑
B26: 5 | C26: 人工成本
B27: 5.1 | C27: 定员标准 | D27: 人 | E27: =假设及结论!D21 -> 20
B28: 5.2 | C28: 人均年工资 | D28: 万元 | E28: =假设及结论!E21*(1+假设及结论!F21) -> 24.992
B29: 6 | C29: 材料费 | D29: 元/kW | E29: =假设及结论!M24 -> 10
B30: 7 | C30: 其他费用
B31: 7.1 | C31: 其他费用 | D31: 元/kW | E31: =假设及结论!Q24 -> 8.5 | H31: 实际
B32: 7.2 | C32: 租地费用（每年） | D32: 万元 | E32: =总成本!E10 -> 155.3202 | F32: =假设及结论!G21&"公顷，"&假设及结论!H21&"美元/公顷/年，共计租地"&假设及结论!G15&"年" -> 1232.7公顷，180美元/公顷/年，共计租地25年 | H32: 178
B33: 7.3 | C33: 一次性土地补偿费 | D33: 万元 | E33: =假设及结论!K21 -> 33.52944 | F33: =假设及结论!J21&"美元/公顷" -> 272美元/公顷 | H33: 272
B34: 四 | C34: 收益类参数
B35: 1 | C35: 首年利用小时数 | D35: h | E35: =假设及结论!I13 -> 1545 | F35: 第一年衰减1%，后续每年0.4%
B36: 2 | C36: 上网电价（不含增值税） | D36: 元/kWh | E36: =假设及结论!I15 -> 0.35 | F36: =TEXT(E36/假设及结论!I21,"##0.##0"&" 美分") -> 0.050 美分
C37: 电网公司收电力服务费 | D37: 元/kWh | E37: =假设及结论!M13 -> 0 | F37: 类似国内的辅助服务费，结算时需要在PPA中扣除
B38: 3 | C38: 增值税税率 | D38: % | E38: =假设及结论!H30 -> 0.12 | F38: 进口豁免征收。
B39: 4 | C39: 所得税税率 | D39: % | E39: =假设及结论!B30 -> 0.1 | F39: 在吉尔吉斯，称为“利润税”“利得税”，豁免
B40: 5 | C40: 城市维护建设税 | D40: % | E40: =假设及结论!F30 -> 0 | F40: 无
B41: 6 | C41: 教育费附加 | D41: % | E41: =假设及结论!G30 -> 0 | F41: 无
B42: 7 | C42: 增值税即征即退 | E42: 否
B43: 8 | C43: 所得税N免N减半 | E43: 无 | F43: 豁免
B44: 9 | C44: 补贴收入 | D44: 万元 | E44: 0
B45: ="注：汇率暂按 "&假设及结论!I21&" 考虑。" -> 注：汇率暂按 7 考虑。
B47: 根据吉尔吉斯共和国的税法（2022 年 1 月 18 日第 4 号）、吉尔吉斯共和国《巴特肯地区地位法 О статусе Баткенской области》（2021年9月10日113号）以及吉尔吉斯共和国内阁决议“关于批准税收优惠的工业活动优惠类型清单 Об утверждении перечня преференциальных видов промышленной деятельности, подлежащих льготному налогообложению”（2024 年 9 月 13 日第 571 号）的法律条款规定，投资者在巴特肯地区投资建设光伏发电设施，应该享受: 1. 进口货物增值税（税法297条第 1条第 20 款）; 2. 利得税（税法240条第3款）; 3. 销售税（税法364条第1条第5款）; 4.土地财产税（税法212条第13节第 1款 c 项）的豁免。

Sheet 损益表
A2: 利 润 和 利 润 分 配 表
W3: 单位:万元
A4: 序 | B4: 年份 名称 | C4: 合计 | D4: 建设经营期
A5: 号 | D5: 1 | E5: 2 | F5: 3 | G5: 4 | H5: 5 | I5: 6 | J5: 7 | K5: 8 | L5: 9 | M5: 10 | N5: 11 | O5: 12 | P5: 13 | Q5: 14 | R5: 15 | S5: 16 | T5: 17 | U5: 18 | V5: 19 | W5: 20 | X5: 21 | Y5: 22 | Z5: 23 | AA5: 24 | AB5: 25 | AC5: 26 | AD5: 27
A6: 1 | B6: 营业收入（不含增值税和销售税） | C6: =SUM(D6:AD6) -> 940024.39 | E6: =销售收入!E6 -> 39737.25 | F6: =销售收入!F6 -> 39339.878 | G6: =销售收入!G6 -> 39180.929 | H6: =销售收入!H6 -> 39021.98 | I6: =销售收入!I6 -> 38863.031 | J6: =销售收入!J6 -> 38704.082 | K6: =销售收入!K6 -> 38545.132 | L6: =销售收入!L6 -> 38386.183 | ... AD6: =销售收入!AD6 -> 0
A7: 2 | B7: 增值税实际收入 | C7: =SUM(D7:AD7) -> 0
A8: 3 | B8: 营业税金及附加 | C8: =SUM(D8:AD8) -> 9400.2439 | E8: =销售收入!E30 -> 397.3725 | F8: =销售收入!F30 -> 393.39878 | G8: =销售收入!G30 -> 391.80928 | H8: =销售收入!H30 -> 390.21979 | I8: =销售收入!I30 -> 388.63031 | J8: =销售收入!J30 -> 387.04082 | K8: =销售收入!K30 -> 385.45132 | L8: =销售收入!L30 -> 383.86183 | ... AD8: =销售收入!AD30 -> 0
A9: 4 | B9: 总成本费用 | C9: =SUM(D9:AD9) -> 345351.78 | D9: =总成本!D21 -> 0 | E9: =总成本!E21 -> 19840.658 | F9: =总成本!F21 -> 19395.106 | G9: =总成本!G21 -> 18949.556 | H9: =总成本!H21 -> 18504.008 | I9: =总成本!I21 -> 18058.463 | J9: =总成本!J21 -> 17879.366 | K9: =总成本!K21 -> 17433.825 | ... AD9: =总成本!AD21 -> 155.3202
A10: 5 | B10: 利润总额（1+2-3-4） | C10: =SUM(D10:AD10) -> 585272.37 | D10: =D6+D7-D8-D9 -> 0 | E10: =E6+E7-E8-E9 -> 19499.219 | F10: =F6+F7-F8-F9 -> 19551.373 | G10: =G6+G7-G8-G9 -> 19839.563 | H10: =H6+H7-H8-H9 -> 20127.751 | I10: =I6+I7-I8-I9 -> 20415.938 | J10: =J6+J7-J8-J9 -> 20437.674 | K10: =K6+K7-K8-K9 -> 20725.856 | ... AD10: =AD6+AD7-AD8-AD9 -> -155.3202
A11: 6 | B11: 税前弥补以前年度亏损 | C11: =SUM(D11:AD11) -> 0 | E11: =IF(AND(SUM($D$14:D$14)<0,E5<ConstructPeriod+5),SUM($D$14:D$14),0) -> 0 | F11: =IF(AND(SUM($D$14:E$14)<0,F5<ConstructPeriod+5),SUM($D$14:E$14),0) -> 0 | G11: =IF(AND(SUM($D$14:F$14)<0,G5<ConstructPeriod+5),SUM($D$14:F$14),0) -> 0 | H11: =IF(AND(SUM($D$14:G$14)<0,H5<ConstructPeriod+5),SUM($D$14:G$14),0) -> 0 | I11: =IF(AND(SUM($D$14:H$14)<0,I5<ConstructPeriod+5),SUM($D$14:H$14),0) -> 0 | J11: =IF(AND(SUM($D$14:I$14)<0,J5<ConstructPeriod+5),SUM($D$14:I$14),0) -> 0 | K11: =IF(AND(SUM($D$14:J$14)<0,K5<ConstructPeriod+5),SUM($D$14:J$14),0) -> 0 | L11: =IF(AND(SUM($D$14:K$14)<0,L5<ConstructPeriod+5),SUM($D$14:K$14),0) -> 0 | ... AD11: =IF(AND(SUM($D$14:AC$14)<0,AD5<ConstructPeriod+5),SUM($D$14:AC$14),0) -> 0
A12: 7 | B12: 应纳税所得额（5+6） | C12: =SUM(D12:AD12) -> 585427.69 | E12: =IF(E10+E11<0,0,E10+E11) -> 19499.219 | F12: =IF(F10+F11<0,0,F10+F11) -> 19551.373 | G12: =IF(G10+G11<0,0,G10+G11) -> 19839.563 | H12: =IF(H10+H11<0,0,H10+H11) -> 20127.751 | I12: =IF(I10+I11<0,0,I10+I11) -> 20415.938 | J12: =IF(J10+J11<0,0,J10+J11) -> 20437.674 | K12: =IF(K10+K11<0,0,K10+K11) -> 20725.856 | L12: =IF(L10+L11<0,0,L10+L11) -> 21014.036 | ... AD12: =IF(AD10+AD11<0,0,AD10+AD11) -> 0
A13: 8 | B13: ="所得税（"&假设及结论!B30*100&"%)"&" 减免"&假设及结论!D30&"年" -> 所得税（10%) 减免10年 | C13: =SUM(D13:AD13) -> 40251.406 | E13: =IF(假设及结论!$C$30="YES",IF(E5<=ConstructPeriod+3,0,IF(E5<=ConstructPeriod+6,E12*假设及结论!$B$30*0.5,E12*假设及结论!$B$30)),E12*IF(E5>10,假设及结论!$B$30,0)) -> 0 | F13: =IF(假设及结论!$C$30="YES",IF(F5<=ConstructPeriod+3,0,IF(F5<=ConstructPeriod+6,F12*假设及结论!$B$30*0.5,F12*假设及结论!$B$30)),F12*IF(F5>10,假设及结论!$B$30,0)) -> 0 | G13: =IF(假设及结论!$C$30="YES",IF(G5<=ConstructPeriod+3,0,IF(G5<=ConstructPeriod+6,G12*假设及结论!$B$30*0.5,G12*假设及结论!$B$30)),G12*IF(G5>10,假设及结论!$B$30,0)) -> 0 | H13: =IF(假设及结论!$C$30="YES",IF(H5<=ConstructPeriod+3,0,IF(H5<=ConstructPeriod+6,H12*假设及结论!$B$30*0.5,H12*假设及结论!$B$30)),H12*IF(H5>10,假设及结论!$B$30,0)) -> 0 | I13: =IF(假设及结论!$C$30="YES",IF(I5<=ConstructPeriod+3,0,IF(I5<=ConstructPeriod+6,I12*假设及结论!$B$30*0.5,I12*假设及结论!$B$30)),I12*IF(I5>10,假设及结论!$B$30,0)) -> 0 | J13: =IF(假设及结论!$C$30="YES",IF(J5<=ConstructPeriod+3,0,IF(J5<=ConstructPeriod+6,J12*假设及结论!$B$30*0.5,J12*假设及结论!$B$30)),J12*IF(J5>10,假设及结论!$B$30,0)) -> 0 | K13: =IF(假设及结论!$C$30="YES",IF(K5<=ConstructPeriod+3,0,IF(K5<=ConstructPeriod+6,K12*假设及结论!$B$30*0.5,K12*假设及结论!$B$30)),K12*IF(K5>10,假设及结论!$B$30,0)) -> 0 | L13: =IF(假设及结论!$C$30="YES",IF(L5<=ConstructPeriod+3,0,IF(L5<=ConstructPeriod+6,L12*假设及结论!$B$30*0.5,L12*假设及结论!$B$30)),L12*IF(L5>10,假设及结论!$B$30,0)) -> 0 | ... AD13: =IF(假设及结论!$C$30="YES",IF(AD5<=ConstructPeriod+3,0,IF(AD5<=ConstructPeriod+6,AD12*假设及结论!$B$30*0.5,AD12*假设及结论!$B$30)),AD12*IF(AD5>10,假设及结论!$B$30,0)) -> 0
A14: 9 | B14: 净利润（5-8） | C14: =SUM(D14:AD14) -> 545020.96 | D14: =D10-D13 -> 0 | E14: =E10-E13 -> 19499.219 | F14: =F10-F13 -> 19551.373 | G14: =G10-G13 -> 19839.563 | H14: =H10-H13 -> 20127.751 | I14: =I10-I13 -> 20415.938 | J14: =J10-J13 -> 20437.674 | K14: =K10-K13 -> 20725.856 | ... AD14: =AD10-AD13 -> -155.3202
A15: 10 | B15: 税后弥补之前亏损 | D15: 0 | E15: =IF(SUM($D$14:D14)<0,SUM($D$14:D14),0) -> 0 | F15: =IF(SUM($D$14:E14)<0,SUM($D$14:E14),0) -> 0 | G15: =IF(SUM($D$14:F14)<0,SUM($D$14:F14),0) -> 0 | H15: =IF(SUM($D$14:G14)<0,SUM($D$14:G14),0) -> 0 | I15: =IF(SUM($D$14:H14)<0,SUM($D$14:H14),0) -> 0 | J15: =IF(SUM($D$14:I14)<0,SUM($D$14:I14),0) -> 0 | K15: =IF(SUM($D$14:J14)<0,SUM($D$14:J14),0) -> 0 | L15: =IF(SUM($D$14:K14)<0,SUM($D$14:K14),0) -> 0 | ... AD15: =IF(SUM($D$14:AC14)<0,SUM($D$14:AC14),0) -> 0
A16: 11 | B16: 期初未分配利润 | D16: =IF(C20<0,0,IF(D5-ConstructPeriod>OperationPeriod,0,C20)) -> 0 | E16: =IF(D20<0,0,IF(E5-ConstructPeriod>OperationPeriod,0,D20)) -> 0 | F16: =IF(E20<0,0,IF(F5-ConstructPeriod>OperationPeriod,0,E20)) -> 16574.337 | G16: =IF(F20<0,0,IF(G5-ConstructPeriod>OperationPeriod,0,F20)) -> 33193.003 | H16: =IF(G20<0,0,IF(H5-ConstructPeriod>OperationPeriod,0,G20)) -> 50056.632 | I16: =IF(H20<0,0,IF(I5-ConstructPeriod>OperationPeriod,0,H20)) -> 67165.221 | J16: =IF(I20<0,0,IF(J5-ConstructPeriod>OperationPeriod,0,I20)) -> 84518.768 | K16: =IF(J20<0,0,IF(K5-ConstructPeriod>OperationPeriod,0,J20)) -> 101890.79 | ... AD16: =IF(AC20<0,0,IF(AD5-ConstructPeriod>OperationPeriod,0,AC20)) -> 0
A17: 12 | B17: 可供分配利润（9+11） | D17: =D14+D15 -> 0 | E17: =E14+E15 -> 19499.219 | F17: =F14+F15 -> 19551.373 | G17: =G14+G15 -> 19839.563 | H17: =H14+H15 -> 20127.751 | I17: =I14+I15 -> 20415.938 | J17: =J14+J15 -> 20437.674 | K17: =K14+K15 -> 20725.856 | ... AD17: =AD14+AD15 -> -155.3202
A18: 13 | B18: ="提取法定盈余公积金("&假设及结论!M33*100&"%)" -> 提取法定盈余公积金(10%) | D18: =IF(D17<0,0,IF(SUM(D$17:$E17)/10<=资金筹措!$F$12/2,D17*假设及结论!$M$33,0)) -> 0 | E18: =IF(E17<0,0,IF(SUM(E$17:$E17)/10<=资金筹措!$F$12/2,E17*假设及结论!$M$33,0)) -> 1949.9219 | F18: =IF(F17<0,0,IF(SUM($E$17:F17)/10<=资金筹措!$F$12/2,F17*假设及结论!$M$33,0)) -> 1955.1373 | G18: =IF(G17<0,0,IF(SUM($E$17:G17)/10<=资金筹措!$F$12/2,G17*假设及结论!$M$33,0)) -> 1983.9563 | H18: =IF(H17<0,0,IF(SUM($E$17:H17)/10<=资金筹措!$F$12/2,H17*假设及结论!$M$33,0)) -> 2012.7751 | I18: =IF(I17<0,0,IF(SUM($E$17:I17)/10<=资金筹措!$F$12/2,I17*假设及结论!$M$33,0)) -> 2041.5938 | J18: =IF(J17<0,0,IF(SUM($E$17:J17)/10<=资金筹措!$F$12/2,J17*假设及结论!$M$33,0)) -> 2043.7674 | K18: =IF(K17<0,0,IF(SUM($E$17:K17)/10<=资金筹措!$F$12/2,K17*假设及结论!$M$33,0)) -> 2072.5856 | L18: =IF(L17<0,0,IF(SUM($E$17:L17)/10<=资金筹措!$F$12/2,L17*假设及结论!$M$33,0)) -> 2101.4036 | M18: =IF(M17<0,0,IF(SUM($E$17:M17)/10<=资金筹措!$F$12/2,M17*假设及结论!$M$33,0)) -> 2130.2214 | ... AD18: =IF(AD17<0,0,IF(SUM($E$17:AD17)/10<=资金筹措!$F$12/2,AD17*假设及结论!$M$33,0)) -> 0
A19: 14 | B19: ="反税基要求/预扣税 ( "&假设及结论!E30*100&" %)" -> 反税基要求/预扣税 ( 5 %) | C19: =SUM(D19:AD19) -> 27251.048 | E19: =E14*假设及结论!$E$30 -> 974.96097 | F19: =F14*假设及结论!$E$30 -> 977.56863 | G19: =G14*假设及结论!$E$30 -> 991.97815 | H19: =H14*假设及结论!$E$30 -> 1006.3876 | I19: =I14*假设及结论!$E$30 -> 1020.7969 | J19: =J14*假设及结论!$E$30 -> 1021.8837 | K19: =K14*假设及结论!$E$30 -> 1036.2928 | L19: =L14*假设及结论!$E$30 -> 1050.7018 | ... AD19: =AD14*假设及结论!$E$30 -> -7.76601
A20: 15 | B20: 可供投资者分配的利润（11+12-13-14） | D20: =IF(D5-ConstructPeriod>OperationPeriod,0,D16+D17-D18) -> 0 | E20: =IF(E5-ConstructPeriod>OperationPeriod,0,E16+E17-E18-E19) -> 16574.337 | F20: =IF(F5-ConstructPeriod>OperationPeriod,0,F16+F17-F18-F19) -> 33193.003 | G20: =IF(G5-ConstructPeriod>OperationPeriod,0,G16+G17-G18-G19) -> 50056.632 | H20: =IF(H5-ConstructPeriod>OperationPeriod,0,H16+H17-H18-H19) -> 67165.221 | I20: =IF(I5-ConstructPeriod>OperationPeriod,0,I16+I17-I18-I19) -> 84518.768 | J20: =IF(J5-ConstructPeriod>OperationPeriod,0,J16+J17-J18-J19) -> 101890.79 | K20: =IF(K5-ConstructPeriod>OperationPeriod,0,K16+K17-K18-K19) -> 119507.77 | L20: =IF(L5-ConstructPeriod>OperationPeriod,0,L16+L17-L18-L19) -> 137369.7 | ... AD20: =IF(AD5-ConstructPeriod>OperationPeriod,0,AD16+AD17-AD18-AD19) -> 0
A21: 16 | B21: 应付优先股股利
A22: 17 | B22: 提取任意盈余公积金
A23: 18 | B23: 应付普通股股利（15-16-17） | D23: =D20-D21-D22 -> 0 | E23: =E20-E21-E22 -> 16574.337 | F23: =F20-F21-F22 -> 33193.003 | G23: =G20-G21-G22 -> 50056.632 | H23: =H20-H21-H22 -> 67165.221 | I23: =I20-I21-I22 -> 84518.768 | J23: =J20-J21-J22 -> 101890.79 | K23: =K20-K21-K22 -> 119507.77 | ... AD23: =AD20-AD21-AD22 -> 0
A24: 19 | B24: 各投资方利润分配
A25: 20 | B25: 未分配利润（15-16-17-19） | C25: =MAX(D25:AD25) -> 477587.76 | D25: =D23-D24 -> 0 | E25: =E23-E24 -> 16574.337 | F25: =F23-F24 -> 33193.003 | G25: =G23-G24 -> 50056.632 | H25: =H23-H24 -> 67165.221 | I25: =I23-I24 -> 84518.768 | J25: =J23-J24 -> 101890.79 | K25: =K23-K24 -> 119507.77 | ... AD25: =AD23-AD24 -> 0
A26: 21 | B26: 息税前利润（利润总额+ 利息支出） | C26: =SUM(D26:AD26) -> 638988.15 | D26: =D10+总成本!D20 -> 0 | E26: =E10+总成本!E20 -> 26213.693 | F26: =F10+总成本!F20 -> 25818.215 | G26: =G10+总成本!G20 -> 25658.773 | H26: =H10+总成本!H20 -> 25499.33 | I26: =I10+总成本!I20 -> 25339.885 | J26: =J10+总成本!J20 -> 24913.99 | K26: =K10+总成本!K20 -> 24754.54 | ... AD26: =AD10+总成本!AD20 -> -155.3202
A27: 22 | B27: 息税折旧摊销前利润（息税前利润+折旧+摊销） | C27: =SUM(D27:AD27) -> 841488.14 | D27: =D26+总成本!D18+总成本!D19 -> 0 | E27: =E26+总成本!E18+总成本!E19 -> 36338.692 | F27: =F26+总成本!F18+总成本!F19 -> 35943.214 | G27: =G26+总成本!G18+总成本!G19 -> 35783.773 | H27: =H26+总成本!H18+总成本!H19 -> 35624.33 | I27: =I26+总成本!I18+总成本!I19 -> 35464.884 | J27: =J26+总成本!J18+总成本!J19 -> 35038.99 | K27: =K26+总成本!K18+总成本!K19 -> 34879.54 | ... AD27: =AD26+总成本!AD18+总成本!AD19 -> -155.3202
E29: =IF(假设及结论!C30="YES",IF(E5<=ConstructPeriod+3,0,IF(E5<=ConstructPeriod+6,E12*假设及结论!$B$30*0.5,E12*假设及结论!$B$30)),E12*假设及结论!$B$30) -> 1949.9219
C30: 平均值
B31: 补贴有延迟时的净利润 | C31: =SUM(E31:AD31)/OperationPeriod -> 3771.0884 | E31: =IF(假设及结论!$F$15>1,E10,E31) -> -969.21797 | F31: =IF(假设及结论!$F$15>1,F10,F31) -> -792.93351 | G31: =IF(假设及结论!$F$15>1,G10,G31) -> 2628.7392 | H31: =IF(假设及结论!$F$15>1,H10,H31) -> 3140.544 | I31: =IF(假设及结论!$F$15>1,I10,I31) -> 3639.3693 | J31: =IF(假设及结论!$F$15>1,J10,J31) -> 3583.9733 | K31: =IF(假设及结论!$F$15>1,K10,K31) -> 3758.7156 | L31: =IF(假设及结论!$F$15>1,L10,L31) -> 3933.1212 | ... AD31: =IF(假设及结论!$F$15>1,AD10,AD31) -> 5.9117156e-13
B32: 补贴无延迟时的净利润 | C32: =SUM(E32:AD32)/OperationPeriod -> 23410.895 | E32: =IF(假设及结论!$F$15=1,E10,E32) -> 19499.219 | F32: =IF(假设及结论!$F$15=1,F10,F32) -> 19551.373 | G32: =IF(假设及结论!$F$15=1,G10,G32) -> 19839.563 | H32: =IF(假设及结论!$F$15=1,H10,H32) -> 20127.751 | I32: =IF(假设及结论!$F$15=1,I10,I32) -> 20415.938 | J32: =IF(假设及结论!$F$15=1,J10,J32) -> 20437.674 | K32: =IF(假设及结论!$F$15=1,K10,K32) -> 20725.856 | L32: =IF(假设及结论!$F$15=1,L10,L32) -> 21014.036 | ... AD32: =IF(假设及结论!$F$15=1,AD10,AD32) -> -155.3202
B33: 补贴无延迟时的所得税 | E33: =IF(假设及结论!$F$15=1,E13,E33) -> 0 | F33: =IF(假设及结论!$F$15=1,F13,F33) -> 0 | G33: =IF(假设及结论!$F$15=1,G13,G33) -> 0 | H33: =IF(假设及结论!$F$15=1,H13,H33) -> 0 | I33: =IF(假设及结论!$F$15=1,I13,I33) -> 0 | J33: =IF(假设及结论!$F$15=1,J13,J33) -> 0 | K33: =IF(假设及结论!$F$15=1,K13,K33) -> 0 | L33: =IF(假设及结论!$F$15=1,L13,L33) -> 0 | ... AD33: =IF(假设及结论!$F$15=1,AD13,AD33) -> 0
B34: 付息 | E34: =还本付息!E29 -> 6714.4734 | F34: =还本付息!F29 -> 6266.8418 | G34: =还本付息!G29 -> 5819.2103 | H34: =还本付息!H29 -> 5371.5787 | I34: =还本付息!I29 -> 4923.9472 | J34: =还本付息!J29 -> 4476.3156 | K34: =还本付息!K29 -> 4028.684 | L34: =还本付息!L29 -> 3581.0525 | ... AD34: =还本付息!AD29 -> -1.7025741e-12
B35: 期初负债余额 | E35: =还本付息!E26 -> 186513.15 | F35: =还本付息!F26 -> 174078.94 | G35: =还本付息!G26 -> 161644.73 | H35: =还本付息!H26 -> 149210.52 | I35: =还本付息!I26 -> 136776.31 | J35: =还本付息!J26 -> 124342.1 | K35: =还本付息!K26 -> 111907.89 | L35: =还本付息!L26 -> 99473.68 | ... AD35: =还本付息!AD26 -> -4.7293724e-11
B36: 实际净现金流 | E36: =资本金现金流!D21 -> 16215.048 | F36: =资本金现金流!E21 -> 16264.594 | G36: =资本金现金流!F21 -> 16538.374 | H36: =资本金现金流!G21 -> 16812.153 | I36: =资本金现金流!H21 -> 17085.93 | J36: =资本金现金流!I21 -> 17106.58 | K36: =资本金现金流!J21 -> 17380.353 | L36: =资本金现金流!K21 -> 17654.124 | ... AD36: =资本金现金流!AC21 -> -147.55419
B37: 年平均EVA | C37: =SUM(E37:AD37)/OperationPeriod -> 15781.91 | E37: =IF(AND(E5>ConstructPeriod,E5<=OperationPeriod+1),E32+E34-E33-(资金筹措!$C$12+E35-E36)*WACC,0) -> 9032.9628 | F37: =IF(AND(F5>ConstructPeriod,F5<=OperationPeriod+1),F32+F34-F33-(资金筹措!$C$12+F35-F36)*WACC,0) -> 9489.5007 | G37: =IF(AND(G5>ConstructPeriod,G5<=OperationPeriod+1),G32+G34-G33-(资金筹措!$C$12+G35-G36)*WACC,0) -> 10197.38 | H37: =IF(AND(H5>ConstructPeriod,H5<=OperationPeriod+1),H32+H34-H33-(资金筹措!$C$12+H35-H36)*WACC,0) -> 10905.257 | I37: =IF(AND(I5>ConstructPeriod,I5<=OperationPeriod+1),I32+I34-I33-(资金筹措!$C$12+I35-I36)*WACC,0) -> 11613.132 | J37: =IF(AND(J5>ConstructPeriod,J5<=OperationPeriod+1),J32+J34-J33-(资金筹措!$C$12+J35-J36)*WACC,0) -> 12037.281 | K37: =IF(AND(K5>ConstructPeriod,K5<=OperationPeriod+1),K32+K34-K33-(资金筹措!$C$12+K35-K36)*WACC,0) -> 12745.151 | L37: =IF(AND(L5>ConstructPeriod,L5<=OperationPeriod+1),L32+L34-L33-(资金筹措!$C$12+L35-L36)*WACC,0) -> 13453.02 | ... AD37: =IF(AND(AD5>ConstructPeriod,AD5<=OperationPeriod+1),AD32+AD34-AD33-(资金筹措!$C$12+AD35-AD36)*WACC,0) -> 0
C38: EVA = 税后净营业利润（NOPAT）-（【加权平均资本成本】WACC*【投资资本总额】TC） | N38: 税后净营业利润（NOPAT） = 营业利润+ 财务费用+ 投资收益- EVA税收调整
N39: EVA税收调整 = 利润表上所得税 + 税率 ×（财务费用 + 营业外支出 - 营业外收入）
B40: 折现率 | C40: 0.08 | D40: 0.09 | E40: 0.1 | F40: 0.11 | G40: 0.12 | H40: 0.13
B41: 股权价值 | C41: =NPV(C40,$E$17:$AD$17) -> 221880.74 | D41: =NPV(D40,$E$17:$AD$17) -> 203330.52 | E41: =NPV(E40,$E$17:$AD$17) -> 187196.01 | F41: =NPV(F40,$E$17:$AD$17) -> 173092.64 | G41: =NPV(G40,$E$17:$AD$17) -> 160704.7 | H41: =NPV(H40,$E$17:$AD$17) -> 149772.05

Sheet 全部投资现金流
A2: 项目投资现金流量表
W3: 单位:万元
A4: 序 | B4: 年份 名称 | C4: 建设营运期
A5: 号 | C5: 1 | D5: 2 | E5: 3 | F5: 4 | G5: 5 | H5: 6 | I5: 7 | J5: 8 | K5: 9 | L5: 10 | M5: 11 | N5: 12 | O5: 13 | P5: 14 | Q5: 15 | R5: 16 | S5: 17 | T5: 18 | U5: 19 | V5: 20 | W5: 21 | X5: 22 | Y5: 23 | Z5: 24 | AA5: 25 | AB5: 26 | AC5: 27
A6: 1 | B6: “增量”现金流入 | C6: =SUM(C7:C10) -> 0 | D6: =SUM(D7:D10) -> 39737.25 | E6: =SUM(E7:E10) -> 39339.878 | F6: =SUM(F7:F10) -> 39180.929 | G6: =SUM(G7:G10) -> 39021.98 | H6: =SUM(H7:H10) -> 38863.031 | I6: =SUM(I7:I10) -> 38704.082 | J6: =SUM(J7:J10) -> 38545.132 | ... AC6: =SUM(AC7:AC10) -> 0
A7: 1.1 | B7: 营业收入 | C7: =损益表!D6 -> 0 | D7: =销售收入!E6 -> 39737.25 | E7: =销售收入!F6 -> 39339.878 | F7: =销售收入!G6 -> 39180.929 | G7: =销售收入!H6 -> 39021.98 | H7: =销售收入!I6 -> 38863.031 | I7: =销售收入!J6 -> 38704.082 | J7: =销售收入!K6 -> 38545.132 | K7: =销售收入!L6 -> 38386.183 | ... AC7: =销售收入!AD6 -> 0
A8: 1.2 | B8: 固定资产增值税抵扣 | C8: =资本金现金流!C8 -> 0 | D8: =销售收入!E40 -> 0 | E8: =销售收入!F40 -> 0 | F8: =销售收入!G40 -> 0 | G8: =销售收入!H40 -> 0 | H8: =销售收入!I40 -> 0 | I8: =销售收入!J40 -> 0 | J8: =销售收入!K40 -> 0 | K8: =销售收入!L40 -> 0 | ... AC8: =销售收入!AD40 -> 0
A9: 1.3 | B9: 回收固定资产余值 | M9: =资本金现金流!M9 -> 0 | N9: =资本金现金流!N9 -> 0 | O9: =资本金现金流!O9 -> 0 | P9: =资本金现金流!P9 -> 0 | Q9: =资本金现金流!Q9 -> 0 | S9: =资本金现金流!S9 -> 0 | U9: =资本金现金流!U9 -> 0
A10: 1.4 | B10: 回收流动资金 | F10: =E10*3 -> 0 | G10: =F10 -> 0 | I10: =H10 -> 0 | J10: =I10 -> 0 | K10: =J10 -> 0 | L10: =K10 -> 0 | M10: =L10 -> 0 | N10: =M10 -> 0 | O10: =N10 -> 0 | P10: =O10 -> 0 | ... AC10: =AB10 -> 0
A11: 2 | B11: “增量”现金流出 | C11: =SUM(C12:C16) -> 264631.9 | D11: =SUM(D12:D16) -> 3398.5576 | E11: =SUM(E12:E16) -> 3396.6634 | F11: =SUM(F12:F16) -> 3397.1556 | G11: =SUM(G12:G16) -> 3397.6498 | H11: =SUM(H12:H16) -> 3398.1462 | I11: =SUM(I12:I16) -> 3665.0919 | J11: =SUM(J12:J16) -> 3665.5924 | ... AC11: =SUM(AC12:AC16) -> 155.3202
A12: 2.1 | B12: 建设投资（不含建设期利息） | C12: =资金筹措!C7 -> 263131.9 | D12: =资金筹措!D7 -> 0
A13: 2.2 | B13: 流动资金 | C13: =资金筹措!C9 -> 1500 | D13: =资金筹措!D9 -> 0 | E13: =资金筹措!E9 -> 0
A14: 2.3 | B14: 经营成本 | C14: =总成本!D17 -> 0 | D14: =总成本!E17 -> 3001.1851 | E14: =总成本!F17 -> 3003.2646 | F14: =总成本!G17 -> 3005.3463 | G14: =总成本!H17 -> 3007.43 | H14: =总成本!I17 -> 3009.5159 | I14: =总成本!J17 -> 3278.0511 | J14: =总成本!K17 -> 3280.1411 | ... AC14: =总成本!AD17 -> 155.3202
A15: 2.4 | B15: 营业税金及附加 | C15: =损益表!D8 -> 0 | D15: =损益表!E8 -> 397.3725 | E15: =损益表!F8 -> 393.39878 | F15: =损益表!G8 -> 391.80928 | G15: =损益表!H8 -> 390.21979 | H15: =损益表!I8 -> 388.63031 | I15: =损益表!J8 -> 387.04082 | J15: =损益表!K8 -> 385.45132 | ... AC15: =损益表!AD8 -> 0
A16: 2.5 | B16: 维持运营投资
A17: 3 | B17: 所得税前“增量”净现金流量 | C17: =C6-C11 -> -264631.9 | D17: =D6-D11 -> 36338.692 | E17: =E6-E11 -> 35943.214 | F17: =F6-F11 -> 35783.773 | G17: =G6-G11 -> 35624.33 | H17: =H6-H11 -> 35464.884 | I17: =I6-I11 -> 35038.99 | J17: =J6-J11 -> 34879.54 | ... AC17: =AC6-AC11 -> -155.3202
A18: 4 | B18: 累计所得税前“增量”净现金流量 | C18: =C17 -> -264631.9 | D18: =IF(D17=0,0,C18+D17) -> -228293.2 | E18: =IF(E17=0,0,D18+E17) -> -192349.99 | F18: =IF(F17=0,0,E18+F17) -> -156566.22 | G18: =IF(G17=0,0,F18+G17) -> -120941.89 | H18: =IF(H17=0,0,G18+H17) -> -85477.002 | I18: =IF(I17=0,0,H18+I17) -> -50438.012 | J18: =IF(J17=0,0,I18+J17) -> -15558.472 | K18: =IF(K17=0,0,J18+K17) -> 19161.616 | ... AC18: =IF(AC17=0,0,AB18+AC17) -> 576856.25
A19: 5 | B19: 调整“增量”所得税 | C19: =损益表!D13 -> 0 | D19: =IF(假设及结论!$C$30="YES",IF(D5<=ConstructPeriod+3,0,IF(D5<=ConstructPeriod+6,损益表!E26*假设及结论!$B$30*0.5,损益表!E26*假设及结论!$B$30)),损益表!E26*IF(E5>10,假设及结论!$B$30,0)) -> 0 | E19: =IF(假设及结论!$C$30="YES",IF(E5<=ConstructPeriod+3,0,IF(E5<=ConstructPeriod+6,损益表!F26*假设及结论!$B$30*0.5,损益表!F26*假设及结论!$B$30)),损益表!F26*IF(F5>10,假设及结论!$B$30,0)) -> 0 | F19: =IF(假设及结论!$C$30="YES",IF(F5<=ConstructPeriod+3,0,IF(F5<=ConstructPeriod+6,损益表!G26*假设及结论!$B$30*0.5,损益表!G26*假设及结论!$B$30)),损益表!G26*IF(G5>10,假设及结论!$B$30,0)) -> 0 | G19: =IF(假设及结论!$C$30="YES",IF(G5<=ConstructPeriod+3,0,IF(G5<=ConstructPeriod+6,损益表!H26*假设及结论!$B$30*0.5,损益表!H26*假设及结论!$B$30)),损益表!H26*IF(H5>10,假设及结论!$B$30,0)) -> 0 | H19: =IF(假设及结论!$C$30="YES",IF(H5<=ConstructPeriod+3,0,IF(H5<=ConstructPeriod+6,损益表!I26*假设及结论!$B$30*0.5,损益表!I26*假设及结论!$B$30)),损益表!I26*IF(I5>10,假设及结论!$B$30,0)) -> 0 | I19: =IF(假设及结论!$C$30="YES",IF(I5<=ConstructPeriod+3,0,IF(I5<=ConstructPeriod+6,损益表!J26*假设及结论!$B$30*0.5,损益表!J26*假设及结论!$B$30)),损益表!J26*IF(J5>10,假设及结论!$B$30,0)) -> 0 | J19: =IF(假设及结论!$C$30="YES",IF(J5<=ConstructPeriod+3,0,IF(J5<=ConstructPeriod+6,损益表!K26*假设及结论!$B$30*0.5,损益表!K26*假设及结论!$B$30)),损益表!K26*IF(K5>10,假设及结论!$B$30,0)) -> 0 | K19: =IF(假设及结论!$C$30="YES",IF(K5<=ConstructPeriod+3,0,IF(K5<=ConstructPeriod+6,损益表!L26*假设及结论!$B$30*0.5,损益表!L26*假设及结论!$B$30)),损益表!L26*IF(L5>10,假设及结论!$B$30,0)) -> 0 | ... AC19: =IF(假设及结论!$C$30="YES",IF(AC5<=ConstructPeriod+3,0,IF(AC5<=ConstructPeriod+6,损益表!AD26*假设及结论!$B$30*0.5,损益表!AD26*假设及结论!$B$30)),损益表!AD26*IF(AD5>10,假设及结论!$B$30,0)) -> 0
A20: 6 | B20: 调整“增量”反税基侵蚀补税/预扣税 | D20: =损益表!E19 -> 974.96097 | E20: =损益表!F19 -> 977.56863 | F20: =损益表!G19 -> 991.97815 | G20: =损益表!H19 -> 1006.3876 | H20: =损益表!I19 -> 1020.7969 | I20: =损益表!J19 -> 1021.8837 | J20: =损益表!K19 -> 1036.2928 | K20: =损益表!L19 -> 1050.7018 | ... AC20: =损益表!AD19 -> -7.76601
A21: 7 | B21: 所得税后“增量”净现金流量 | C21: =C17-C19 -> -264631.9 | D21: =D17-D19-D20 -> 35363.731 | E21: =E17-E19-E20 -> 34965.645 | F21: =F17-F19-F20 -> 34791.795 | G21: =G17-G19-G20 -> 34617.942 | H21: =H17-H19-H20 -> 34444.087 | I21: =I17-I19-I20 -> 34017.106 | J21: =J17-J19-J20 -> 33843.247 | K21: =K17-K19-K20 -> 33669.387 | ... AC21: =AC17-AC19-AC20 -> -147.55419
A22: 8 | B22: 累计所得税后“增量”净现金流量 | C22: =C21 -> -264631.9 | D22: =IF(D21=0,0,C22+D21) -> -229268.16 | E22: =IF(E21=0,0,D22+E21) -> -194302.52 | F22: =IF(F21=0,0,E22+F21) -> -159510.72 | G22: =IF(G21=0,0,F22+G21) -> -124892.78 | H22: =IF(H21=0,0,G22+H21) -> -90448.694 | I22: =IF(I21=0,0,H22+I21) -> -56431.588 | J22: =IF(J21=0,0,I22+J21) -> -22588.341 | K22: =IF(K21=0,0,J22+K21) -> 11081.046 | ... AC22: =IF(AC21=0,0,AB22+AC21) -> 505970.21
B25: 计算指标
B26: 项目增量财务内部收益率（%）（所得税前） | E26: =IRR(C17:AC17) -> 0.12456638
B27: 项目增量财务内部收益率（%）（所得税后） | E27: =IRR(C21:AC21) -> 0.11599219
B28: ="税前财务净现值(折现率 "&WACC*100&"%)" -> 税前财务净现值(折现率 6.825%) | E28: =NPV(DiscountRate,C17:AC17) -> 133147.11
B29: ="税后财务净现值(折现率 "&WACC*100&"%)" -> 税后财务净现值(折现率 6.825%) | E29: =NPV(DiscountRate,C21:AC21) -> 107966.84
B30: 增量投资回收期（年）（所得税前） | E30: {=(MATCH(1,IF(C18:AC18>0,1,0),0)-1)-INDEX($C$17:$AC$18,2,(MATCH(1,IF(C18:AC18>0,1,0),0)-1))/INDEX($C$17:$AC$18,1,(MATCH(1,IF(C18:AC18>0,1,0),0)))} -> 8.4481115
B31: 增量投资回收期（年）（所得税后） | E31: {=(MATCH(1,IF(C22:AC22>0,1,0),0)-1)-INDEX($C$21:$AC$22,2,(MATCH(1,IF(C22:AC22>0,1,0),0)-1))/INDEX($C$21:$AC$22,1,(MATCH(1,IF(C22:AC22>0,1,0),0)))} -> 8.6708866

Sheet 资本金现金流
A2: 资本金现金流量表
W3: 单位:万元
A4: 序 | B4: 年份 名称 | C4: 建设营运期
A5: 号 | C5: 1 | D5: 2 | E5: 3 | F5: 4 | G5: 5 | H5: 6 | I5: 7 | J5: 8 | K5: 9 | L5: 10 | M5: 11 | N5: 12 | O5: 13 | P5: 14 | Q5: 15 | R5: 16 | S5: 17 | T5: 18 | U5: 19 | V5: 20 | W5: 21 | X5: 22 | Y5: 23 | Z5: 24 | AA5: 25 | AB5: 26 | AC5: 27
A6: 1 | B6: “增量”现金流入 | C6: =SUM(C7:C10) -> 0 | D6: =SUM(D7:D10) -> 39737.25 | E6: =SUM(E7:E10) -> 39339.878 | F6: =SUM(F7:F10) -> 39180.929 | G6: =SUM(G7:G10) -> 39021.98 | H6: =SUM(H7:H10) -> 38863.031 | I6: =SUM(I7:I10) -> 38704.082 | J6: =SUM(J7:J10) -> 38545.132 | ... AC6: =SUM(AC7:AC10) -> 0
A7: 1.1 | B7: 营业收入 | C7: =损益表!D6 -> 0 | D7: =销售收入!E6 -> 39737.25 | E7: =销售收入!F6 -> 39339.878 | F7: =销售收入!G6 -> 39180.929 | G7: =销售收入!H6 -> 39021.98 | H7: =销售收入!I6 -> 38863.031 | I7: =销售收入!J6 -> 38704.082 | J7: =销售收入!K6 -> 38545.132 | K7: =销售收入!L6 -> 38386.183 | ... AC7: =销售收入!AD6 -> 0
A8: 1.2 | B8: 增值税初始收入 | D8: =销售收入!E40 -> 0 | E8: =销售收入!F40 -> 0 | F8: =销售收入!G40 -> 0 | G8: =销售收入!H40 -> 0 | H8: =销售收入!I40 -> 0 | I8: =销售收入!J40 -> 0 | J8: =销售收入!K40 -> 0 | K8: =销售收入!L40 -> 0 | ... AC8: =销售收入!AD40 -> 0
A9: 1.3 | B9: 回收固定资产余值 | G9: =F9 -> 0 | H9: =G9 -> 0 | I9: =H9 -> 0 | J9: =I9 -> 0 | K9: =J9 -> 0 | L9: =K9 -> 0 | M9: =L9 -> 0 | N9: =M9 -> 0 | ... Q9: =P9 -> 0 | S9: =R9 -> 0 | U9: =T9 -> 0
A10: 1.4 | B10: 回收流动资金
A11: 2 | B11: “增量”现金流出 | C11: =SUM(C12:C17) -> 81434.207 | D11: =SUM(D12:D18) -> 23522.202 | E11: =SUM(E12:E18) -> 23075.284 | F11: =SUM(F12:F18) -> 22642.554 | G11: =SUM(G12:G18) -> 22209.826 | H11: =SUM(H12:H18) -> 21777.1 | I11: =SUM(I12:I18) -> 21597.501 | J11: =SUM(J12:J18) -> 21164.779 | K11: =SUM(K12:K18) -> 20732.059 | ... AC11: =SUM(AC12:AC18) -> 147.55419
A12: 2.1 | B12: 项目资本金 | C12: =资金筹措!C12 -> 81434.207 | D12: =资金筹措!D12 -> 0 | E12: =资金筹措!E12 -> 0
A13: 2.4 | B13: 借款本金偿还 | D13: =还本付息!E16 -> 12434.21 | E13: =还本付息!F16 -> 12434.21 | F13: =还本付息!G16 -> 12434.21 | G13: =还本付息!H16 -> 12434.21 | H13: =还本付息!I16 -> 12434.21 | I13: =还本付息!J16 -> 12434.21 | J13: =还本付息!K16 -> 12434.21 | K13: =还本付息!L16 -> 12434.21 | ... AC13: =还本付息!AD16 -> 0
A14: 2.5 | B14: 借款利息支付 | D14: =还本付息!E17 -> 6714.4734 | E14: =还本付息!F17 -> 6266.8418 | F14: =还本付息!G17 -> 5819.2103 | G14: =还本付息!H17 -> 5371.5787 | H14: =还本付息!I17 -> 4923.9472 | I14: =还本付息!J17 -> 4476.3156 | J14: =还本付息!K17 -> 4028.684 | K14: =还本付息!L17 -> 3581.0525 | ... AC14: =还本付息!AD17 -> -1.7025741e-12
A15: 2.6 | B15: 经营成本 | C15: =总成本!D17 -> 0 | D15: =总成本!E17 -> 3001.1851 | E15: =总成本!F17 -> 3003.2646 | F15: =总成本!G17 -> 3005.3463 | G15: =总成本!H17 -> 3007.43 | H15: =总成本!I17 -> 3009.5159 | I15: =总成本!J17 -> 3278.0511 | J15: =总成本!K17 -> 3280.1411 | ... AC15: =总成本!AD17 -> 155.3202
A16: 2.7 | B16: 营业税金及附加 | C16: =损益表!D8 -> 0 | D16: =损益表!E8 -> 397.3725 | E16: =损益表!F8 -> 393.39878 | F16: =损益表!G8 -> 391.80928 | G16: =损益表!H8 -> 390.21979 | H16: =损益表!I8 -> 388.63031 | I16: =损益表!J8 -> 387.04082 | J16: =损益表!K8 -> 385.45132 | ... AC16: =损益表!AD8 -> 0
A17: 2.8 | B17: 所得税 | C17: =损益表!D13 -> 0 | D17: =损益表!E13 -> 0 | E17: =损益表!F13 -> 0 | F17: =损益表!G13 -> 0 | G17: =损益表!H13 -> 0 | H17: =损益表!I13 -> 0 | I17: =损益表!J13 -> 0 | J17: =损益表!K13 -> 0 | ... AC17: =损益表!AD13 -> 0
A18: 2.9 | B18: 反税基侵蚀补税/预扣税 | D18: =损益表!E19 -> 974.96097 | E18: =损益表!F19 -> 977.56863 | F18: =损益表!G19 -> 991.97815 | G18: =损益表!H19 -> 1006.3876 | H18: =损益表!I19 -> 1020.7969 | I18: =损益表!J19 -> 1021.8837 | J18: =损益表!K19 -> 1036.2928 | K18: =损益表!L19 -> 1050.7018 | ... AC18: =损益表!AD19 -> -7.76601
A19: 3 | B19: 净现金流量（所得税前） | C19: =C6-C11 -> -81434.207 | D19: =D21+D17+D18 -> 17190.009 | E19: =E21+E17+E18 -> 17242.162 | F19: =F21+F17+F18 -> 17530.353 | G19: =G21+G17+G18 -> 17818.541 | H19: =H21+H17+H18 -> 18106.727 | I19: =I21+I17+I18 -> 18128.464 | J19: =J21+J17+J18 -> 18416.646 | K19: =K21+K17+K18 -> 18704.826 | ... AC19: =AC21+AC17+AC18 -> -155.3202
A20: 4 | B20: 累计净现金流量（所得税前） | C20: =C19 -> -81434.207 | D20: =IF(D19=0,0,D19+C20) -> -64244.198 | E20: =IF(E19=0,0,E19+D20) -> -47002.036 | F20: =IF(F19=0,0,F19+E20) -> -29471.683 | G20: =IF(G19=0,0,G19+F20) -> -11653.142 | H20: =IF(H19=0,0,H19+G20) -> 6453.5849 | I20: =IF(I19=0,0,I19+H20) -> 24582.049 | J20: =IF(J19=0,0,J19+I20) -> 42998.695 | K20: =IF(K19=0,0,K19+J20) -> 61703.521 | ... AC20: =IF(AC19=0,0,AC19+AB20) -> 519825
A21: 5 | B21: 净现金流量（所得税后） | C21: =C6-C11 -> -81434.207 | D21: =D6-D11 -> 16215.048 | E21: =E6-E11 -> 16264.594 | F21: =F6-F11 -> 16538.374 | G21: =G6-G11 -> 16812.153 | H21: =H6-H11 -> 17085.93 | I21: =I6-I11 -> 17106.58 | J21: =J6-J11 -> 17380.353 | ... AC21: =AC6-AC11 -> -147.55419
A22: 6 | B22: 累计净现金流量（所得税后） | C22: =C21 -> -81434.207 | D22: =IF(D21=0,0,D21+C22) -> -65219.159 | E22: =IF(E21=0,0,E21+D22) -> -48954.565 | F22: =IF(F21=0,0,F21+E22) -> -32416.191 | G22: =IF(G21=0,0,G21+F22) -> -15604.038 | H22: =IF(H21=0,0,H21+G22) -> 1481.8927 | I22: =IF(I21=0,0,I21+H22) -> 18588.473 | J22: =IF(J21=0,0,J21+I22) -> 35968.826 | K22: =IF(K21=0,0,K21+J22) -> 53622.95 | ... AC22: =IF(AC21=0,0,AC21+AB22) -> 452322.55
B24: 财务内部收益(%)（所得税前） | E24: =IRR(C19:AC19) -> 0.2262975
B25: ="财务净现值(折现率 "&WACC*100&"%)（所得税前）" -> 财务净现值(折现率 6.825%)（所得税前） | E25: =NPV(DiscountRate,C19:AC19) -> 161892.22
B26: 投资回收期（所得税前） | E26: {=(MATCH(1,IF(C20:AC20>0,1,0),0)-1)-INDEX($C$19:$AC$20,2,(MATCH(1,IF(C20:AC20>0,1,0),0)-1))/INDEX($C$19:$AC$20,1,(MATCH(1,IF(C20:AC20>0,1,0),0)))} -> 5.6435808
B27: 财务内部收益(%)（所得税后） | E27: =IRR(C21:AC21) -> 0.21052865
B28: ="财务净现值(折现率 "&WACC*100&"%)（所得税后）" -> 财务净现值(折现率 6.825%)（所得税后） | E28: =NPV(DiscountRate,C21:AC21) -> 138383.91
B29: 投资回收期（所得税后） | E29: {=(MATCH(1,IF(C22:AC22>0,1,0),0)-1)-INDEX($C$21:$AC$22,2,(MATCH(1,IF(C22:AC22>0,1,0),0)-1))/INDEX($C$21:$AC$22,1,(MATCH(1,IF(C22:AC22>0,1,0),0)))} -> 5.9132682

Sheet 资产负债表
C1: =C15-C6 -> 0
A2: 资 产 负 债 表
D3: =D15-D6 -> 0 | E3: =E15-E6 -> 0 | F3: =F15-F6 -> 0 | G3: =G15-G6 -> 0 | H3: =H15-H6 -> 0 | I3: =I15-I6 -> 0 | J3: =J15-J6 -> 0 | K3: =K15-K6 -> 0 | ... AC3: =AC15-AC6 -> -4.7293724e-11
A4: 序 | B4: 年份 名称 | C4: 建设经营期
A5: 号 | C5: 1 | D5: 2 | E5: 3 | F5: 4 | G5: 5 | H5: 6 | I5: 7 | J5: 8 | K5: 9 | L5: 10 | M5: 11 | N5: 12 | O5: 13 | P5: 14 | Q5: 15 | R5: 16 | S5: 17 | T5: 18 | U5: 19 | V5: 20 | W5: 21 | X5: 22 | Y5: 23 | Z5: 24 | AA5: 25 | AB5: 26 | AC5: 27
A6: 1 | B6: 资产 | C6: =SUM(C7,C10:C12) -> 267947.36 | D6: =SUM(D7,D10:D13) -> 274037.41 | E6: =SUM(E7,E10:E13) -> 280177 | F6: =SUM(F7,F10:F13) -> 286590.37 | G6: =SUM(G7,G10:G13) -> 293277.53 | H6: =SUM(H7,H10:H13) -> 300238.46 | I6: =SUM(I7,I10:I13) -> 307220.04 | J6: =SUM(J7,J10:J13) -> 314475.39 | K6: =SUM(K7,K10:K13) -> 322004.52 | ... AC6: =SUM(AC7,AC10:AC13) -> 0
A7: 1.1 | B7: 流动资产总额 | C7: =SUM(C8:C9) -> 1500 | D7: =SUM(D8:D9) -> 17715.048 | E7: =SUM(E8:E9) -> 33979.642 | F7: =SUM(F8:F9) -> 50518.016 | G7: =SUM(G8:G9) -> 67330.17 | H7: =SUM(H8:H9) -> 84416.1 | I7: =SUM(I8:I9) -> 101522.68 | J7: =SUM(J8:J9) -> 118903.03 | ... AC7: =SUM(AC8:AC9) -> 0
A8: 1.1.1 | B8: 流动资产 | C8: =资金筹措!C9 -> 1500 | D8: =IF(C5>ConstructPeriod+OperationPeriod,0,C8+资金筹措!D9) -> 1500 | E8: =IF(D5<ConstructPeriod+OperationPeriod,D8+资金筹措!E9,0) -> 1500 | F8: =IF(E5<ConstructPeriod+OperationPeriod,E8,0) -> 1500 | G8: =IF(F5<ConstructPeriod+OperationPeriod,F8,0) -> 1500 | H8: =IF(G5<ConstructPeriod+OperationPeriod,G8,0) -> 1500 | I8: =IF(H5<ConstructPeriod+OperationPeriod,H8,0) -> 1500 | J8: =IF(I5<ConstructPeriod+OperationPeriod,I8,0) -> 1500 | K8: =IF(J5<ConstructPeriod+OperationPeriod,J8,0) -> 1500 | L8: =IF(K5<ConstructPeriod+OperationPeriod,K8,0) -> 1500 | M8: =IF(L5<ConstructPeriod+OperationPeriod,L8,0) -> 1500 | ... AC8: =IF(AB5<ConstructPeriod+OperationPeriod,AB8,0) -> 0
A9: 1.1.2 | B9: 累计盈余资金 | C9: =财务计划!C43 -> 0 | D9: =财务计划!D43 -> 16215.048 | E9: =财务计划!E43 -> 32479.642 | F9: =财务计划!F43 -> 49018.016 | G9: =财务计划!G43 -> 65830.17 | H9: =财务计划!H43 -> 82916.1 | I9: =财务计划!I43 -> 100022.68 | J9: =财务计划!J43 -> 117403.03 | ... AC9: =财务计划!AC43 -> 0
A10: 1.2 | B10: 在建工程 | C10: =FixedAssets -> 266447.36 | D10: =IF(D5<=ConstructPeriod,资金筹措!D7+资金筹措!D9+C10,0) -> 0
A11: 1.3 | B11: 固定资产净值 | C11: =折旧!G19 -> 0 | D11: =折旧!H19 -> 256322.36 | E11: =折旧!I19 -> 246197.36 | F11: =折旧!J19 -> 236072.36 | G11: =折旧!K19 -> 225947.36 | H11: =折旧!L19 -> 215822.36 | I11: =折旧!M19 -> 205697.36 | J11: =折旧!N19 -> 195572.36 | ... AC11: =折旧!AG19 -> 0
A12: 1.4 | B12: 无形及递延资产净值 | C12: =摊销!E20 -> 0 | D12: =摊销!F20 -> 0 | E12: =摊销!G20 -> 0 | F12: =摊销!H20 -> 0 | G12: =摊销!I20 -> 0 | H12: =摊销!J20 -> 0 | I12: =摊销!K20 -> 0 | J12: =摊销!L20 -> 0 | ... AC12: =摊销!AE20 -> 0
A13: 1.5 | B13: 可抵扣增值税形成资产 | C13: =销售收入!D38 -> 0 | D13: =销售收入!E41-SUM(销售收入!$E$42:销售收入!E42) -> 0 | E13: =销售收入!F41-SUM(销售收入!$E$42:销售收入!F42) -> 0 | F13: =销售收入!G41-SUM(销售收入!$E$42:销售收入!G42) -> 0 | G13: =销售收入!H41-SUM(销售收入!$E$42:销售收入!H42) -> 0 | H13: =销售收入!I41-SUM(销售收入!$E$42:销售收入!I42) -> 0 | I13: =销售收入!J41-SUM(销售收入!$E$42:销售收入!J42) -> 0 | J13: =销售收入!K41-SUM(销售收入!$E$42:销售收入!K42) -> 0 | K13: =销售收入!L41-SUM(销售收入!$E$42:销售收入!L42) -> 0 | ... AC13: =销售收入!AD41-SUM(销售收入!$E$42:销售收入!AD42) -> 0
B14: check sum | C14: =IF(C6-C15=0,"OK","NOK") -> OK | D14: =IF(D6-D15=0,"OK","NOK") -> OK | E14: =IF(E6-E15=0,"OK","NOK") -> OK | F14: =IF(F6-F15=0,"OK","NOK") -> OK | G14: =IF(G6-G15=0,"OK","NOK") -> OK | H14: =IF(H6-H15=0,"OK","NOK") -> OK | I14: =IF(I6-I15=0,"OK","NOK") -> OK | J14: =IF(J6-J15=0,"OK","NOK") -> OK | ... AC14: =IF(AC6-AC15=0,"OK","NOK") -> NOK
A15: 2 | B15: 负债和所有者权益 | C15: =C21+C22 -> 267947.36 | D15: =D21+D22 -> 274037.41 | E15: =SUM(E21:E22) -> 280177 | F15: =SUM(F21:F22) -> 286590.37 | G15: =SUM(G21:G22) -> 293277.53 | H15: =SUM(H21:H22) -> 300238.46 | I15: =SUM(I21:I22) -> 307220.04 | J15: =SUM(J21:J22) -> 314475.39 | K15: =SUM(K21:K22) -> 322004.52 | L15: =SUM(L21:L22) -> 329807.41 | ... AC15: =SUM(AC21:AC22) -> -4.7293724e-11
A16: 2.1 | B16: 流动负债总额 | C16: =SUM(C17:C18) -> 0 | D16: =SUM(D17:D18) -> 0 | E16: =SUM(E17:E18) -> 0 | F16: =SUM(F17:F18) -> 0 | G16: =SUM(G17:G18) -> 0 | H16: =SUM(H17:H18) -> 0 | I16: =SUM(I17:I18) -> 0 | J16: =SUM(J17:J18) -> 0 | ... AC16: =SUM(AC17:AC18) -> 0
A17: 2.1.1 | B17: 短期借款
A18: 2.1.4 | B18: 其他
A19: 2.2 | B19: 长期借款 | C19: =还本付息!D18 -> 186513.15 | D19: =还本付息!E18 -> 174078.94 | E19: =还本付息!F18 -> 161644.73 | F19: =还本付息!G18 -> 149210.52 | G19: =还本付息!H18 -> 136776.31 | H19: =还本付息!I18 -> 124342.1 | I19: =还本付息!J18 -> 111907.89 | J19: =还本付息!K18 -> 99473.68 | ... AC19: =还本付息!AD18 -> -4.7293724e-11
A20: 2.3 | B20: 流动资金借款 | D20: =还本付息!E21 -> 0 | E20: =还本付息!F21 -> 0 | F20: =还本付息!G21 -> 0 | G20: =还本付息!H21 -> 0 | H20: =还本付息!I21 -> 0 | I20: =还本付息!J21 -> 0 | J20: =还本付息!K21 -> 0 | K20: =还本付息!L21 -> 0 | ... AC20: =还本付息!AD21 -> 0
B21: 负债小计（2.1+2.2+2.3） | C21: =SUM(C16,C19:C20) -> 186513.15 | D21: =SUM(D16,D19:D20) -> 174078.94 | E21: =SUM(E16,E19:E20) -> 161644.73 | F21: =SUM(F16,F19:F20) -> 149210.52 | G21: =SUM(G16,G19:G20) -> 136776.31 | H21: =SUM(H16,H19:H20) -> 124342.1 | I21: =SUM(I16,I19:I20) -> 111907.89 | J21: =SUM(J16,J19:J20) -> 99473.68 | ... AC21: =SUM(AC16,AC19:AC20) -> -4.7293724e-11
A22: 2.4 | B22: 所有者权益 | C22: =SUM(C23:C26) -> 81434.207 | D22: =SUM(D23:D27) -> 99958.466 | E22: =SUM(E23:E27) -> 118532.27 | F22: =SUM(F23:F27) -> 137379.85 | G22: =SUM(G23:G26) -> 156501.22 | H22: =SUM(H23:H26) -> 175896.36 | I22: =SUM(I23:I26) -> 195312.15 | J22: =SUM(J23:J26) -> 215001.71 | K22: =SUM(K23:K26) -> 234965.05 | L22: =SUM(L23:L26) -> 255202.15 | M22: =SUM(M23:M26) -> 273661.94 | N22: =SUM(N23:N26) -> 292140.29 | ... AC22: =SUM(AC23:AC26) -> 0
A23: 2.4.1 | B23: 资本金 | C23: =IF(C5-ConstructPeriod<=OperationPeriod,资金筹措!$C$12,0) -> 81434.207 | D23: =IF(D5-ConstructPeriod<=OperationPeriod,IF(ConstructPeriod=1,资金筹措!$C$12,资金筹措!$C$12+资金筹措!$D$12),0) -> 81434.207 | E23: =IF(E5-ConstructPeriod<=OperationPeriod,IF(ConstructPeriod=1,资金筹措!$C$12,资金筹措!$C$12+资金筹措!$D$12),0) -> 81434.207 | F23: =IF(F5-ConstructPeriod<=OperationPeriod,IF(ConstructPeriod=1,资金筹措!$C$12,资金筹措!$C$12+资金筹措!$D$12),0) -> 81434.207 | G23: =IF(G5-ConstructPeriod<=OperationPeriod,IF(ConstructPeriod=1,资金筹措!$C$12,资金筹措!$C$12+资金筹措!$D$12),0) -> 81434.207 | H23: =IF(H5-ConstructPeriod<=OperationPeriod,IF(ConstructPeriod=1,资金筹措!$C$12,资金筹措!$C$12+资金筹措!$D$12),0) -> 81434.207 | I23: =IF(I5-ConstructPeriod<=OperationPeriod,IF(ConstructPeriod=1,资金筹措!$C$12,资金筹措!$C$12+资金筹措!$D$12),0) -> 81434.207 | J23: =IF(J5-ConstructPeriod<=OperationPeriod,IF(ConstructPeriod=1,资金筹措!$C$12,资金筹措!$C$12+资金筹措!$D$12),0) -> 81434.207 | K23: =IF(K5-ConstructPeriod<=OperationPeriod,IF(ConstructPeriod=1,资金筹措!$C$12,资金筹措!$C$12+资金筹措!$D$12),0) -> 81434.207 | ... AC23: =IF(AC5-ConstructPeriod<=OperationPeriod,IF(ConstructPeriod=1,资金筹措!$C$12,资金筹措!$C$12+资金筹措!$D$12),0) -> 0
A24: 2.4.2 | B24: 资本公积金
A25: 2.4.3 | B25: 累计盈余公积金 | C25: =损益表!D18 -> 0 | D25: =IF(D5-ConstructPeriod<=OperationPeriod,C25+损益表!E18,0) -> 1949.9219 | E25: =IF(E5-ConstructPeriod<=OperationPeriod,D25+损益表!F18,0) -> 3905.0592 | F25: =IF(F5-ConstructPeriod<=OperationPeriod,E25+损益表!G18,0) -> 5889.0155 | G25: =IF(G5-ConstructPeriod<=OperationPeriod,F25+损益表!H18,0) -> 7901.7907 | H25: =IF(H5-ConstructPeriod<=OperationPeriod,G25+损益表!I18,0) -> 9943.3844 | I25: =IF(I5-ConstructPeriod<=OperationPeriod,H25+损益表!J18,0) -> 11987.152 | J25: =IF(J5-ConstructPeriod<=OperationPeriod,I25+损益表!K18,0) -> 14059.738 | K25: =IF(K5-ConstructPeriod<=OperationPeriod,J25+损益表!L18,0) -> 16161.141 | ... AC25: =IF(AC5-ConstructPeriod<=OperationPeriod,AB25+损益表!AD18,0) -> 0
A26: 2.4.4 | B26: 累计未分配利润 | C26: =损益表!D25 -> 0 | D26: =损益表!E25 -> 16574.337 | E26: =损益表!F25 -> 33193.003 | F26: =损益表!G25 -> 50056.632 | G26: =损益表!H25 -> 67165.221 | H26: =损益表!I25 -> 84518.768 | I26: =损益表!J25 -> 101890.79 | J26: =损益表!K25 -> 119507.77 | ... AC26: =损益表!AD25 -> 0
A27: 2.4.5 | C27: =损益表!D19 -> 0
B29: 计算指标
B30: 资产负债率(%) | C30: =IF(C6<=0,0,C21/C6*100) -> 69.608132 | D30: =IF(D6<=0,0,D21/D6*100) -> 63.523788 | E30: =IF(E6<=0,0,E21/E6*100) -> 57.69379 | F30: =IF(F6<=0,0,F21/F6*100) -> 52.064037 | G30: =IF(G6<=0,0,G21/G6*100) -> 46.63716 | H30: =IF(H6<=0,0,H21/H6*100) -> 41.414448 | I30: =IF(I6<=0,0,I21/I6*100) -> 36.425973 | J30: =IF(J6<=0,0,J21/J6*100) -> 31.631626 | ... AC30: =IF(AC6<=0,0,AC21/AC6*100) -> 0
B31: ROE | C31: 0 | D31: =IF(D22<=0,0,IF(D5<=ConstructPeriod,0,损益表!E14/资产负债表!D22)) -> 0.19507322 | E31: =IF(E22<=0,0,IF(E5<=ConstructPeriod,0,损益表!F14/资产负债表!E22)) -> 0.16494557 | F31: =IF(F22<=0,0,IF(F5<=ConstructPeriod,0,损益表!G14/资产负债表!F22)) -> 0.14441392 | G31: =IF(G22<=0,0,IF(G5<=ConstructPeriod,0,损益表!H14/资产负债表!G22)) -> 0.12861083 | H31: =IF(H22<=0,0,IF(H5<=ConstructPeriod,0,损益表!I14/资产负债表!H22)) -> 0.11606799 | I31: =IF(I22<=0,0,IF(I5<=ConstructPeriod,0,损益表!J14/资产负债表!I22)) -> 0.10464108 | J31: =IF(J22<=0,0,IF(J5<=ConstructPeriod,0,损益表!K14/资产负债表!J22)) -> 0.096398564 | K31: =IF(K22<=0,0,IF(K5<=ConstructPeriod,0,损益表!L14/资产负债表!K22)) -> 0.089434733 | ... AC31: =IF(AC22<=0,0,IF(AC5<=ConstructPeriod,0,损益表!AD14/资产负债表!AC22)) -> 0
B32: 平均ROE | C32: =SUM(C31:AC31)/(ConstructPeriod+OperationPeriod) -> 0.0768366 | D32: =D6-D15 -> 0 | E32: =E6-E15 -> 0 | F32: =F6-F15 -> 0 | G32: =G6-G15 -> 0 | H32: =H6-H15 -> 0
E33: =E15-E6 -> 0 | F33: =F15-F6 -> 0 | G33: =G15-G6 -> 0 | H33: =H15-H6 -> 0 | I33: =I15-I6 -> 0 | J33: =J15-J6 -> 0

Sheet 总成本
A2: 总 成 本 费 用 表
X3: 单位:万元
A4: 序 | B4: 年份 名称 | C4: 合计 | D4: 建设经营期
A5: 号 | D5: 1 | E5: 2 | F5: 3 | G5: 4 | H5: 5 | I5: 6 | J5: 7 | K5: 8 | L5: 9 | M5: 10 | N5: 11 | O5: 12 | P5: 13 | Q5: 14 | R5: 15 | S5: 16 | T5: 17 | U5: 18 | V5: 19 | W5: 20 | X5: 21 | Y5: 22 | Z5: 23 | AA5: 24 | AB5: 25 | AC5: 26 | AD5: 27
A6: 1 | B6: 工资及福利费 | C6: =SUM(E6:AD6) -> 12496 | D6: =IF(假设及结论!$D$24=3,IF(D5<=ConstructPeriod,0,IF(D5>OperationPeriod+ConstructPeriod,0,(假设及结论!$D$27*假设及结论!$E$21)*(1+假设及结论!$F$21))),IF(D5<=ConstructPeriod,0,IF(D5>OperationPeriod+ConstructPeriod,0,(假设及结论!$D$21*假设及结论!$E$21)*(1+假设及结论!$F$21)))) -> 0 | E6: =IF(假设及结论!$D$24=3,IF(E5<=ConstructPeriod,0,IF(E5>OperationPeriod+ConstructPeriod,0,(假设及结论!$D$27*假设及结论!$E$21)*(1+假设及结论!$F$21))),IF(E5<=ConstructPeriod,0,IF(E5>OperationPeriod+ConstructPeriod,0,(假设及结论!$D$21*假设及结论!$E$21)*(1+假设及结论!$F$21)))) -> 499.84 | F6: =IF(假设及结论!$D$24=3,IF(F5<=ConstructPeriod,0,IF(F5>OperationPeriod+ConstructPeriod,0,(假设及结论!$D$27*假设及结论!$E$21)*(1+假设及结论!$F$21))),IF(F5<=ConstructPeriod,0,IF(F5>OperationPeriod+ConstructPeriod,0,(假设及结论!$D$21*假设及结论!$E$21)*(1+假设及结论!$F$21)))) -> 499.84 | G6: =IF(假设及结论!$D$24=3,IF(G5<=ConstructPeriod,0,IF(G5>OperationPeriod+ConstructPeriod,0,(假设及结论!$D$27*假设及结论!$E$21)*(1+假设及结论!$F$21))),IF(G5<=ConstructPeriod,0,IF(G5>OperationPeriod+ConstructPeriod,0,(假设及结论!$D$21*假设及结论!$E$21)*(1+假设及结论!$F$21)))) -> 499.84 | H6: =IF(假设及结论!$D$24=3,IF(H5<=ConstructPeriod,0,IF(H5>OperationPeriod+ConstructPeriod,0,(假设及结论!$D$27*假设及结论!$E$21)*(1+假设及结论!$F$21))),IF(H5<=ConstructPeriod,0,IF(H5>OperationPeriod+ConstructPeriod,0,(假设及结论!$D$21*假设及结论!$E$21)*(1+假设及结论!$F$21)))) -> 499.84 | I6: =IF(假设及结论!$D$24=3,IF(I5<=ConstructPeriod,0,IF(I5>OperationPeriod+ConstructPeriod,0,(假设及结论!$D$27*假设及结论!$E$21)*(1+假设及结论!$F$21))),IF(I5<=ConstructPeriod,0,IF(I5>OperationPeriod+ConstructPeriod,0,(假设及结论!$D$21*假设及结论!$E$21)*(1+假设及结论!$F$21)))) -> 499.84 | J6: =IF(假设及结论!$D$24=3,IF(J5<=ConstructPeriod,0,IF(J5>OperationPeriod+ConstructPeriod,0,(假设及结论!$D$27*假设及结论!$E$21)*(1+假设及结论!$F$21))),IF(J5<=ConstructPeriod,0,IF(J5>OperationPeriod+ConstructPeriod,0,(假设及结论!$D$21*假设及结论!$E$21)*(1+假设及结论!$F$21)))) -> 499.84 | K6: =IF(假设及结论!$D$24=3,IF(K5<=ConstructPeriod,0,IF(K5>OperationPeriod+ConstructPeriod,0,(假设及结论!$D$27*假设及结论!$E$21)*(1+假设及结论!$F$21))),IF(K5<=ConstructPeriod,0,IF(K5>OperationPeriod+ConstructPeriod,0,(假设及结论!$D$21*假设及结论!$E$21)*(1+假设及结论!$F$21)))) -> 499.84 | ... AD6: =IF(假设及结论!$D$24=3,IF(AD5<=ConstructPeriod,0,IF(AD5>OperationPeriod+ConstructPeriod,0,(假设及结论!$D$27*假设及结论!$E$21)*(1+假设及结论!$F$21))),IF(AD5<=ConstructPeriod,0,IF(AD5>OperationPeriod+ConstructPeriod,0,(假设及结论!$D$21*假设及结论!$E$21)*(1+假设及结论!$F$21)))) -> 0
A7: 2 | B7: 维修费 | C7: =SUM(E7:AD7) -> 17476.054 | D7: =IF(假设及结论!$D$24=1,IF(D6=0,0,IF(D5>ConstructPeriod+假设及结论!$C$24,IF(假设及结论!$B$24=1,假设及结论!$O$24*InstalledCapacity*(1+CPI)^(D5-1),假设及结论!$I$24*InstalledCapacity*(1+CPI)^(D5-1)),IF(假设及结论!$B$24=1,假设及结论!$N$24*InstalledCapacity*(1+CPI)^(D5-1),假设及结论!$H$24*InstalledCapacity*(1+CPI)^(D5-1)))),IF(假设及结论!$D$24=2,D28,IF(D6=0,0,IF(D5>ConstructPeriod+假设及结论!$C$24,IF(假设及结论!$B$24=1,假设及结论!$O$24*InstalledCapacity*假设及结论!$E$18*(1+CPI)^(D5-1),假设及结论!$I$24*InstalledCapacity*假设及结论!$E$18*(1+CPI)^(D5-1)),IF(假设及结论!$B$24=1,假设及结论!$N$24*InstalledCapacity*假设及结论!$E$18*(1+CPI)^(D5-1),假设及结论!$H$24*InstalledCapacity*假设及结论!$E$18*(1+CPI)^(D5-1)))))) -> 0 | E7: =IF(假设及结论!$D$24=1,IF(E6=0,0,IF(E5>ConstructPeriod+假设及结论!$C$24,IF(假设及结论!$B$24=1,假设及结论!$O$24*InstalledCapacity*(1+CPI)^(E5-1),假设及结论!$I$24*InstalledCapacity*(1+CPI)^(E5-1)),IF(假设及结论!$B$24=1,假设及结论!$N$24*InstalledCapacity*(1+CPI)^(E5-1),假设及结论!$H$24*InstalledCapacity*(1+CPI)^(E5-1)))),IF(假设及结论!$D$24=2,E28,IF(E6=0,0,IF(E5>ConstructPeriod+假设及结论!$C$24,IF(假设及结论!$B$24=1,假设及结论!$O$24*InstalledCapacity*假设及结论!$E$18*(1+CPI)^(E5-1),假设及结论!$I$24*InstalledCapacity*假设及结论!$E$18*(1+CPI)^(E5-1)),IF(假设及结论!$B$24=1,假设及结论!$N$24*InstalledCapacity*假设及结论!$E$18*(1+CPI)^(E5-1),假设及结论!$H$24*InstalledCapacity*假设及结论!$E$18*(1+CPI)^(E5-1)))))) -> 690.69 | F7: =IF(假设及结论!$D$24=1,IF(F6=0,0,IF(F5>ConstructPeriod+假设及结论!$C$24,IF(假设及结论!$B$24=1,假设及结论!$O$24*InstalledCapacity*(1+CPI)^(F5-1),假设及结论!$I$24*InstalledCapacity*(1+CPI)^(F5-1)),IF(假设及结论!$B$24=1,假设及结论!$N$24*InstalledCapacity*(1+CPI)^(F5-1),假设及结论!$H$24*InstalledCapacity*(1+CPI)^(F5-1)))),IF(假设及结论!$D$24=2,F28,IF(F6=0,0,IF(F5>ConstructPeriod+假设及结论!$C$24,IF(假设及结论!$B$24=1,假设及结论!$O$24*InstalledCapacity*假设及结论!$E$18*(1+CPI)^(F5-1),假设及结论!$I$24*InstalledCapacity*假设及结论!$E$18*(1+CPI)^(F5-1)),IF(假设及结论!$B$24=1,假设及结论!$N$24*InstalledCapacity*假设及结论!$E$18*(1+CPI)^(F5-1),假设及结论!$H$24*InstalledCapacity*假设及结论!$E$18*(1+CPI)^(F5-1)))))) -> 691.38069 | G7: =IF(假设及结论!$D$24=1,IF(G6=0,0,IF(G5>ConstructPeriod+假设及结论!$C$24,IF(假设及结论!$B$24=1,假设及结论!$O$24*InstalledCapacity*(1+CPI)^(G5-1),假设及结论!$I$24*InstalledCapacity*(1+CPI)^(G5-1)),IF(假设及结论!$B$24=1,假设及结论!$N$24*InstalledCapacity*(1+CPI)^(G5-1),假设及结论!$H$24*InstalledCapacity*(1+CPI)^(G5-1)))),IF(假设及结论!$D$24=2,G28,IF(G6=0,0,IF(G5>ConstructPeriod+假设及结论!$C$24,IF(假设及结论!$B$24=1,假设及结论!$O$24*InstalledCapacity*假设及结论!$E$18*(1+CPI)^(G5-1),假设及结论!$I$24*InstalledCapacity*假设及结论!$E$18*(1+CPI)^(G5-1)),IF(假设及结论!$B$24=1,假设及结论!$N$24*InstalledCapacity*假设及结论!$E$18*(1+CPI)^(G5-1),假设及结论!$H$24*InstalledCapacity*假设及结论!$E$18*(1+CPI)^(G5-1)))))) -> 692.07207 | H7: =IF(假设及结论!$D$24=1,IF(H6=0,0,IF(H5>ConstructPeriod+假设及结论!$C$24,IF(假设及结论!$B$24=1,假设及结论!$O$24*InstalledCapacity*(1+CPI)^(H5-1),假设及结论!$I$24*InstalledCapacity*(1+CPI)^(H5-1)),IF(假设及结论!$B$24=1,假设及结论!$N$24*InstalledCapacity*(1+CPI)^(H5-1),假设及结论!$H$24*InstalledCapacity*(1+CPI)^(H5-1)))),IF(假设及结论!$D$24=2,H28,IF(H6=0,0,IF(H5>ConstructPeriod+假设及结论!$C$24,IF(假设及结论!$B$24=1,假设及结论!$O$24*InstalledCapacity*假设及结论!$E$18*(1+CPI)^(H5-1),假设及结论!$I$24*InstalledCapacity*假设及结论!$E$18*(1+CPI)^(H5-1)),IF(假设及结论!$B$24=1,假设及结论!$N$24*InstalledCapacity*假设及结论!$E$18*(1+CPI)^(H5-1),假设及结论!$H$24*InstalledCapacity*假设及结论!$E$18*(1+CPI)^(H5-1)))))) -> 692.76414 | I7: =IF(假设及结论!$D$24=1,IF(I6=0,0,IF(I5>ConstructPeriod+假设及结论!$C$24,IF(假设及结论!$B$24=1,假设及结论!$O$24*InstalledCapacity*(1+CPI)^(I5-1),假设及结论!$I$24*InstalledCapacity*(1+CPI)^(I5-1)),IF(假设及结论!$B$24=1,假设及结论!$N$24*InstalledCapacity*(1+CPI)^(I5-1),假设及结论!$H$24*InstalledCapacity*(1+CPI)^(I5-1)))),IF(假设及结论!$D$24=2,I28,IF(I6=0,0,IF(I5>ConstructPeriod+假设及结论!$C$24,IF(假设及结论!$B$24=1,假设及结论!$O$24*InstalledCapacity*假设及结论!$E$18*(1+CPI)^(I5-1),假设及结论!$I$24*InstalledCapacity*假设及结论!$E$18*(1+CPI)^(I5-1)),IF(假设及结论!$B$24=1,假设及结论!$N$24*InstalledCapacity*假设及结论!$E$18*(1+CPI)^(I5-1),假设及结论!$H$24*InstalledCapacity*假设及结论!$E$18*(1+CPI)^(I5-1)))))) -> 693.45691 | J7: =IF(假设及结论!$D$24=1,IF(J6=0,0,IF(J5>ConstructPeriod+假设及结论!$C$24,IF(假设及结论!$B$24=1,假设及结论!$O$24*InstalledCapacity*(1+CPI)^(J5-1),假设及结论!$I$24*InstalledCapacity*(1+CPI)^(J5-1)),IF(假设及结论!$B$24=1,假设及结论!$N$24*InstalledCapacity*(1+CPI)^(J5-1),假设及结论!$H$24*InstalledCapacity*(1+CPI)^(J5-1)))),IF(假设及结论!$D$24=2,J28,IF(J6=0,0,IF(J5>ConstructPeriod+假设及结论!$C$24,IF(假设及结论!$B$24=1,假设及结论!$O$24*InstalledCapacity*假设及结论!$E$18*(1+CPI)^(J5-1),假设及结论!$I$24*InstalledCapacity*假设及结论!$E$18*(1+CPI)^(J5-1)),IF(假设及结论!$B$24=1,假设及结论!$N$24*InstalledCapacity*假设及结论!$E$18*(1+CPI)^(J5-1),假设及结论!$H$24*InstalledCapacity*假设及结论!$E$18*(1+CPI)^(J5-1)))))) -> 694.15036 | K7: =IF(假设及结论!$D$24=1,IF(K6=0,0,IF(K5>ConstructPeriod+假设及结论!$C$24,IF(假设及结论!$B$24=1,假设及结论!$O$24*InstalledCapacity*(1+CPI)^(K5-1),假设及结论!$I$24*InstalledCapacity*(1+CPI)^(K5-1)),IF(假设及结论!$B$24=1,假设及结论!$N$24*InstalledCapacity*(1+CPI)^(K5-1),假设及结论!$H$24*InstalledCapacity*(1+CPI)^(K5-1)))),IF(假设及结论!$D$24=2,K28,IF(K6=0,0,IF(K5>ConstructPeriod+假设及结论!$C$24,IF(假设及结论!$B$24=1,假设及结论!$O$24*InstalledCapacity*假设及结论!$E$18*(1+CPI)^(K5-1),假设及结论!$I$24*InstalledCapacity*假设及结论!$E$18*(1+CPI)^(K5-1)),IF(假设及结论!$B$24=1,假设及结论!$N$24*InstalledCapacity*假设及结论!$E$18*(1+CPI)^(K5-1),假设及结论!$H$24*InstalledCapacity*假设及结论!$E$18*(1+CPI)^(K5-1)))))) -> 694.84451 | ... AD7: =IF(假设及结论!$D$24=1,IF(AD6=0,0,IF(AD5>ConstructPeriod+假设及结论!$C$24,IF(假设及结论!$B$24=1,假设及结论!$O$24*InstalledCapacity*(1+CPI)^(AD5-1),假设及结论!$I$24*InstalledCapacity*(1+CPI)^(AD5-1)),IF(假设及结论!$B$24=1,假设及结论!$N$24*InstalledCapacity*(1+CPI)^(AD5-1),假设及结论!$H$24*InstalledCapacity*(1+CPI)^(AD5-1)))),IF(假设及结论!$D$24=2,AD28,IF(AD6=0,0,IF(AD5>ConstructPeriod+假设及结论!$C$24,IF(假设及结论!$B$24=1,假设及结论!$O$24*InstalledCapacity*假设及结论!$E$18*(1+CPI)^(AD5-1),假设及结论!$I$24*InstalledCapacity*假设及结论!$E$18*(1+CPI)^(AD5-1)),IF(假设及结论!$B$24=1,假设及结论!$N$24*InstalledCapacity*假设及结论!$E$18*(1+CPI)^(AD5-1),假设及结论!$H$24*InstalledCapacity*假设及结论!$E$18*(1+CPI)^(AD5-1)))))) -> 0
A8: 3 | B8: 材料费 | C8: =SUM(E8:AD8) -> 18995.711 | D8: =IF(假设及结论!$D$24=1,IF(D6=0,0,IF(D5>ConstructPeriod+假设及结论!$C$24,IF(假设及结论!$B$24=1,假设及结论!$M$24*InstalledCapacity*(1+CPI)^(D5-1),假设及结论!$G$24*InstalledCapacity*(1+CPI)^(D5-1)),IF(假设及结论!$B$24=1,假设及结论!$L$24*InstalledCapacity*(1+CPI)^(D5-1),假设及结论!$F$24*InstalledCapacity*(1+CPI)^(D5-1)))),IF(假设及结论!$D$24=2,0,IF(D6=0,0,IF(D5>ConstructPeriod+假设及结论!$C$24,IF(假设及结论!$B$24=1,假设及结论!$M$27*InstalledCapacity*假设及结论!$E$18*(1+CPI)^(D5-1),假设及结论!$G$27*InstalledCapacity*假设及结论!$E$18*(1+CPI)^(D5-1)),IF(假设及结论!$B$24=1,假设及结论!$L$27*InstalledCapacity*假设及结论!$E$18*(1+CPI)^(D5-1),假设及结论!$F$27*InstalledCapacity*假设及结论!$E$18*(1+CPI)^(D5-1)))))) -> 0 | E8: =IF(假设及结论!$D$24=1,IF(E6=0,0,IF(E5>ConstructPeriod+假设及结论!$C$24,IF(假设及结论!$B$24=1,假设及结论!$M$24*InstalledCapacity*(1+CPI)^(E5-1),假设及结论!$G$24*InstalledCapacity*(1+CPI)^(E5-1)),IF(假设及结论!$B$24=1,假设及结论!$L$24*InstalledCapacity*(1+CPI)^(E5-1),假设及结论!$F$24*InstalledCapacity*(1+CPI)^(E5-1)))),IF(假设及结论!$D$24=2,0,IF(E6=0,0,IF(E5>ConstructPeriod+假设及结论!$C$24,IF(假设及结论!$B$24=1,假设及结论!$M$27*InstalledCapacity*假设及结论!$E$18*(1+CPI)^(E5-1),假设及结论!$G$27*InstalledCapacity*假设及结论!$E$18*(1+CPI)^(E5-1)),IF(假设及结论!$B$24=1,假设及结论!$L$27*InstalledCapacity*假设及结论!$E$18*(1+CPI)^(E5-1),假设及结论!$F$27*InstalledCapacity*假设及结论!$E$18*(1+CPI)^(E5-1)))))) -> 750.75 | F8: =IF(假设及结论!$D$24=1,IF(F6=0,0,IF(F5>ConstructPeriod+假设及结论!$C$24,IF(假设及结论!$B$24=1,假设及结论!$M$24*InstalledCapacity*(1+CPI)^(F5-1),假设及结论!$G$24*InstalledCapacity*(1+CPI)^(F5-1)),IF(假设及结论!$B$24=1,假设及结论!$L$24*InstalledCapacity*(1+CPI)^(F5-1),假设及结论!$F$24*InstalledCapacity*(1+CPI)^(F5-1)))),IF(假设及结论!$D$24=2,0,IF(F6=0,0,IF(F5>ConstructPeriod+假设及结论!$C$24,IF(假设及结论!$B$24=1,假设及结论!$M$27*InstalledCapacity*假设及结论!$E$18*(1+CPI)^(F5-1),假设及结论!$G$27*InstalledCapacity*假设及结论!$E$18*(1+CPI)^(F5-1)),IF(假设及结论!$B$24=1,假设及结论!$L$27*InstalledCapacity*假设及结论!$E$18*(1+CPI)^(F5-1),假设及结论!$F$27*InstalledCapacity*假设及结论!$E$18*(1+CPI)^(F5-1)))))) -> 751.50075 | G8: =IF(假设及结论!$D$24=1,IF(G6=0,0,IF(G5>ConstructPeriod+假设及结论!$C$24,IF(假设及结论!$B$24=1,假设及结论!$M$24*InstalledCapacity*(1+CPI)^(G5-1),假设及结论!$G$24*InstalledCapacity*(1+CPI)^(G5-1)),IF(假设及结论!$B$24=1,假设及结论!$L$24*InstalledCapacity*(1+CPI)^(G5-1),假设及结论!$F$24*InstalledCapacity*(1+CPI)^(G5-1)))),IF(假设及结论!$D$24=2,0,IF(G6=0,0,IF(G5>ConstructPeriod+假设及结论!$C$24,IF(假设及结论!$B$24=1,假设及结论!$M$27*InstalledCapacity*假设及结论!$E$18*(1+CPI)^(G5-1),假设及结论!$G$27*InstalledCapacity*假设及结论!$E$18*(1+CPI)^(G5-1)),IF(假设及结论!$B$24=1,假设及结论!$L$27*InstalledCapacity*假设及结论!$E$18*(1+CPI)^(G5-1),假设及结论!$F$27*InstalledCapacity*假设及结论!$E$18*(1+CPI)^(G5-1)))))) -> 752.25225 | H8: =IF(假设及结论!$D$24=1,IF(H6=0,0,IF(H5>ConstructPeriod+假设及结论!$C$24,IF(假设及结论!$B$24=1,假设及结论!$M$24*InstalledCapacity*(1+CPI)^(H5-1),假设及结论!$G$24*InstalledCapacity*(1+CPI)^(H5-1)),IF(假设及结论!$B$24=1,假设及结论!$L$24*InstalledCapacity*(1+CPI)^(H5-1),假设及结论!$F$24*InstalledCapacity*(1+CPI)^(H5-1)))),IF(假设及结论!$D$24=2,0,IF(H6=0,0,IF(H5>ConstructPeriod+假设及结论!$C$24,IF(假设及结论!$B$24=1,假设及结论!$M$27*InstalledCapacity*假设及结论!$E$18*(1+CPI)^(H5-1),假设及结论!$G$27*InstalledCapacity*假设及结论!$E$18*(1+CPI)^(H5-1)),IF(假设及结论!$B$24=1,假设及结论!$L$27*InstalledCapacity*假设及结论!$E$18*(1+CPI)^(H5-1),假设及结论!$F$27*InstalledCapacity*假设及结论!$E$18*(1+CPI)^(H5-1)))))) -> 753.0045 | I8: =IF(假设及结论!$D$24=1,IF(I6=0,0,IF(I5>ConstructPeriod+假设及结论!$C$24,IF(假设及结论!$B$24=1,假设及结论!$M$24*InstalledCapacity*(1+CPI)^(I5-1),假设及结论!$G$24*InstalledCapacity*(1+CPI)^(I5-1)),IF(假设及结论!$B$24=1,假设及结论!$L$24*InstalledCapacity*(1+CPI)^(I5-1),假设及结论!$F$24*InstalledCapacity*(1+CPI)^(I5-1)))),IF(假设及结论!$D$24=2,0,IF(I6=0,0,IF(I5>ConstructPeriod+假设及结论!$C$24,IF(假设及结论!$B$24=1,假设及结论!$M$27*InstalledCapacity*假设及结论!$E$18*(1+CPI)^(I5-1),假设及结论!$G$27*InstalledCapacity*假设及结论!$E$18*(1+CPI)^(I5-1)),IF(假设及结论!$B$24=1,假设及结论!$L$27*InstalledCapacity*假设及结论!$E$18*(1+CPI)^(I5-1),假设及结论!$F$27*InstalledCapacity*假设及结论!$E$18*(1+CPI)^(I5-1)))))) -> 753.75751 | J8: =IF(假设及结论!$D$24=1,IF(J6=0,0,IF(J5>ConstructPeriod+假设及结论!$C$24,IF(假设及结论!$B$24=1,假设及结论!$M$24*InstalledCapacity*(1+CPI)^(J5-1),假设及结论!$G$24*InstalledCapacity*(1+CPI)^(J5-1)),IF(假设及结论!$B$24=1,假设及结论!$L$24*InstalledCapacity*(1+CPI)^(J5-1),假设及结论!$F$24*InstalledCapacity*(1+CPI)^(J5-1)))),IF(假设及结论!$D$24=2,0,IF(J6=0,0,IF(J5>ConstructPeriod+假设及结论!$C$24,IF(假设及结论!$B$24=1,假设及结论!$M$27*InstalledCapacity*假设及结论!$E$18*(1+CPI)^(J5-1),假设及结论!$G$27*InstalledCapacity*假设及结论!$E$18*(1+CPI)^(J5-1)),IF(假设及结论!$B$24=1,假设及结论!$L$27*InstalledCapacity*假设及结论!$E$18*(1+CPI)^(J5-1),假设及结论!$F$27*InstalledCapacity*假设及结论!$E$18*(1+CPI)^(J5-1)))))) -> 754.51127 | K8: =IF(假设及结论!$D$24=1,IF(K6=0,0,IF(K5>ConstructPeriod+假设及结论!$C$24,IF(假设及结论!$B$24=1,假设及结论!$M$24*InstalledCapacity*(1+CPI)^(K5-1),假设及结论!$G$24*InstalledCapacity*(1+CPI)^(K5-1)),IF(假设及结论!$B$24=1,假设及结论!$L$24*InstalledCapacity*(1+CPI)^(K5-1),假设及结论!$F$24*InstalledCapacity*(1+CPI)^(K5-1)))),IF(假设及结论!$D$24=2,0,IF(K6=0,0,IF(K5>ConstructPeriod+假设及结论!$C$24,IF(假设及结论!$B$24=1,假设及结论!$M$27*InstalledCapacity*假设及结论!$E$18*(1+CPI)^(K5-1),假设及结论!$G$27*InstalledCapacity*假设及结论!$E$18*(1+CPI)^(K5-1)),IF(假设及结论!$B$24=1,假设及结论!$L$27*InstalledCapacity*假设及结论!$E$18*(1+CPI)^(K5-1),假设及结论!$F$27*InstalledCapacity*假设及结论!$E$18*(1+CPI)^(K5-1)))))) -> 755.26578 | ... AD8: =IF(假设及结论!$D$24=1,IF(AD6=0,0,IF(AD5>ConstructPeriod+假设及结论!$C$24,IF(假设及结论!$B$24=1,假设及结论!$M$24*InstalledCapacity*(1+CPI)^(AD5-1),假设及结论!$G$24*InstalledCapacity*(1+CPI)^(AD5-1)),IF(假设及结论!$B$24=1,假设及结论!$L$24*InstalledCapacity*(1+CPI)^(AD5-1),假设及结论!$F$24*InstalledCapacity*(1+CPI)^(AD5-1)))),IF(假设及结论!$D$24=2,0,IF(AD6=0,0,IF(AD5>ConstructPeriod+假设及结论!$C$24,IF(假设及结论!$B$24=1,假设及结论!$M$27*InstalledCapacity*假设及结论!$E$18*(1+CPI)^(AD5-1),假设及结论!$G$27*InstalledCapacity*假设及结论!$E$18*(1+CPI)^(AD5-1)),IF(假设及结论!$B$24=1,假设及结论!$L$27*InstalledCapacity*假设及结论!$E$18*(1+CPI)^(AD5-1),假设及结论!$F$27*InstalledCapacity*假设及结论!$E$18*(1+CPI)^(AD5-1)))))) -> 0
A9: 4 | B9: 保险费 | C9: =SUM(E9:AD9) -> 19983.552 | D9: =IF(D6=0,0,(资金筹措!$C$7+资金筹措!$C$8-销售收入!$C$38)*假设及结论!$L$33) -> 0 | E9: =IF(E6=0,0,IF(假设及结论!$M$30=1,(资金筹措!$F$7+资金筹措!$F$8-销售收入!$C$38)*假设及结论!$L$33,(资金筹措!$F$7+资金筹措!$F$8-销售收入!$C$38)*E32)) -> 266.44736 | F9: =IF(F6=0,0,IF(假设及结论!$M$30=1,(资金筹措!$F$7+资金筹措!$F$8-销售收入!$C$38)*假设及结论!$L$33,(资金筹措!$F$7+资金筹措!$F$8-销售收入!$C$38)*F32)) -> 266.44736 | G9: =IF(G6=0,0,IF(假设及结论!$M$30=1,(资金筹措!$F$7+资金筹措!$F$8-销售收入!$C$38)*假设及结论!$L$33,(资金筹措!$F$7+资金筹措!$F$8-销售收入!$C$38)*G32)) -> 266.44736 | H9: =IF(H6=0,0,IF(假设及结论!$M$30=1,(资金筹措!$F$7+资金筹措!$F$8-销售收入!$C$38)*假设及结论!$L$33,(资金筹措!$F$7+资金筹措!$F$8-销售收入!$C$38)*H32)) -> 266.44736 | I9: =IF(I6=0,0,IF(假设及结论!$M$30=1,(资金筹措!$F$7+资金筹措!$F$8-销售收入!$C$38)*假设及结论!$L$33,(资金筹措!$F$7+资金筹措!$F$8-销售收入!$C$38)*I32)) -> 266.44736 | J9: =IF(J6=0,0,IF(假设及结论!$M$30=1,(资金筹措!$F$7+资金筹措!$F$8-销售收入!$C$38)*假设及结论!$L$33,(资金筹措!$F$7+资金筹措!$F$8-销售收入!$C$38)*J32)) -> 532.89471 | K9: =IF(K6=0,0,IF(假设及结论!$M$30=1,(资金筹措!$F$7+资金筹措!$F$8-销售收入!$C$38)*假设及结论!$L$33,(资金筹措!$F$7+资金筹措!$F$8-销售收入!$C$38)*K32)) -> 532.89471 | L9: =IF(L6=0,0,IF(假设及结论!$M$30=1,(资金筹措!$F$7+资金筹措!$F$8-销售收入!$C$38)*假设及结论!$L$33,(资金筹措!$F$7+资金筹措!$F$8-销售收入!$C$38)*L32)) -> 532.89471 | ... AD9: =IF(AD6=0,0,IF(假设及结论!$M$30=1,(资金筹措!$F$7+资金筹措!$F$8-销售收入!$C$38)*假设及结论!$L$33,(资金筹措!$F$7+资金筹措!$F$8-销售收入!$C$38)*AD32)) -> 0
A10: 5 | B10: 土地租金 | C10: =SUM(E10:AD10) -> 4038.3252 | E10: =假设及结论!$G$21*假设及结论!$H$21*假设及结论!$I$21/10000 -> 155.3202 | F10: =E10 -> 155.3202 | G10: =F10 -> 155.3202 | H10: =G10 -> 155.3202 | I10: =H10 -> 155.3202 | J10: =I10 -> 155.3202 | K10: =J10 -> 155.3202 | L10: =K10 -> 155.3202 | M10: =L10 -> 155.3202 | ... AD10: =AC10 -> 155.3202
A11: 6 | B11: 土地税 | C11: =SUM(E11:AD11) -> 0 | E11: =假设及结论!$G$21*假设及结论!$L$21*假设及结论!$M$21 -> 0 | F11: =假设及结论!$G$21*假设及结论!$L$21*假设及结论!$M$21 -> 0 | G11: =假设及结论!$G$21*假设及结论!$L$21*假设及结论!$M$21 -> 0 | H11: =假设及结论!$G$21*假设及结论!$L$21*假设及结论!$M$21 -> 0 | I11: =假设及结论!$G$21*假设及结论!$L$21*假设及结论!$M$21 -> 0 | J11: =假设及结论!$G$21*假设及结论!$L$21*假设及结论!$M$21 -> 0 | K11: =假设及结论!$G$21*假设及结论!$L$21*假设及结论!$M$21 -> 0 | L11: =假设及结论!$G$21*假设及结论!$L$21*假设及结论!$M$21 -> 0 | ... AD11: =假设及结论!$G$21*假设及结论!$L$21*假设及结论!$M$21 -> 0
A12: 7 | B12: 销售税
A13: 8 | B13: 到期拆除费 | E13: =IF(E5-ConstructPeriod=OperationPeriod,假设及结论!$O$33*资金筹措!$F$7,0) -> 0 | F13: =IF(F5-ConstructPeriod=OperationPeriod,假设及结论!$O$33*资金筹措!$F$7,0) -> 0 | G13: =IF(G5-ConstructPeriod=OperationPeriod,假设及结论!$O$33*资金筹措!$F$7,0) -> 0 | H13: =IF(H5-ConstructPeriod=OperationPeriod,假设及结论!$O$33*资金筹措!$F$7,0) -> 0 | I13: =IF(I5-ConstructPeriod=OperationPeriod,假设及结论!$O$33*资金筹措!$F$7,0) -> 0 | J13: =IF(J5-ConstructPeriod=OperationPeriod,假设及结论!$O$33*资金筹措!$F$7,0) -> 0 | K13: =IF(K5-ConstructPeriod=OperationPeriod,假设及结论!$O$33*资金筹措!$F$7,0) -> 0 | L13: =IF(L5-ConstructPeriod=OperationPeriod,假设及结论!$O$33*资金筹措!$F$7,0) -> 0 | ... AD13: =IF(AD5-ConstructPeriod=OperationPeriod,假设及结论!$O$33*资金筹措!$F$7,0) -> 0
A14: 9 | B14: 海域使用费 | E14: =IF(type=1,0,IF(E5-ConstructPeriod>0,IF(E5-ConstructPeriod>OperationPeriod,0,假设及结论!$N$33),0)) -> 0 | F14: =IF(type=1,0,IF(F5-ConstructPeriod>0,IF(F5-ConstructPeriod>OperationPeriod,0,假设及结论!$N$33),0)) -> 0 | G14: =IF(type=1,0,IF(G5-ConstructPeriod>0,IF(G5-ConstructPeriod>OperationPeriod,0,假设及结论!$N$33),0)) -> 0 | H14: =IF(type=1,0,IF(H5-ConstructPeriod>0,IF(H5-ConstructPeriod>OperationPeriod,0,假设及结论!$N$33),0)) -> 0 | I14: =IF(type=1,0,IF(I5-ConstructPeriod>0,IF(I5-ConstructPeriod>OperationPeriod,0,假设及结论!$N$33),0)) -> 0 | J14: =IF(type=1,0,IF(J5-ConstructPeriod>0,IF(J5-ConstructPeriod>OperationPeriod,0,假设及结论!$N$33),0)) -> 0 | K14: =IF(type=1,0,IF(K5-ConstructPeriod>0,IF(K5-ConstructPeriod>OperationPeriod,0,假设及结论!$N$33),0)) -> 0 | L14: =IF(type=1,0,IF(L5-ConstructPeriod>0,IF(L5-ConstructPeriod>OperationPeriod,0,假设及结论!$N$33),0)) -> 0 | ... AD14: =IF(type=1,0,IF(AD5-ConstructPeriod>0,IF(AD5-ConstructPeriod>OperationPeriod,0,假设及结论!$N$33),0)) -> 0
A15: 10 | B15: 其他费用 | C15: =SUM(E15:AD15) -> 16146.355 | D15: =IF(假设及结论!$D$24=1,IF(D6=0,0,IF(D5>ConstructPeriod+假设及结论!$C$24,IF(假设及结论!$B$24=1,RIGHT(假设及结论!$Q$24,2)*InstalledCapacity*(1+CPI)^(D5-1),RIGHT(假设及结论!$K$24,2)*InstalledCapacity*(1+CPI)^(D5-1)),IF(假设及结论!$B$24=1,LEFT(假设及结论!$Q$24,2)*InstalledCapacity*(1+CPI)^(D5-1),LEFT(假设及结论!$K$24,2)*InstalledCapacity*(1+CPI)^(D5-1)))),IF(假设及结论!$D$24=2,0,IF(D6=0,0,IF(D5>ConstructPeriod+假设及结论!$C$24,IF(假设及结论!$B$24=1,RIGHT(假设及结论!$Q$27,2)*InstalledCapacity*假设及结论!$E$18*(1+CPI)^(D5-1),RIGHT(假设及结论!$K$27,2)*InstalledCapacity*假设及结论!$E$18*(1+CPI)^(D5-1)),IF(假设及结论!$B$24=1,LEFT(假设及结论!$Q$27,2)*InstalledCapacity*假设及结论!$E$18*(1+CPI)^(D5-1),LEFT(假设及结论!$K$27,2)*InstalledCapacity*假设及结论!$E$18*(1+CPI)^(D5-1)))))) -> 0 | E15: =IF(假设及结论!$D$24=1,IF(E6=0,0,IF(E5>ConstructPeriod+假设及结论!$C$24,IF(假设及结论!$B$24=1,假设及结论!$Q$24*InstalledCapacity*(1+CPI)^(E5-1),假设及结论!$K$24*InstalledCapacity*(1+CPI)^(E5-1)),IF(假设及结论!$B$24=1,假设及结论!$P$24*InstalledCapacity*(1+CPI)^(E5-1),假设及结论!$J$24*InstalledCapacity*(1+CPI)^(E5-1)))),IF(假设及结论!$D$24=2,0,IF(E6=0,0,IF(E5>ConstructPeriod+假设及结论!$C$24,IF(假设及结论!$B$24=1,假设及结论!$Q$27*InstalledCapacity*假设及结论!$E$18*(1+CPI)^(E5-1),假设及结论!$K$27*InstalledCapacity*假设及结论!$E$18*(1+CPI)^(E5-1)),IF(假设及结论!$B$24=1,假设及结论!$P$27*InstalledCapacity*假设及结论!$E$18*(1+CPI)^(E5-1),假设及结论!$J$27*InstalledCapacity*假设及结论!$E$18*(1+CPI)^(E5-1)))))) -> 638.1375 | F15: =IF(假设及结论!$D$24=1,IF(F6=0,0,IF(F5>ConstructPeriod+假设及结论!$C$24,IF(假设及结论!$B$24=1,假设及结论!$Q$24*InstalledCapacity*(1+CPI)^(F5-1),假设及结论!$K$24*InstalledCapacity*(1+CPI)^(F5-1)),IF(假设及结论!$B$24=1,假设及结论!$P$24*InstalledCapacity*(1+CPI)^(F5-1),假设及结论!$J$24*InstalledCapacity*(1+CPI)^(F5-1)))),IF(假设及结论!$D$24=2,0,IF(F6=0,0,IF(F5>ConstructPeriod+假设及结论!$C$24,IF(假设及结论!$B$24=1,假设及结论!$Q$27*InstalledCapacity*假设及结论!$E$18*(1+CPI)^(F5-1),假设及结论!$K$27*InstalledCapacity*假设及结论!$E$18*(1+CPI)^(F5-1)),IF(假设及结论!$B$24=1,假设及结论!$P$27*InstalledCapacity*假设及结论!$E$18*(1+CPI)^(F5-1),假设及结论!$J$27*InstalledCapacity*假设及结论!$E$18*(1+CPI)^(F5-1)))))) -> 638.77564 | G15: =IF(假设及结论!$D$24=1,IF(G6=0,0,IF(G5>ConstructPeriod+假设及结论!$C$24,IF(假设及结论!$B$24=1,假设及结论!$Q$24*InstalledCapacity*(1+CPI)^(G5-1),假设及结论!$K$24*InstalledCapacity*(1+CPI)^(G5-1)),IF(假设及结论!$B$24=1,假设及结论!$P$24*InstalledCapacity*(1+CPI)^(G5-1),假设及结论!$J$24*InstalledCapacity*(1+CPI)^(G5-1)))),IF(假设及结论!$D$24=2,0,IF(G6=0,0,IF(G5>ConstructPeriod+假设及结论!$C$24,IF(假设及结论!$B$24=1,假设及结论!$Q$27*InstalledCapacity*假设及结论!$E$18*(1+CPI)^(G5-1),假设及结论!$K$27*InstalledCapacity*假设及结论!$E$18*(1+CPI)^(G5-1)),IF(假设及结论!$B$24=1,假设及结论!$P$27*InstalledCapacity*假设及结论!$E$18*(1+CPI)^(G5-1),假设及结论!$J$27*InstalledCapacity*假设及结论!$E$18*(1+CPI)^(G5-1)))))) -> 639.41441 | H15: =IF(假设及结论!$D$24=1,IF(H6=0,0,IF(H5>ConstructPeriod+假设及结论!$C$24,IF(假设及结论!$B$24=1,假设及结论!$Q$24*InstalledCapacity*(1+CPI)^(H5-1),假设及结论!$K$24*InstalledCapacity*(1+CPI)^(H5-1)),IF(假设及结论!$B$24=1,假设及结论!$P$24*InstalledCapacity*(1+CPI)^(H5-1),假设及结论!$J$24*InstalledCapacity*(1+CPI)^(H5-1)))),IF(假设及结论!$D$24=2,0,IF(H6=0,0,IF(H5>ConstructPeriod+假设及结论!$C$24,IF(假设及结论!$B$24=1,假设及结论!$Q$27*InstalledCapacity*假设及结论!$E$18*(1+CPI)^(H5-1),假设及结论!$K$27*InstalledCapacity*假设及结论!$E$18*(1+CPI)^(H5-1)),IF(假设及结论!$B$24=1,假设及结论!$P$27*InstalledCapacity*假设及结论!$E$18*(1+CPI)^(H5-1),假设及结论!$J$27*InstalledCapacity*假设及结论!$E$18*(1+CPI)^(H5-1)))))) -> 640.05383 | I15: =IF(假设及结论!$D$24=1,IF(I6=0,0,IF(I5>ConstructPeriod+假设及结论!$C$24,IF(假设及结论!$B$24=1,假设及结论!$Q$24*InstalledCapacity*(1+CPI)^(I5-1),假设及结论!$K$24*InstalledCapacity*(1+CPI)^(I5-1)),IF(假设及结论!$B$24=1,假设及结论!$P$24*InstalledCapacity*(1+CPI)^(I5-1),假设及结论!$J$24*InstalledCapacity*(1+CPI)^(I5-1)))),IF(假设及结论!$D$24=2,0,IF(I6=0,0,IF(I5>ConstructPeriod+假设及结论!$C$24,IF(假设及结论!$B$24=1,假设及结论!$Q$27*InstalledCapacity*假设及结论!$E$18*(1+CPI)^(I5-1),假设及结论!$K$27*InstalledCapacity*假设及结论!$E$18*(1+CPI)^(I5-1)),IF(假设及结论!$B$24=1,假设及结论!$P$27*InstalledCapacity*假设及结论!$E$18*(1+CPI)^(I5-1),假设及结论!$J$27*InstalledCapacity*假设及结论!$E$18*(1+CPI)^(I5-1)))))) -> 640.69388 | J15: =IF(假设及结论!$D$24=1,IF(J6=0,0,IF(J5>ConstructPeriod+假设及结论!$C$24,IF(假设及结论!$B$24=1,假设及结论!$Q$24*InstalledCapacity*(1+CPI)^(J5-1),假设及结论!$K$24*InstalledCapacity*(1+CPI)^(J5-1)),IF(假设及结论!$B$24=1,假设及结论!$P$24*InstalledCapacity*(1+CPI)^(J5-1),假设及结论!$J$24*InstalledCapacity*(1+CPI)^(J5-1)))),IF(假设及结论!$D$24=2,0,IF(J6=0,0,IF(J5>ConstructPeriod+假设及结论!$C$24,IF(假设及结论!$B$24=1,假设及结论!$Q$27*InstalledCapacity*假设及结论!$E$18*(1+CPI)^(J5-1),假设及结论!$K$27*InstalledCapacity*假设及结论!$E$18*(1+CPI)^(J5-1)),IF(假设及结论!$B$24=1,假设及结论!$P$27*InstalledCapacity*假设及结论!$E$18*(1+CPI)^(J5-1),假设及结论!$J$27*InstalledCapacity*假设及结论!$E$18*(1+CPI)^(J5-1)))))) -> 641.33458 | K15: =IF(假设及结论!$D$24=1,IF(K6=0,0,IF(K5>ConstructPeriod+假设及结论!$C$24,IF(假设及结论!$B$24=1,假设及结论!$Q$24*InstalledCapacity*(1+CPI)^(K5-1),假设及结论!$K$24*InstalledCapacity*(1+CPI)^(K5-1)),IF(假设及结论!$B$24=1,假设及结论!$P$24*InstalledCapacity*(1+CPI)^(K5-1),假设及结论!$J$24*InstalledCapacity*(1+CPI)^(K5-1)))),IF(假设及结论!$D$24=2,0,IF(K6=0,0,IF(K5>ConstructPeriod+假设及结论!$C$24,IF(假设及结论!$B$24=1,假设及结论!$Q$27*InstalledCapacity*假设及结论!$E$18*(1+CPI)^(K5-1),假设及结论!$K$27*InstalledCapacity*假设及结论!$E$18*(1+CPI)^(K5-1)),IF(假设及结论!$B$24=1,假设及结论!$P$27*InstalledCapacity*假设及结论!$E$18*(1+CPI)^(K5-1),假设及结论!$J$27*InstalledCapacity*假设及结论!$E$18*(1+CPI)^(K5-1)))))) -> 641.97591 | L15: =IF(假设及结论!$D$24=1,IF(L6=0,0,IF(L5>ConstructPeriod+假设及结论!$C$24,IF(假设及结论!$B$24=1,假设及结论!$Q$24*InstalledCapacity*(1+CPI)^(L5-1),假设及结论!$K$24*InstalledCapacity*(1+CPI)^(L5-1)),IF(假设及结论!$B$24=1,假设及结论!$P$24*InstalledCapacity*(1+CPI)^(L5-1),假设及结论!$J$24*InstalledCapacity*(1+CPI)^(L5-1)))),IF(假设及结论!$D$24=2,0,IF(L6=0,0,IF(L5>ConstructPeriod+假设及结论!$C$24,IF(假设及结论!$B$24=1,假设及结论!$Q$27*InstalledCapacity*假设及结论!$E$18*(1+CPI)^(L5-1),假设及结论!$K$27*InstalledCapacity*假设及结论!$E$18*(1+CPI)^(L5-1)),IF(假设及结论!$B$24=1,假设及结论!$P$27*InstalledCapacity*假设及结论!$E$18*(1+CPI)^(L5-1),假设及结论!$J$27*InstalledCapacity*假设及结论!$E$18*(1+CPI)^(L5-1)))))) -> 642.61789 | ... AD15: =IF(假设及结论!$D$24=1,IF(AD6=0,0,IF(AD5>ConstructPeriod+假设及结论!$C$24,IF(假设及结论!$B$24=1,假设及结论!$Q$24*InstalledCapacity*(1+CPI)^(AD5-1),假设及结论!$K$24*InstalledCapacity*(1+CPI)^(AD5-1)),IF(假设及结论!$B$24=1,假设及结论!$P$24*InstalledCapacity*(1+CPI)^(AD5-1),假设及结论!$J$24*InstalledCapacity*(1+CPI)^(AD5-1)))),IF(假设及结论!$D$24=2,0,IF(AD6=0,0,IF(AD5>ConstructPeriod+假设及结论!$C$24,IF(假设及结论!$B$24=1,假设及结论!$Q$27*InstalledCapacity*假设及结论!$E$18*(1+CPI)^(AD5-1),假设及结论!$K$27*InstalledCapacity*假设及结论!$E$18*(1+CPI)^(AD5-1)),IF(假设及结论!$B$24=1,假设及结论!$P$27*InstalledCapacity*假设及结论!$E$18*(1+CPI)^(AD5-1),假设及结论!$J$27*InstalledCapacity*假设及结论!$E$18*(1+CPI)^(AD5-1)))))) -> 0
A16: 11 | B16: 外委费用 | E16: =IF(假设及结论!$B$24=1,0,假设及结论!$E$24*假设及结论!$F$13) -> 0 | F16: =IF(假设及结论!$B$24=1,0,假设及结论!$E$24*假设及结论!$F$13) -> 0 | G16: =IF(假设及结论!$B$24=1,0,假设及结论!$E$24*假设及结论!$F$13) -> 0 | H16: =IF(假设及结论!$B$24=1,0,假设及结论!$E$24*假设及结论!$F$13) -> 0 | I16: =IF(假设及结论!$B$24=1,0,假设及结论!$E$24*假设及结论!$F$13) -> 0 | J16: =IF(假设及结论!$B$24=1,0,假设及结论!$E$24*假设及结论!$F$13) -> 0 | K16: =IF(假设及结论!$B$24=1,0,假设及结论!$E$24*假设及结论!$F$13) -> 0 | L16: =IF(假设及结论!$B$24=1,0,假设及结论!$E$24*假设及结论!$F$13) -> 0 | ... AD16: =IF(假设及结论!$B$24=1,0,假设及结论!$E$24*假设及结论!$F$13) -> 0
A17: 12 | B17: 经营成本(1~11项合计) | C17: =SUM(C6:C15) -> 89135.997 | D17: =SUM(D6:D15) -> 0 | E17: =SUM(E6:E16) -> 3001.1851 | F17: =SUM(F6:F16) -> 3003.2646 | G17: =SUM(G6:G16) -> 3005.3463 | H17: =SUM(H6:H16) -> 3007.43 | I17: =SUM(I6:I16) -> 3009.5159 | J17: =SUM(J6:J16) -> 3278.0511 | K17: =SUM(K6:K16) -> 3280.1411 | L17: =SUM(L6:L16) -> 3282.2332 | ... AD17: =SUM(AD6:AD16) -> 155.3202
A18: 13 | B18: 折旧费 | C18: =SUM(E18:AD18) -> 202499.99 | D18: =折旧!G8 -> 0 | E18: =折旧!H8 -> 10125 | F18: =折旧!I8 -> 10125 | G18: =折旧!J8 -> 10125 | H18: =折旧!K8 -> 10125 | I18: =折旧!L8 -> 10125 | J18: =折旧!M8 -> 10125 | K18: =折旧!N8 -> 10125 | ... AD18: =折旧!AG8 -> 0
A19: 14 | B19: 摊销 | D19: =摊销!E19 -> 0 | E19: =摊销!F19 -> 0 | F19: =摊销!G19 -> 0 | G19: =摊销!H19 -> 0 | H19: =摊销!I19 -> 0 | I19: =摊销!J19 -> 0 | J19: =摊销!K19 -> 0 | K19: =摊销!L19 -> 0 | ... AD19: =摊销!AE19 -> 0
A20: 15 | B20: 财务费用 | C20: =SUM(E20:AD20) -> 53715.787 | D20: =还本付息!D29 -> 0 | E20: =还本付息!E29 -> 6714.4734 | F20: =还本付息!F29 -> 6266.8418 | G20: =还本付息!G29 -> 5819.2103 | H20: =还本付息!H29 -> 5371.5787 | I20: =还本付息!I29 -> 4923.9472 | J20: =还本付息!J29 -> 4476.3156 | K20: =还本付息!K29 -> 4028.684 | ... AD20: =还本付息!AD29 -> -1.7025741e-12
A21: 16 | B21: 总成本费用合计(13~15合计) | C21: =SUM(E21:AD21) -> 345351.78 | D21: =SUM(D17:D20) -> 0 | E21: =SUM(E17:E20) -> 19840.658 | F21: =SUM(F17:F20) -> 19395.106 | G21: =SUM(G17:G20) -> 18949.556 | H21: =SUM(H17:H20) -> 18504.008 | I21: =SUM(I17:I20) -> 18058.463 | J21: =SUM(J17:J20) -> 17879.366 | K21: =SUM(K17:K20) -> 17433.825 | ... AD21: =SUM(AD17:AD20) -> 155.3202
B22: 其中:固定成本 | D22: =D21-D23 -> 0 | E22: =E21-E23 -> 19089.908 | F22: =F21-F23 -> 18643.605 | G22: =G21-G23 -> 18197.304 | H22: =H21-H23 -> 17751.004 | I22: =I21-I23 -> 17304.705 | J22: =J21-J23 -> 17124.855 | K22: =K21-K23 -> 16678.559 | ... AD22: =AD21-AD23 -> 155.3202
B23: 可变成本 | E23: =E8 -> 750.75 | F23: =F8 -> 751.50075 | G23: =G8 -> 752.25225 | H23: =H8 -> 753.0045 | I23: =I8 -> 753.75751 | J23: =J8 -> 754.51127 | K23: =K8 -> 755.26578 | L23: =L8 -> 756.02104 | ... AD23: =AD8 -> 0
B24: 平均经营成本 （元/kw） | C24: =SUM(E24:AD24)/OperationPeriod -> 47.539198 | E24: =E17/假设及结论!$F13 -> 40.015801 | F24: =F17/假设及结论!$F13 -> 40.043528 | G24: =G17/假设及结论!$F13 -> 40.071284 | H24: =H17/假设及结论!$F13 -> 40.099067 | I24: =I17/假设及结论!$F13 -> 40.126878 | J24: =J17/假设及结论!$F13 -> 43.707348 | K24: =K17/假设及结论!$F13 -> 43.735215 | L24: =L17/假设及结论!$F13 -> 43.763109 | ... AD24: =AD17/假设及结论!$F13 -> 2.070936
B25: 以下采用了累进的维修费测算方式
C27: 合计 | D27: 1 | E27: 2 | F27: 3 | G27: 4 | H27: 5 | I27: 6 | J27: 7 | K27: 8 | L27: 9 | M27: 10 | N27: 11 | O27: 12 | P27: 13 | Q27: 14 | R27: 15 | S27: 16 | T27: 17 | U27: 18 | V27: 19 | W27: 20 | X27: 21 | Y27: 22 | Z27: 23 | AA27: 24 | AB27: 25 | AC27: 26 | AD27: 27
A28: 陆上风电光伏 | B28: 维修费用和材料费用 | C28: =SUM(E28:AD28) -> 37569.077 | E28: =IF(E27<OperationPeriod+1,$C$30*E29,0) -> 932.56575 | F28: =IF(F27<OperationPeriod+1,$C$30*F29,0) -> 932.56575 | G28: =IF(G27<OperationPeriod+1,$C$30*G29,0) -> 932.56575 | H28: =IF(H27<OperationPeriod+1,$C$30*H29,0) -> 932.56575 | I28: =IF(I27<OperationPeriod+1,$C$30*I29,0) -> 932.56575 | J28: =IF(J27<OperationPeriod+1,$C$30*J29,0) -> 1731.9078 | K28: =IF(K27<OperationPeriod+1,$C$30*K29,0) -> 1731.9078 | L28: =IF(L27<OperationPeriod+1,$C$30*L29,0) -> 1731.9078 | ... AD28: =IF(AD27<OperationPeriod+1,$C$30*AD29,0) -> 0
B29: 陆上风场维修费率 | E29: 0.0035 | F29: 0.0035 | G29: 0.0035 | H29: 0.0035 | I29: 0.0035 | J29: 0.0065 | K29: 0.0065 | L29: 0.0065 | M29: 0.0065 | N29: 0.0065 | O29: 0.0065 | P29: 0.0065 | Q29: 0.0065 | R29: 0.0065 | S29: 0.0065 | T29: 0.0065 | U29: 0.0065 | V29: 0.0065 | W29: 0.0065 | X29: 0.0065 | Y29: 0.0065 | Z29: 0.0065 | AA29: 0.0065 | AB29: 0.0065 | AC29: 0.01 | AD29: 0.005
B30: 原值 | C30: =折旧!E7 -> 266447.36
A32: 保险费 | B32: 第一年 0.1%，每五年增加 0.1% | E32: 0.001 | F32: 0.001 | G32: 0.001 | H32: 0.001 | I32: 0.001 | J32: 0.002 | K32: 0.002 | L32: 0.002 | M32: 0.002 | N32: 0.002 | O32: 0.003 | P32: 0.003 | Q32: 0.003 | R32: 0.003 | S32: 0.003 | T32: 0.004 | U32: 0.004 | V32: 0.004 | W32: 0.004 | X32: 0.004 | Y32: 0.005 | Z32: 0.005 | AA32: 0.005 | AB32: 0.005 | AC32: 0.005
A35: 海上风电 | B35: 维修费用 | C35: =SUM(E35:AD35) -> 79934.207 | E35: =IF(E27<OperationPeriod+1,$C$30*E36) -> 2664.4736 | F35: =IF(F27<OperationPeriod+1,$C$30*F36,0) -> 2664.4736 | G35: =IF(G27<OperationPeriod+1,$C$30*G36,0) -> 2664.4736 | H35: =IF(H27<OperationPeriod+1,$C$30*H36,0) -> 2664.4736 | I35: =IF(I27<OperationPeriod+1,$C$30*I36,0) -> 2664.4736 | J35: =IF(J27<OperationPeriod+1,$C$30*J36,0) -> 2664.4736 | K35: =IF(K27<OperationPeriod+1,$C$30*K36,0) -> 3197.3683 | L35: =IF(L27<OperationPeriod+1,$C$30*L36,0) -> 3197.3683 | M35: =IF(M27<OperationPeriod+1,$C$30*M36,0) -> 3197.3683 | ... AD35: =IF(AD27<OperationPeriod+1,$C$30*AD36,0) -> 0
B36: 海上风场维修费率 | E36: 0.01 | F36: 0.01 | G36: 0.01 | H36: 0.01 | I36: 0.01 | J36: 0.01 | K36: 0.012 | L36: 0.012 | M36: 0.012 | N36: 0.012 | O36: 0.012 | P36: 0.012 | Q36: 0.012 | R36: 0.012 | S36: 0.012 | T36: 0.012 | U36: 0.015 | V36: 0.015 | W36: 0.015 | X36: 0.015 | Y36: 0.015 | Z36: 0.015 | AA36: 0.015 | AB36: 0.015 | AC36: 0.015 | AD36: 0.015
B37: 原值 | C37: =折旧!E7 -> 266447.36

Sheet 假设及结论
B2: 风电、光伏及储能电站投资分析模型 （creator：zhangjing™）
B3: 使用说明 模型中只有橙色或者绿色单元格中是手动输入参数。 注：在没有充分理解模型各工作表中数据的勾稽关系的情况下，切勿盲目改动除橙色和绿色之外的其他颜色单元格，否则可能造成模型损坏。
B5: 投资收益指标
B6: 项目总投资 (万元) | C6: ="交流/直流容量 （MW） 容配比 "&TEXT(假设及结论!$F$13/假设及结论!$E$13,"#.##") -> 交流/直流容量 （MW） 容配比 1.25 | D6: 电站造价 （元/W） | E6: 电站总投资 (万元) | F6: 电站EPC 总价 | G6: 资本金 IRR | H6: 资本金NPV | I6: 资本金投资回收期(年) | J6: 平均年收入 | K6: 平均年净利润 | L6: 建设期利息 | M6: 总投资收益率(ROI) | N6: 投资利税率 | O6: 平均净资产收益率ROE | P6: 折现率 WACC | Q6: 电价含税与否 (增值税和销售税)
B7: =$B$13 -> 267947.36 | C7: =$E$13*10&" / "&$F$13*10 -> 600 / 750 | D7: =$C$13/$F$13/1000 -> 3.355328 | E7: =$C$13 -> 251649.6 | F7: =C15 -> 247200 | G7: =资本金现金流!$E$27 -> 0.21052865 | H7: =资本金现金流!E28 -> 138383.91 | I7: =资本金现金流!E29 -> 5.9132682 | J7: =(销售收入!C6)/OperationPeriod -> 37600.975 | K7: =损益表!C14/H13 -> 21800.838 | L7: =资金筹措!$F$8 -> 3315.4619 | M7: =损益表!C26/TotalInvestment/(OperationPeriod+ConstructPeriod) -> 0.091721253 | N7: =(损益表!C6-损益表!C9)/TotalInvestment/(OperationPeriod+ConstructPeriod) -> 0.085360138 | O7: =资产负债表!C32 -> 0.0768366 | P7: =WACC -> 0.06825 | Q7: NO
B8: 首年小时数 (小时) | C8: 储能比例/配置小时数 | D8: 储能投资单价 (元/wh) | E8: 储能总投资 （万元） | F8: 储能EPC 总价 | G8: 全投资 IRR | H8: 全投资NPV | I8: 全投资回收期(年) | J8: LCOE= (初期投资-因折旧导致的税费减免现值+因项目运营导致的成本的现值-固定资产残值的现值) / (发电量的现值） | L8: 度电投资LCOE | M8: 项目总投资 | N8: 因折旧导致的税费减免的现值 | O8: 因项目运营导致的成本的现值 | P8: 固定资产残值的现值 | Q8: 发电量现值
B9: =$I$13 -> 1545 | C9: =$E$18*100&"% / "&$D$18&"小时" -> 30% / 1小时 | D9: =IF($D$18=0,0,$B$18/$F$13/$D$18/$E$18/1000) -> 0.70449032 | E9: =B18 -> 15851.032 | F9: =E15 -> 15404.307 | G9: =全部投资现金流!$E$27 -> 0.11599219 | H9: =全部投资现金流!E29 -> 107966.84 | I9: =全部投资现金流!E31 -> 8.6708866 | L9: =(M9-N9+O9-P9)/Q9 -> 0.22946726 | M9: =B13 -> 267947.36 | N9: =NPV(WACC,折旧!H22:AG22) -> 7114.9236 | O9: =NPV(WACC,总成本!E17:AD17)+NPV(WACC,总成本!E20:AD20) -> 78074.18 | P9: =NPV(WACC,折旧!H21:AG21) -> 59861.798 | Q9: =NPV(WACC,销售收入!E11:AD11)+NPV(WACC,销售收入!E15:AD15)+NPV(WACC,销售收入!E19:AD19)+NPV(WACC,销售收入!E26:AD26) -> 1216055
B10: 核心基础假设
B11: 基础部分 | I11: 电量和电价
B12: 项目总投资 (万元) | C12: 电站总投资 (万元) | D12: 陆上、储能 = 1 海上 = 2 | E12: ="交流侧容量 （万千瓦） 容配比 "&TEXT($F$13/$E$13,"#.##") -> 交流侧容量 （万千瓦） 容配比 1.25 | F12: 直流侧容量 （万千瓦） | G12: 建设期(年) 陆上/光伏=1年 海上=2年 | H12: 运营期(年) | I12: 首年小时数 (小时) | J12: 实际发电 小时数 (小时) | K12: 政策性保障小时数规定 (小时) | L12: 实际保障小时数 (小时) | M12: 电力辅助服务费(元/kwh) | N12: 储能等效小时数 (小时) | O12: 市场化交易小时数 (小时) | P12: 实际超发小时数 (小时) | Q12: 过网费 (元/kwh)
B13: =C13+B18+D15 -> 267947.36 | C13: =C15+B15 -> 251649.6 | D13: 1 | E13: 60 | F13: 75 | G13: 1 | H13: 25 | I13: 1545 | J13: =I13*(1+$R$33)*(1+$Q$15) -> 1529.55 | K13: 1545 | L13: =IF(I13=0,0,IF(J13-K13>N13,K13,K13-(N13-(J13-K13)))) -> 1424.55 | M13: 0 | N13: =I18*E18 -> 105 | O13: =IF(J13-K13-N13>0,IF(J13-K13-N13>J13-K13,J13-K13,J13-K13-N13),0) -> 0 | P13: =IF(J13-K13>N13,J13-K13-N13-O13,0) -> 0 | Q13: 0
B14: 电站 业主管理费 (EPC价*1.8%) | C14: 电站EPC 总价 | D14: 储能 业主管理费 (EPC价*2.9%) | E14: 储能EPC 总价 | F14: 补贴开始从第N年 | G14: 补贴持续 | H14: 综合电价 (元/kwh) | I14: 核准电价 (元/kwh) | J14: 标杆电价 (元/kwh) | K14: 补贴电价 (元/kwh) | L14: 保障电价 (元/kwh) | M14: 保障电价 下浮比例要求 | N14: 储能电价 (元/kwh) 按市场化价格 | O14: 市场化交易电价 (元/kwh) | P14: 超发电价 (元/kwh) | Q14: 线损率
B15: =C15*MID(B14,16,4) -> 4449.6 | C15: 247200 | D15: =E15*MID(D14,16,4) -> 446.72491 | E15: =$B$18*(1+$P$33)/(1+MID($D$14,16,4)) -> 15404.307 | F15: 1 | G15: 25 | H15: =L15*L13/J13+N15*N13/J13+O15*O13/J13+P15*P13/J13 -> 0.35 | I15: 0.35 | J15: 0.35 | K15: =I15-J15 -> 0 | L15: =J15*(1-M15)*(1+$Q$33)+K15-M13-Q13 -> 0.35 | M15: 0 | N15: =L15 -> 0.35 | O15: 0.35 | P15: 0.35 | Q15: 0
B16: 储能投资参数
B17: 储能 全寿命期投资 （万元） | C17: 储能初始投资(元/wh) | D17: 储能配置小时数 | E17: 储能比例 | F17: 储能天/年 | G17: 电池技术 | H17: 储能设备可利用小时数 | I17: 储能年利用小时数 | J17: 电芯更换次数 | K17: 更换成本 (元/wh) | L17: 单次更换成本金额(万元) | M17: 更换成本折现投资金额 | N17: 储能电价 | O17: 儲能效率 | P17: 容量租赁比例 | Q17: 容量租赁价格 (元/wh)
B18: =E13*C18*D18*E18*1000+M18 -> 15851.032 | C18: 0.8 | D18: 1 | E18: 0.3 | F18: 350 | G18: 磷酸铁锂 | H18: 6000 | I18: =F18*D18 -> 350 | J18: =IF(D18=0,0,H13/(H18/I18)) -> 1.4583333 | K18: 0.25 | L18: =E13*K18*D18*E18*1000 -> 4500 | M18: =IF(D18=0,0,L18*INT(J18)/((1+WACC)^(H18/I18))+L18*(INT(J18)-1)/((1+WACC)^OperationPeriod)) -> 1451.0322 | N18: =N15 -> 0.35 | O18: 0.85 | P18: 0.85 | Q18: 0
B19: 風電/光伏 运维人员参数 | G19: 土地补偿款及租金 + 汇率 | L19: 土地税基单价和土地税率 | N19: 光伏板衰减 | P19: 首年小时数 年平均小时数
B20: 每50MW运营自维维护人数 | C20: 每50MW运营外维维护人数 | D20: 员工人数 | E20: 人均工资 （万元） | F20: 福利占比 | G20: 项目占地 （公顷） | H20: 年租金标准 （美元/公顷） | I20: 汇率 US$ / ￥ | J20: 土地补偿标准 （US$ /公顷） | K20: 土地补偿款 | L20: 单位土地税基 (￥/sq.m) | M20: 土地税率 | N20: 第一年末 | O20: 后续年衰减 | P20: 首年小时数 | Q20: 平均小时数
B21: 1.3 | C21: 1 | D21: =IF($B$24=1,ROUND(B21*IF(type=1,F13/5,F13/5*3),0),ROUND(C21*IF(type=1,F13/5,F13/5*3),0)) -> 20 | E21: 15.62 | F21: 0.6 | G21: 1232.7 | H21: 180 | I21: 7 | J21: =272 -> 272 | K21: =G21*J21/10000 -> 33.52944 | L21: 0 | M21: 0.01 | N21: 0.01 | O21: 0.004 | P21: =I13 -> 1545 | Q21: =$P$21*(1+(1-$N$21)+(1-$N$21)*(1-$O$21)*(1-(1-$O$21)^($H$13-2))/$O$21)/$H$13 -> 1464.5634
B22: 运维模式及维修费计算模式 | E22: 風電光伏外委模式费用参数 | L22: 風電光伏自维模式费用参数
B23: 1 自维 2 外委 | C23: 质保期(年) | D23: 1 定额 2 比例 3 仅儲能 | E23: 外委年费用 (元/kw) | F23: 质保期内 材料费 (元/kw) | G23: 质保期外 材料费 (元/kw) | H23: 质保期内 维修费 (元/kw) | I23: 质保期外 维修费 (元/kw) | J23: 其他费 质保期内 (元/KW) | K23: 其他费 质保期外 (元/KW) | L23: 质保期内 材料费 (元/kw) | M23: 质保期外 材料费 (元/kw) | N23: 质保期内 维修费 (元/kw) | O23: 质保期外 维修费 (元/kw) | P23: 其他费 质保期内 (元/KW) | Q23: 其他费 质保期外 (元/KW)
B24: 1 | C24: 0 | D24: 1 | E24: 0 | F24: 0.225 | G24: 0.47 | H24: 0.262 | I24: 2.081 | J24: 30 | K24: 50 | L24: 10 | M24: 10 | N24: 4 | O24: 9.2 | P24: 3 | Q24: 8.5
B25: 儲能運維人員 | E25: 儲能外委模式费用参数 | L25: 儲能自维模式费用参数
B26: 每100MWh运营自维维护人数 | C26: 每100MW运营外维维护人数 | D26: 员工人数 | E26: 外委年费用 (元/kw) | F26: 质保期内 材料费 (元/kw) | G26: 质保期外 材料费 (元/kw) | H26: 质保期内 维修费 (元/kw) | I26: 质保期外 维修费 (元/kw) | J26: 其他费 质保期内 (元/KW) | K26: 其他费 质保期内/外 (元/KW) | L26: 质保期内 材料费 (元/kw) | M26: 质保期外 材料费 (元/kw) | N26: 质保期内 维修费 (元/kw) | O26: 质保期外 维修费 (元/kw) | P26: 其他费 质保期内 (元/KW) | Q26: 其他费 质保期外 (元/KW)
B27: 10 | C27: 0 | D27: =IF($B$24=1,ROUND(B27*IF(type=1,F13*E18/10,F13*E18/5*3),0),ROUND(C27*IF(type=1,F13*E18/10,F13*E18/10*3),0)) -> 23 | E27: 0 | F27: 0.225 | G27: 0.47 | H27: 0.262 | I27: 2.081 | J27: 30 | K27: 50 | L27: 4.5 | M27: 11.3 | N27: 5.24 | O27: 49.62 | P27: 15 | Q27: 28
B28: 各项税率 | N28: 融资参数
B29: 所得税率 | C29: 所得税有/无三免三减半政策 | D29: 所得税优惠年限 | E29: 反税基侵蚀补税/预扣税 | F29: 城市维护建设费率 | G29: 教育附加费率 | H29: 增值税率 | I29: 增值税豁免年限 | J29: 增值税抵扣返还50% | K29: 销售税率 | L29: 销售税优惠年限 | M29: 保险费方式 1.固定定额 2.自定比率 | N29: 流动资金 贷款利率 | O29: 贷款期限 | P29: 项目 贷款利率 | Q29: 资本金比例 | R29: 还款方式 1 等额本息 2 等额本金
B30: 0.1 | C30: NO | D30: 10 | E30: 0.05 | F30: 0 | G30: 0 | H30: 0.12 | I30: 25 | J30: NO | K30: 0.01 | L30: 10 | M30: 2 | N30: 0.0345 | O30: 15 | P30: 0.036 | Q30: 0.3 | R30: 2
B31: 固定资产及设备 | G31: 折旧参数 | I31: 财产税 | K31: 其他税率 | N31: 海上风电专有参数 | P31: 敏感性波动
B32: 流动资金(￥/kw) 光伏/陆上=20 海上=25 | C32: 固定资产 | D32: 每千瓦投资 | E32: 每千瓦设备采购价 | F32: 设备占比 | G32: 折旧年限(年) | H32: 折旧残值 | I32: 税基 | J32: 税率 | K32: 通货膨胀率 CPI | L32: 保险费率 | M32: 法定盈余公积金比例 | N32: 海域使用费 (万元/年) | O32: 到期拆除费占固定资产比例 | P32: 总投资波动 | Q32: 电价波动 | R32: 小时数波动
B33: =IF(Q30>50%,0,IF(type=1,$F$13*MID($B$32,18,2),$F$13*MID($B$32,24,2))) -> 1500 | C33: =资金筹措!F7+资金筹措!F8 -> 266447.36 | D33: =B13/F13 -> 3572.6314 | E33: 2448 | F33: =E33/D33 -> 0.68520922 | G33: 25 | H33: 0.05 | I33: 租赁协议 | J33: 0.01 | K33: 0.001 | L33: 0.005 | M33: 0.1 | N33: 0 | O33: 0 | P33: 0 | Q33: 0 | R33: -0.01
B36: 风电价格政策 | P36: 省级电网 | Q36: 燃煤发电标杆上网电价
B37: 风区 | C37: 覆盖范围 | J37: 电价 | P37: 蒙西 | Q37: 0.2772 | R37: =Q37/$I$21 -> 0.0396
J38: 2015 | K38: 2016 | L38: 2018 | M38: 2019 | N38: 2020 | P38: 新疆 | Q38: 0.25 | R38: =Q38/$I$21 -> 0.035714286
B39: 第I类风能资源区 | C39: 内蒙古自治区除赤峰市、通辽市、兴安盟、呼伦贝尔市以外的其他地区; 新疆维吾尔自治区乌鲁木齐市、伊犁哈萨克族自治州、克拉玛依市、石河子市; | J39: 0.51 | K39: 0.47 | L39: 0.4 | M39: 0.34 | N39: 0.29 | P39: 蒙东 | Q39: 0.3035 | R39: =Q39/$I$21 -> 0.043357143
B40: 第II类风能资源区 | C40: 河北省张家口市、承德市; 内蒙古自治区赤峰市、通辽市、兴安盟、呼伦贝尔市; 甘肃嘉峪关市、酒泉市; 云南省 | J40: 0.54 | K40: 0.5 | L40: 0.45 | M40: 0.39 | N40: 0.34 | P40: 云南 | Q40: 0.3358 | R40: =Q40/$I$21 -> 0.047971429
B41: 第III类风能资源区 | C41: 吉林省白城市、松原市; 黑龙江省鸡西市、双鸭山市、七台河市、绥化市、伊春市、大兴安岭地区; 甘肃省除嘉峪关市、酒泉市以外的其他地区; 新疆维吾尔自治区除乌鲁木齐市、伊犁哈萨克族自治州、克拉玛依市、石河子市以外的其他地区; 宁夏回族自治区; | J41: 0.58 | K41: 0.54 | L41: 0.49 | M41: 0.43 | N41: 0.38 | P41: 冀北 | Q41: 0.3634 | R41: =Q41/$I$21 -> 0.051914286
B42: 第IV类风能资源区 | C42: 除前三类资源区以外的其他地区。 | J42: 0.61 | K42: 0.6 | L42: 0.57 | M42: 0.52 | N42: 0.47 | P42: 甘肃 | Q42: 0.2978 | R42: =Q42/$I$21 -> 0.042542857
P43: 吉林 | Q43: 0.3717 | R43: =Q43/$I$21 -> 0.0531
B44: 光伏价格政策 | P44: 黑龙江 | Q44: 0.3723 | R44: =Q44/$I$21 -> 0.053185714
B45: 风区 | C45: 覆盖范围 | E45: 电价 | P45: 宁夏 | Q45: 0.2595 | R45: =Q45/$I$21 -> 0.037071429
E46: 2015年 | F46: 2016年 | I46: 2017年 | J46: 2018年 | K46: 2019年 | L46: 2020年 | P46: 山西 | Q46: 0.3205 | R46: =Q46/$I$21 -> 0.045785714
B47: 第I类地区 | C47: 宁夏,青海海西,甘肃嘉峪关、武威、张掖、酒泉、敦煌、金昌,新疆哈密、塔城、阿勒泰、克拉玛依,内蒙古除赤峰、通辽、兴安盟、呼伦贝尔以外地区 | E47: 0.9 | F47: 0.8 | I47: 0.65 | J47: =I47-0.03 -> 0.62 | K47: =J47-0.03 -> 0.59 | L47: =K47-0.03 -> 0.56 | P47: 青海 | Q47: 0.3247 | R47: =Q47/$I$21 -> 0.046385714
B48: 第II类地区 | C48: 北京,天津,黑龙江,吉林,辽宁,四川,云南,内蒙古赤峰、通辽、兴安盟、呼伦贝尔,河北承德、张家口、唐山、秦皇岛,山西大同、朔州、忻州,陕西榆林、延安,青海、甘肃、新疆除I类外其他地区 | E48: 0.95 | F48: 0.88 | I48: 0.75 | J48: =I48-0.03 -> 0.72 | K48: =J48-0.03 -> 0.69 | L48: =K48-0.03 -> 0.66 | P48: 陕西 | Q48: 0.3346 | R48: =Q48/$I$21 -> 0.0478
B49: 第III类地区 | C49: 除I类、II类资源区以外的其他地区 | E49: 1 | F49: 0.98 | I49: 0.85 | J49: =I49-0.02 -> 0.83 | K49: =J49-0.02 -> 0.81 | L49: =K49-0.02 -> 0.79 | P49: 贵州 | Q49: 0.3363 | R49: =Q49/$I$21 -> 0.048042857
P50: 冀南 | Q50: 0.3497 | R50: =Q50/$I$21 -> 0.049957143
P51: 天津 | Q51: 0.3514 | R51: =Q51/$I$21 -> 0.0502
P52: 北京 | Q52: 0.3515 | R52: =Q52/$I$21 -> 0.050214286
P53: 河南 | Q53: 0.3551 | R53: =Q53/$I$21 -> 0.050728571
P54: 辽宁 | Q54: 0.3685 | R54: =Q54/$I$21 -> 0.052642857
P55: 安徽 | Q55: 0.3693 | R55: =Q55/$I$21 -> 0.052757143
P56: 山东 | Q56: 0.3729 | R56: =Q56/$I$21 -> 0.053271429
P57: 福建 | Q57: 0.3737 | R57: =Q57/$I$21 -> 0.053385714
P58: 江苏 | Q58: 0.378 | R58: =Q58/$I$21 -> 0.054
P59: 重庆 | Q59: 0.3796 | R59: =Q59/$I$21 -> 0.054228571
P60: 湖北 | Q60: 0.3981 | R60: =Q60/$I$21 -> 0.056871429
P61: 江西 | Q61: 0.3993 | R61: =Q61/$I$21 -> 0.057042857
... P68: 广东 | Q68: 0.4505 | R68: =Q68/$I$21 -> 0.064357143

Sheet WACC
B2: 吉尔吉斯巴特肯600MW光伏项目 · WACC测算（全部人民币贷款情形）
B3: 前提：债务全部采用人民币贷款（Rd=4.5%，5Y LPR 3.5%＋境外风险）；收入/现金流同步按人民币口径或已作汇率对冲。黄色＝输入可改，灰色＝公式。
B5: 【输入参数】
B6: 资本金比例 E/V | C6: =假设及结论!Q30 -> 0.3
B7: 负债比例 D/V | C7: =1-C6 -> 0.7
B8: 企业所得税率 Tc（吉尔吉斯，前10年减免期可改0） | C8: =假设及结论!B30 -> 0.1
B9: 行业无杠杆β βu（光伏0.31~0.46，取0.40） | C9: 0.4
B10: 无风险利率 rRF（人民币/中10Y，2026-08） | C10: 0.017
B11: 成熟市场股权风险溢价 ERP | C11: 0.05
B12: 吉尔吉斯国家风险溢价 CRP（主权B3，5Y欧元债利差~415bp×1.3） | C12: 0.054
B13: 债务成本 Rd（人民币贷款，5Y LPR 3.5%+境外风险） | C13: 0.045
B15: 【测算结果（公式自动计算）】
B16: 再杠杆β βL = βu×[1+(1−Tc)×D/E] | C16: =C9*(1+(1-C8)*C7/C6) -> 1.24
B17: 权益成本 Re（人民币） = rRF+βL×ERP+CRP | C17: =C10+C16*C11+C12 -> 0.133
B18: 税后债务成本 Rd×(1−Tc) | C18: =C13*(1-C8) -> 0.0405
B19: WACC（全部人民币贷款）★ = E/V×Re+D/V×Rd×(1−Tc) | C19: =C6*C17+C7*C18 -> 0.06825
B20: 结论：全部人民币贷款可大幅降低融资成本，WACC 由美元融资的 9.3% 降至约 6.8%（降幅约 2.5 个百分点）。前提是收入/成本已人民币化或已对冲汇率；若 PPA 仍锚定美元而债务全为人民币，存在币种错配，应附加汇率敏感性并计入套保成本。
B22: 【对比：美元融资(基准) vs 全人民币融资】
B23: 参数 | C23: 美元融资(基准·主表) | D23: 全人民币融资
B24: 无风险利率 rRF | C24: =[1]WACC测算!B9 -> 0.047 | D24: =C10 -> 0.017
B25: 再杠杆β βL | C25: =[1]WACC测算!B17 -> 1.24 | D25: =C16 -> 1.24
B26: 权益成本 Re | C26: =[1]WACC测算!B18 -> 0.163 | D26: =C17 -> 0.133
B27: 债务成本 Rd | C27: =[1]WACC测算!B13 -> 0.07 | D27: =C13 -> 0.045
B28: 税后债务成本 Rd×(1−Tc) | C28: =[1]WACC测算!B20 -> 0.063 | D28: =C18 -> 0.0405
B29: WACC ★ | C29: =[1]WACC测算!B22 -> 0.093 | D29: =C19 -> 0.06825
B32: 敏感性：WACC（全人民币融资）随 Rd(人民币) 与 CRP 变化
B33: Rd↓ / CRP→ | D33: 0.03 | E33: 0.04 | F33: 0.054 | G33: 0.06 | H33: 0.07
B34: Rd=3.5% | C34: 0.035 | D34: =$C$6*($C$10+$C$16*$C$11+D$33)+$C$7*$C34*(1-$C$8) -> 0.05475 | E34: =$C$6*($C$10+$C$16*$C$11+E$33)+$C$7*$C34*(1-$C$8) -> 0.05775 | F34: =$C$6*($C$10+$C$16*$C$11+F$33)+$C$7*$C34*(1-$C$8) -> 0.06195 | G34: =$C$6*($C$10+$C$16*$C$11+G$33)+$C$7*$C34*(1-$C$8) -> 0.06375 | H34: =$C$6*($C$10+$C$16*$C$11+H$33)+$C$7*$C34*(1-$C$8) -> 0.06675
B35: Rd=4.0% | C35: 0.04 | D35: =$C$6*($C$10+$C$16*$C$11+D$33)+$C$7*$C35*(1-$C$8) -> 0.0579 | E35: =$C$6*($C$10+$C$16*$C$11+E$33)+$C$7*$C35*(1-$C$8) -> 0.0609 | F35: =$C$6*($C$10+$C$16*$C$11+F$33)+$C$7*$C35*(1-$C$8) -> 0.0651 | G35: =$C$6*($C$10+$C$16*$C$11+G$33)+$C$7*$C35*(1-$C$8) -> 0.0669 | H35: =$C$6*($C$10+$C$16*$C$11+H$33)+$C$7*$C35*(1-$C$8) -> 0.0699
B36: Rd=4.5% | C36: 0.045 | D36: =$C$6*($C$10+$C$16*$C$11+D$33)+$C$7*$C36*(1-$C$8) -> 0.06105 | E36: =$C$6*($C$10+$C$16*$C$11+E$33)+$C$7*$C36*(1-$C$8) -> 0.06405 | F36: =$C$6*($C$10+$C$16*$C$11+F$33)+$C$7*$C36*(1-$C$8) -> 0.06825 | G36: =$C$6*($C$10+$C$16*$C$11+G$33)+$C$7*$C36*(1-$C$8) -> 0.07005 | H36: =$C$6*($C$10+$C$16*$C$11+H$33)+$C$7*$C36*(1-$C$8) -> 0.07305
B37: Rd=5.0% | C37: 0.05 | D37: =$C$6*($C$10+$C$16*$C$11+D$33)+$C$7*$C37*(1-$C$8) -> 0.0642 | E37: =$C$6*($C$10+$C$16*$C$11+E$33)+$C$7*$C37*(1-$C$8) -> 0.0672 | F37: =$C$6*($C$10+$C$16*$C$11+F$33)+$C$7*$C37*(1-$C$8) -> 0.0714 | G37: =$C$6*($C$10+$C$16*$C$11+G$33)+$C$7*$C37*(1-$C$8) -> 0.0732 | H37: =$C$6*($C$10+$C$16*$C$11+H$33)+$C$7*$C37*(1-$C$8) -> 0.0762
B38: Rd=5.5% | C38: 0.055 | D38: =$C$6*($C$10+$C$16*$C$11+D$33)+$C$7*$C38*(1-$C$8) -> 0.06735 | E38: =$C$6*($C$10+$C$16*$C$11+E$33)+$C$7*$C38*(1-$C$8) -> 0.07035 | F38: =$C$6*($C$10+$C$16*$C$11+F$33)+$C$7*$C38*(1-$C$8) -> 0.07455 | G38: =$C$6*($C$10+$C$16*$C$11+G$33)+$C$7*$C38*(1-$C$8) -> 0.07635 | H38: =$C$6*($C$10+$C$16*$C$11+H$33)+$C$7*$C38*(1-$C$8) -> 0.07935
B40: 注：基准组合 Rd=4.5%、CRP=5.4% → WACC≈6.8%。若人民币对美元贬值10%，相当于美元口径下融资成本上升，建议另做汇率敏感性。

Sheet 敏感性分析
E2: 敏感性分析基准数据
E3: 补贴从运营期 第N年开始 | F3: 1 | G3: 含税电价 | H3: =假设及结论!I15 -> 0.35
E4: 总投资投资 | F4: =假设及结论!B13 -> 267947.36 | G4: 小时数 | H4: =假设及结论!I13 -> 1545
G5: 全投资IRR | H5: 资本金IRR
G6: =假设及结论!G9 -> 0.11599219 | H6: =假设及结论!G7 -> 0.21052865
E8: 项目敏感性分析 | K8: 项目核心经营数据
E9: 项目 | F9: 变化 | G9: 全投资内部收益率 | H9: 资本金内部收益率 | K9: 序号 | L9: 项目名称 | M9: 运营 | N9: 运营 | O9: 运营 | P9: 运营 | Q9: 运营 | R9: 运营期
E10: 基本方案 | G10: =IF(AND($F$4=假设及结论!$B$13,$H$3=假设及结论!$I$15,$H$4=假设及结论!$I$13,F3=假设及结论!F15),G6,G10) -> 0.11599219 | H10: =IF(AND($F$4=假设及结论!$B$13,$H$3=假设及结论!$I$15,$H$4=假设及结论!$I$13,F3=假设及结论!F15),H6,H10) -> 0.21052865 | M10: 第1年 | N10: 第2年 | O10: 第3年 | P10: 第4年 | Q10: 第5年 | R10: 年均
F11: 0.1 | G11: =IF((1+F11)*$F$4=假设及结论!$B$13,$G$6,$G11) -> #REF! | H11: =IF((1+F11)*$F$4=假设及结论!$B$13,$H$6,$H11) -> #REF! | K11: 1 | L11: 总收入 | M11: =IF(AND($F$4=假设及结论!$B$13,$H$3=假设及结论!$I$15,$H$4=假设及结论!$I$13,假设及结论!$F$15=1,假设及结论!$G$15=OperationPeriod),销售收入!E6,M11) -> 39737.25 | N11: =IF(AND($F$4=假设及结论!$B$13,$H$3=假设及结论!$I$15,$H$4=假设及结论!$I$13,假设及结论!$F$15=1,假设及结论!$G$15=OperationPeriod),销售收入!F6,N11) -> 39339.878 | O11: =IF(AND($F$4=假设及结论!$B$13,$H$3=假设及结论!$I$15,$H$4=假设及结论!$I$13,假设及结论!$F$15=1,假设及结论!$G$15=OperationPeriod),销售收入!G6,O11) -> 39180.929 | P11: =IF(AND($F$4=假设及结论!$B$13,$H$3=假设及结论!$I$15,$H$4=假设及结论!$I$13,假设及结论!$F$15=1,假设及结论!$G$15=OperationPeriod),销售收入!H6,P11) -> 39021.98 | Q11: =IF(AND($F$4=假设及结论!$B$13,$H$3=假设及结论!$I$15,$H$4=假设及结论!$I$13,假设及结论!$F$15=1,假设及结论!$G$15=OperationPeriod),销售收入!I6,Q11) -> 38863.031 | R11: =IF(AND($F$4=假设及结论!$B$13,$H$3=假设及结论!$I$15,$H$4=假设及结论!$I$13,假设及结论!$F$15=1,假设及结论!$G$15=OperationPeriod),SUM(销售收入!E6:AD6)/OperationPeriod,R11) -> 37600.975
E12: 投资总额 | F12: 0.05 | G12: =IF((1+F12)*$F$4=假设及结论!$B$13,$G$6,$G12) -> #REF! | H12: =IF((1+F12)*$F$4=假设及结论!$B$13,$H$6,$H12) -> #REF! | K12: 2 | L12: 净利润 | M12: =IF(AND($F$4=假设及结论!$B$13,$H$3=假设及结论!$I$15,$H$4=假设及结论!$I$13,假设及结论!$F$15=1,假设及结论!$G$15=OperationPeriod),损益表!E14,M12) -> 19499.219 | N12: =IF(AND($F$4=假设及结论!$B$13,$H$3=假设及结论!$I$15,$H$4=假设及结论!$I$13,假设及结论!$F$15=1,假设及结论!$G$15=OperationPeriod),损益表!F14,N12) -> 19551.373 | O12: =IF(AND($F$4=假设及结论!$B$13,$H$3=假设及结论!$I$15,$H$4=假设及结论!$I$13,假设及结论!$F$15=1,假设及结论!$G$15=OperationPeriod),损益表!G14,O12) -> 19839.563 | P12: =IF(AND($F$4=假设及结论!$B$13,$H$3=假设及结论!$I$15,$H$4=假设及结论!$I$13,假设及结论!$F$15=1,假设及结论!$G$15=OperationPeriod),损益表!H14,P12) -> 20127.751 | Q12: =IF(AND($F$4=假设及结论!$B$13,$H$3=假设及结论!$I$15,$H$4=假设及结论!$I$13,假设及结论!$F$15=1,假设及结论!$G$15=OperationPeriod),损益表!I14,Q12) -> 20415.938 | R12: =IF(AND($F$4=假设及结论!$B$13,$H$3=假设及结论!$I$15,$H$4=假设及结论!$I$13,假设及结论!$F$15=1),SUM(损益表!E14:AD14)/OperationPeriod,R12) -> 21800.838
E13: 变化 | F13: -0.05 | G13: =IF((1+F13)*$F$4=假设及结论!$B$13,$G$6,$G13) -> #REF! | H13: =IF((1+F13)*$F$4=假设及结论!$B$13,$H$6,$H13) -> #REF! | K13: 3 | L13: EVA | M13: =IF(AND($F$4=假设及结论!$B$13,$H$3=假设及结论!$I$15,$H$4=假设及结论!$I$13,$F$3=假设及结论!$F$15),损益表!E37,M13) -> 9032.9628 | N13: =IF(AND($F$4=假设及结论!$B$13,$H$3=假设及结论!$I$15,$H$4=假设及结论!$I$13,$F$3=假设及结论!$F$15),损益表!F37,N13) -> 9489.5007 | O13: =IF(AND($F$4=假设及结论!$B$13,$H$3=假设及结论!$I$15,$H$4=假设及结论!$I$13,$F$3=假设及结论!$F$15),损益表!G37,O13) -> 10197.38 | P13: =IF(AND($F$4=假设及结论!$B$13,$H$3=假设及结论!$I$15,$H$4=假设及结论!$I$13,$F$3=假设及结论!$F$15),损益表!H37,P13) -> 10905.257 | Q13: =IF(AND($F$4=假设及结论!$B$13,$H$3=假设及结论!$I$15,$H$4=假设及结论!$I$13,$F$3=假设及结论!$F$15),损益表!I37,Q13) -> 11613.132 | R13: =IF(AND($F$4=假设及结论!$B$13,$H$3=假设及结论!$I$15,$H$4=假设及结论!$I$13,$F$3=假设及结论!$F$15),SUM(损益表!E37:AD37)/OperationPeriod,R13) -> 15781.91
F14: -0.1 | G14: =IF((1+F14)*$F$4=假设及结论!$B$13,$G$6,$G14) -> #REF! | H14: =IF((1+F14)*$F$4=假设及结论!$B$13,$H$6,$H14) -> #REF! | K14: 4 | L14: 净现金流 | M14: =IF(AND($F$4=假设及结论!$B$13,$H$3=假设及结论!$I$15,$H$4=假设及结论!$I$13,$F$3=假设及结论!$F$15),资本金现金流!D21,M14) -> 16215.048 | N14: =IF(AND($F$4=假设及结论!$B$13,$H$3=假设及结论!$I$15,$H$4=假设及结论!$I$13,$F$3=假设及结论!$F$15),资本金现金流!E21,N14) -> 16264.594 | O14: =IF(AND($F$4=假设及结论!$B$13,$H$3=假设及结论!$I$15,$H$4=假设及结论!$I$13,$F$3=假设及结论!$F$15),资本金现金流!F21,O14) -> 16538.374 | P14: =IF(AND($F$4=假设及结论!$B$13,$H$3=假设及结论!$I$15,$H$4=假设及结论!$I$13,$F$3=假设及结论!$F$15),资本金现金流!G21,P14) -> 16812.153 | Q14: =IF(AND($F$4=假设及结论!$B$13,$H$3=假设及结论!$I$15,$H$4=假设及结论!$I$13,$F$3=假设及结论!$F$15),资本金现金流!H21,Q14) -> 17085.93 | R14: =IF(AND($F$4=假设及结论!$B$13,$H$3=假设及结论!$I$15,$H$4=假设及结论!$I$13,$F$3=假设及结论!$F$15),SUM(资本金现金流!D21:AC21)/OperationPeriod,R14) -> 21350.27
F15: -0.05 | G15: =IF((1+F15)*$H$3=假设及结论!$I$15,$G$6,$G15) -> 0 | H15: =IF((1+F15)*$H$3=假设及结论!$I$15,$H$6,$H15) -> 0
E16: 上网电价 | F16: -0.1 | G16: =IF((1+F16)*$H$3=假设及结论!$I$15,$G$6,$G16) -> 0 | H16: =IF((1+F16)*$H$3=假设及结论!$I$15,$H$6,$H16) -> 0 | K16: 吉尔吉斯斯坦 600MW 光伏经济性测算(电价 = 5美分/kwh)
E17: 变化 | F17: -0.15 | G17: =IF((1+F17)*$H$3=假设及结论!$I$15,$G$6,$G17) -> 0 | H17: =IF((1+F17)*$H$3=假设及结论!$I$15,$H$6,$H17) -> 0 | K17: 总投资 （万元） | L17: 电站EPC （万元） | M17: 储能投资（万元） | O17: 全投资 IRR | P17: 资本金 IRR | Q17: 备注
F18: -0.2 | G18: =IF((1+F18)*$H$3=假设及结论!$I$15,$G$6,$G18) -> 0 | H18: =IF((1+F18)*$H$3=假设及结论!$I$15,$H$6,$H18) -> 0 | M18: 储能小时数 | N18: 储能投资
F19: 0.1 | G19: =IF((1+F19)*$H$4=假设及结论!$I$13,$G$6,$G19) -> #NUM! | H19: =IF((1+F19)*$H$4=假设及结论!$I$13,$H$6,$H19) -> #NUM! | K19: 285040 | L19: 280000 | M19: - | N19: 无储能 | O19: 0.11704399 | P19: 0.27006473 | Q19: EPC = 28亿时
E20: 利用小时数 | F20: 0.05 | G20: =IF((1+F20)*$H$4=假设及结论!$I$13,$G$6,$G20) -> #NUM! | H20: =IF((1+F20)*$H$4=假设及结论!$I$13,$H$6,$H20) -> #NUM! | K20: 363200 | L20: 356778 | M20: - | N20: 无储能 | O20: 0.085029657 | P20: 0.15598482 | Q20: 全投资IRR=8.5%时
E21: 变化 | F21: -0.05 | G21: =IF((1+F21)*$H$4=假设及结论!$I$13,$G$6,$G21) -> #NUM! | H21: =IF((1+F21)*$H$4=假设及结论!$I$13,$H$6,$H21) -> #NUM!
F22: -0.1 | G22: =IF((1+F22)*$H$4=假设及结论!$I$13,$G$6,$G22) -> #NUM! | H22: =IF((1+F22)*$H$4=假设及结论!$I$13,$H$6,$H22) -> #NUM! | M22: ="带储能 "&假设及结论!E18*100&"%" -> 带储能 30%
K23: 305281.43 | L23: 280000 | M23: 1 | N23: 19686.605 | O23: 0.11165487 | P23: 0.23734029 | Q23: 电站EPC=28亿时
K24: 395259.51 | L24: 368762.28 | M24: 1 | N24: 19315.16 | O24: 0.084977548 | P24: 0.1489434 | Q24: 全投资IRR=8.5%时反算
K25: 379559.51 | L25: 353339.88 | M25: 1 | N25: 19315.16 | O25: 0.09001488 | P25: 0.16371686 | Q25: 全投资IRR=9.0%时反算
K26: 351459.51 | L26: 325736.74 | M26: 1 | N26: 19315.16 | O26: 0.099956916 | P26: 0.19475027 | Q26: 全投资IRR=8.5%时反算
K28: 计算：
K29: =假设及结论!B$7 -> 267947.36 | L29: =假设及结论!F7 -> 247200 | M29: =IF(假设及结论!D18=0,"无储能",假设及结论!D18) -> 1 | N29: =假设及结论!E9 -> 15851.032 | O29: =假设及结论!$G$9 -> 0.11599219 | P29: =假设及结论!$G$7 -> 0.21052865
K31: 吉尔吉斯斯坦 600MW 光伏经济性测算(电价 = 5美分/kwh 不含税)
K32: 总投资 （万元） | L32: 电站EPC （万元） | M32: 储能投资（万元） | O32: 全投资 IRR | P32: 资本金 IRR | Q32: 备注
M33: 储能小时数 | N33: 储能投资
I34: 电价优惠期 15年 | K34: 395259.51 | L34: 368762.28 | M34: 1 | N34: 19315.16 | O34: 0.084977548 | P34: 0.1489434 | Q34: 全投资IRR=8.5%时反算
K35: 379559.51 | L35: 353339.88 | M35: 1 | N35: 19315.16 | O35: 0.09001488 | P35: 0.16371686 | Q35: 全投资IRR=9.0%时反算
K36: 351459.51 | L36: 325736.74 | M36: 1 | N36: 19315.16 | O36: 0.099956916 | P36: 0.19475027 | Q36: 全投资IRR=8.5%时反算
I38: 电价优惠期 25年 | K38: =假设及结论!B$7 -> 267947.36 | L38: =假设及结论!F16 -> 0 | M38: =IF(假设及结论!D27=0,"无储能",假设及结论!D27) -> 23 | N38: =假设及结论!E18 -> 0.3 | O38: =假设及结论!G$9 -> 0.11599219 | P38: =假设及结论!G$7 -> 0.21052865
K39: 325413.02 | L39: 280000 | M39: 2 | N39: 39266.387 | O39: 0.086259101 | P39: 0.15211259 | Q39: 电站EPC=28亿时
K40: 327841.43 | L40: 302161.1 | M40: 1 | N40: 19686.605 | O40: 0.084976184 | P40: 0.15006293 | Q40: 全投资IRR=8.5%时反算
K41: 328873.02 | L41: 283398.82 | M41: 2 | N41: 39266.387 | O41: 0.084961806 | P41: 0.14838457 | Q41: 全投资IRR=8.5%时反算
K44: 总投资 （万元） | L44: 电站EPC （万元） | M44: 储能投资（万元） | O44: 全投资 IRR | P44: 资本金 IRR | Q44: 备注
M45: 储能小时数 | N45: 储能投资
K46: =假设及结论!B$7 -> 267947.36

Sheet 11院EPC价
A1: 吉尔吉斯斯坦780兆瓦光伏发电项目EPC报价
A2: 序号 Serial number | B2: 项目名称 Item Name | C2: 型号规格 Type And Specification | D2: 单位 Unit | E2: 数量 Quantity | F2: 单价(元) Unit Price(yuan) | G2: 合价（万元） Combined price(ten thousand yuan) | H2: 单瓦（元/瓦） Unit price per watt (yuan/watt)
A3: 一 I | B3: 主要设备材料采购费 Purchase cost of major equipment and materials
A4: 1 | B4: 光伏组件 PV modules | C4: 720Wp-PERC单晶双面电池组件、满足IEC标准/TUV认证 720Wp-PERC single-crystal double-sided PV module, meet the IEC standard /TUV certification | D4: Wp | E4: 750000000 | F4: 0.9 | G4: =F4*E4/10000 -> 67500 | H4: =G4/$E$4*10000 -> 0.9
A5: 2 | B5: 箱变 | C5: 35KV、IP65、效率大于99%、满足IEC标准/TUV认证 35KV, IP65, efficiency greater than 99%, meet the IEC standard /TUV certification | D5: Wp | E5: 750000000 | F5: 0.1 | G5: =F5*E5/10000 -> 7500 | H5: =G5/$E$4*10000 -> 0.1
A6: 3 | B6: 逆变器 | D6: Wp | E6: 750000000 | F6: 0.13 | G6: =F6*E6/10000 -> 9750 | H6: =G6/$E$4*10000 -> 0.13
A7: 4 | B7: 支架 bracket | C7: Q355B、Q235B锌镁铝 Q355B, Q235B Zinc magnesium aluminum | D7: Wp | E7: 750000000 | F7: 0.24 | G7: =F7*E7/10000 -> 18000 | H7: =G7/$E$4*10000 -> 0.24
A8: 5 | B8: 桩基础 Pile foundation | D8: Wp | E8: 750000000 | F8: 0.09 | G8: =F8*E8/10000 -> 6750 | H8: =G8/$E$4*10000 -> 0.09
A9: 6 | B9: 电缆 Cables | C9: 光伏电缆（铜1*4mm²）、低压直流（铝合金）、高压电缆（铝合金） 、光纤 Photovoltaic cable (copper 1*4mm²), low voltage DC (aluminum alloy), high voltage cable (aluminum alloy), optical fiber | D9: Wp | E9: 750000000 | F9: 0.23 | G9: =F9*E9/10000 -> 17250 | H9: =G9/$E$4*10000 -> 0.23
A10: 7 | B10: 光伏区通讯及视频监控 Communication and video monitoring in PV area | C10: 安装及调试 Installation and commissioning | D10: Wp | E10: 750000000 | F10: 0.01 | G10: =F10*E10/10000 -> 750 | H10: =G10/$E$4*10000 -> 0.01
B11: 小计 Subtotal price | G11: =SUM(G4:G10) -> 127500 | H11: =G11/$E$4*10000 -> 1.7
A12: 二 II | B12: 光伏区施工 Construction of PV area
A13: 1 | B13: 测量放点 Measurement and setting out | D13: Wp | E13: 750000000 | F13: 0.005 | G13: =F13*E13/10000 -> 375 | H13: =G13/$E$4*10000 -> 0.005
A14: 2 | B14: 土建基础施工 Civil foundation construction | C14: 桩基础施工 pile foundation construction | D14: Wp | E14: 750000000 | F14: 0.07 | G14: =F14*E14/10000 -> 5250 | H14: =G14/$E$4*10000 -> 0.07
A15: 3 | B15: 设备安装 Equipment installation | C15: 支架、组件、汇流箱、一体机 Bracket, modules, combiner box,box transformer and inverter integrated machine | D15: Wp | E15: 750000000 | F15: 0.21 | G15: =F15*E15/10000 -> 15750 | H15: =G15/$E$4*10000 -> 0.21 | I15: 0.3
A16: 4 | B16: 电气安装 Electric installation | C16: 电缆敷设、接地系统 Cable laying and grounding system | D16: Wp | E16: 750000000 | F16: 0.13 | G16: =F16*E16/10000 -> 9750 | H16: =G16/$E$4*10000 -> 0.13
A17: 5 | B17: 调试及试验 Commissioning and testing | C17: 光伏区设备材料、调试及预防性试验费 Commissioning and preventive test fees for equipment and materials in PV area | D17: Wp | E17: 750000000 | F17: 0.01 | G17: =F17*E17/10000 -> 750 | H17: =G17/$E$4*10000 -> 0.01
A18: 6 | B18: 设备基础等土建工程 Equipment foundation and other civil works | C18: 箱逆变一体机等土建工程 foundation of box transformer and inverter integrated machine and other civil works | D18: Wp | E18: 750000000 | F18: 0.008 | G18: =F18*E18/10000 -> 600 | H18: =G18/$E$4*10000 -> 0.008
A19: 7 | B19: 光伏区围栏 Fence for PV area | C19: 1.8m高浸塑围栏、丝径2.2mm 1.8m high dip plastic fence, with wire diameter of 2.2mm | D19: Wp | E19: 750000000 | F19: 0.008 | G19: =F19*E19/10000 -> 600 | H19: =G19/$E$4*10000 -> 0.008
A20: 8 | B20: 光伏区道路 Road in PV area | C20: 场区检修道路（4m宽砂石道路） Site maintenance road (4m wide gravel road) | D20: Wp | E20: 750000000 | F20: 0.01 | G20: =F20*E20/10000 -> 750 | H20: =G20/$E$4*10000 -> 0.01
A21: 9 | B21: 施工辅材 Construction auxiliary material | C21: 桥架、线管、防火泥、防火封堵等 Cable Tray, line pipe, fire mud, fire sealing, etc | D21: Wp | E21: 750000000 | F21: 0.035 | G21: =F21*E21/10000 -> 2625 | H21: =G21/$E$4*10000 -> 0.035
A22: 10 | B22: 试桩 trial pile | D22: 项 Item | E22: 1 | F22: 2300000 | G22: =F22*E22/10000 -> 230 | H22: =G22/$E$4*10000 -> 0.0030666667
A23: 11 | B23: 临建设施 Temporary construction facilities | C23: 现场办公区、生活区及水、电、油、网等 Water, electricity, oil, Internet, and other facilities for on-site office area and living area | D23: 项 Item | E23: 1 | F23: 12000000 | G23: =F23*E23/10000 -> 1200 | H23: =G23/$E$4*10000 -> 0.016
A24: 12 | B24: 安全文明措施费 Safety and civilization measures expense | D24: 项 Item | E24: 1 | F24: 6000000 | G24: =F24*E24/10000 -> 600 | H24: =G24/$E$4*10000 -> 0.008
B25: 小计 Subtotal price | G25: =SUM(G13:G24) -> 38480 | H25: =G25/$E$4*10000 -> 0.51306667
A26: 三 III | B26: 升压站及送出工程 Engineering of booster station and power transmission lines
A27: 1 | B27: 500kV 升压站 500kV booster station | C27: 2*290MVA主变，总容量580MW、主变等电气设备满足IEC标准 | D27: 座 | E27: 1 | F27: =0.235*750000000 -> 176250000 | G27: =F27*E27/10000 -> 17625 | H27: =G27/$E$4*10000 -> 0.235
A28: 2 | B28: 220kV 升压站 220kV booster station | C28: 2*290MVA主变，总容量580MW、主变等电气设备满足IEC标准 | D28: 座 | E28: 1 | F28: =0.14*750000000 -> 105000000 | G28: =F28*E28/10000 -> 10500 | H28: =G28/$E$4*10000 -> 0.14
A29: 3 | B29: 送出工程 Power transmission lines | C29: 500kv线路 | D29: km | E29: 1 | F29: 5000000 | G29: =F29*E29/10000 -> 500 | H29: =G29/$E$4*10000 -> 0.0066666667
A30: 4 | B30: 送出工程 Power transmission lines | C30: 220kv线路 | D30: km | E30: 1 | F30: 3000000 | G30: =F30*E30/10000 -> 300 | H30: =G30/$E$4*10000 -> 0.004
A31: 5 | B31: 调试试验费 Commissioning and testing fee | D31: 项 Item | E31: 1 | F31: 8000000 | G31: =F31*E31/10000 -> 800 | H31: =G31/$E$4*10000 -> 0.010666667
B32: 小计 Subtotal price | G32: =SUM(G27:G31) -> 29725 | H32: =G32/$E$4*10000 -> 0.39633333
A33: 四 IV | B33: 勘察设计费 Survey and design expenses
A34: 1 | B34: 地勘、测绘 Geological surveying and mapping | D34: Wp | E34: 750000000 | F34: 0.005 | G34: =F34*E34/10000 -> 375 | H34: =G34/$E$4*10000 -> 0.005
A35: 2 | B35: 光伏区设计 Design of PV area | D35: Wp | E35: 750000000 | F35: 0.02 | G35: =F35*E35/10000 -> 1500 | H35: =G35/$E$4*10000 -> 0.02
A36: 3 | B36: 500kV和220kv升压站设计 Design of 500kV booster station | D36: Wp | E36: 750000000 | F36: 0.023 | G36: =F36*E36/10000 -> 1725 | H36: =G36/$E$4*10000 -> 0.023
A37: 4 | B37: 转图费用 | D37: Wp | E37: 750000000 | F37: 0.02 | G37: =F37*E37/10000 -> 1500 | H37: =G37/$E$4*10000 -> 0.02
A38: 5 | B38: 线路设计 Design of power transmission lines | D38: 项 Item | E38: 1 | G38: 300 | H38: =G38/$E$4*10000 -> 0.004
B39: 小计 Subtotal price | G39: =SUM(G34:G38) -> 5400 | H39: =G39/$E$4*10000 -> 0.072
A40: 五 V | B40: 其他 Others
A41: 1 | B41: 手续审批 | D41: Wp | E41: 750000000 | F41: 0.2 | G41: =F41*E41/10000 -> 15000 | H41: =G41/$E$4*10000 -> 0.2
A42: 2 | B42: 征林征地及补偿 | D42: Wp | E42: 750000000 | F42: 0.1 | G42: =F42*E42/10000 -> 7500 | H42: =G42/$E$4*10000 -> 0.1
A43: 3 | B43: 水土保持 | D43: Wp | E43: 750000000 | F43: 0.15 | G43: =F43*E43/10000 -> 11250 | H43: =G43/$E$4*10000 -> 0.15
A44: 4 | B44: 场外道路 | D44: Wp | E44: 750000000 | F44: 0.1 | G44: =F44*E44/10000 -> 7500 | H44: =G44/$E$4*10000 -> 0.1
A45: 5 | B45: 保险费 Insurance expenses | C45: 建筑工程一切险、团意险 Construction All Risks Insurance and Group Accident Insurance | D45: 项 Item | E45: 1 | G45: 700 | H45: =G45/$E$4*10000 -> 0.0093333333
A46: 6 | B46: 公司管理费 Home office overheads | D46: 项 Item | E46: 1 | G46: 3850 | H46: =G46/$E$4*10000 -> 0.051333333
A47: 7 | B47: 现场管理费 Field overhead | D47: 项 Item | E47: 1 | G47: 3200 | H47: =G47/$E$4*10000 -> 0.042666667
A48: 8 | B48: 履约保函费用 Charge for issuing performance security | D48: 项 Item | E48: 1 | G48: 300 | H48: =G48/$E$4*10000 -> 0.004
A49: 9 | B49: 税务法务咨询服务费 Consulting service fee | D49: 项 Item | E49: 1 | G49: 500 | H49: =G49/$E$4*10000 -> 0.0066666667
A50: 10 | B50: 税金 Taxes | C50: 中国境内税务成本 Tax costs in China | D50: 项 Item | E50: 1 | G50: 3500 | H50: =G50/$E$4*10000 -> 0.046666667
B51: 小计 Subtotal price | G51: =SUM(G41:G50) -> 53300 | H51: =G51/$E$4*10000 -> 0.71066667
A52: 六 | B52: 运费
B53: 运费 | D53: 项 Item | E53: 1 | G53: 24850 | H53: =G53/$E$4*10000 -> 0.33133333
A54: 七 | B54: 总计Total Price | G54: =G51+G39+G32+G25+G53+G11 -> 279255 | H54: =G54/$E$4*10000 -> 3.7234
G58: =G54-SUM(G41:G44) -> 238005 | H58: =G58/$E$4*10000 -> 3.1734

Sheet 决策信息模版
C5: ="吉尔吉斯斯坦共和国 - "&假设及结论!E13*10&"MW光伏发电项目投资构成情况 Kyrgyzstan Investment composition of photovoltaic power generation projects "&"IRR="&TEXT($E$11*100,"#,##.#0")&"%, 电价持续 Electricity prices continue= "&假设及结论!G15&" 年" -> 吉尔吉斯斯坦共和国 - 600MW光伏发电项目投资构成情况 Kyrgyzstan Investment composition of photovoltaic power generation projects IRR=11.60%, 电价持续 Electricity prices continue= 25 年
C6: unit：Chinese Yuan USD 1= 7 Yuan
C7: 1 项目测算情况 Project measurements | D7: ="交流/直流容量 （MW） 容配比 "&"AC/DC capacity "&TEXT(假设及结论!$F$13/假设及结论!$E$13,"#.##") -> 交流/直流容量 （MW） 容配比 AC/DC capacity 1.25 | E7: ="电价 Electrictity Prie "&IF(假设及结论!$Q$7="NO","(不含税)","(含税)")&" (US$/kwh)" -> 电价 Electrictity Prie (不含税) (US$/kwh) | F7: 首年小时数 The rist hours of Electricity (小时) | G7: 储能比例 EnergyStorageRatio /配置小时数 Hours | H7: DSCR need >1.25 偿债备付率 （min/average） | I7: 项目占地 lands （Hectare 公顷） | J7: 年租金标准 Aanual Rent Fee (US$/Hectare) | K7: 土地补偿标准 Land compensation （US$ /Hectare）
D8: =假设及结论!$C$7 -> 600 / 750 | E8: =假设及结论!$I$15/假设及结论!$I$21 -> 0.05 | F8: =假设及结论!$B$9 -> 1545 | G8: =假设及结论!$C$9 -> 30% / 1小时 | H8: {=ROUND(SMALL(IF(还本付息!$E$33:$AD$33<>0,还本付息!$E$33:$AD$33),1),3)&" / "&ROUND(SUM(还本付息!$E$33:$AD$33)/DebtPeriod,3)} -> 1.898 / 2.131 | I8: =假设及结论!$G$21 -> 1232.7 | J8: =假设及结论!$H$21 -> 180 | K8: =假设及结论!$J$21 -> 272
D10: 项目总投资 total project investment (￥10,000 万元) | E10: 全投资 Total Investment IRR | F10: 资本金 Equity IRR | G10: 其中： 电站总投资 Total Investment (￥10,000 万元) | H10: 其中： 储能总投资 Energy Storage Investment （￥10,000 万元） | I10: 储能动态投资造价 Energy storage dynamic investment cost (￥/wh) | J10: 电站动态 投资造价 电站动态 （￥/W） | K10: 平均运维成本 Average operation and maintenance cost （￥/KW）
D11: =假设及结论!$B$7 -> 267947.36 | E11: =全部投资现金流!$E$27 -> 0.11599219 | F11: =资本金现金流!$E$27 -> 0.21052865 | G11: =假设及结论!$E$7 -> 251649.6 | H11: =假设及结论!$E$9 -> 15851.032 | I11: =假设及结论!$D$9 -> 0.70449032 | J11: =假设及结论!$D$7 -> 3.355328 | K11: =总成本!C24 -> 47.539198
D12: ="测算总投资 estimated total investment：当收益率为Calculate the total investment: when the rate of return is "&TEXT($E$11*100,"##0.00")&"% ，总投资为The total investment is（1）" -> 测算总投资 estimated total investment：当收益率为Calculate the total investment: when the rate of return is 11.60% ，总投资为The total investment is（1） | J12: =D11 -> 267947.36
C14: 2 建设期利息和业主管理费 Construction period interest and owner management fees | D14: a | E14: 建设期利息 Interest during construction period | I14: =J14/假设及结论!$F$13/1000 -> 0.044206158 | J14: =资金筹措!C8 -> 3315.4619
D15: b | E15: 业主管理费（含电站+储能）Owner management fee (including power station + energy storage) | I15: =J15/假设及结论!$F$13/1000 -> 0.065284332 | J15: =假设及结论!B15+假设及结论!D15 -> 4896.3249
D16: c | E16: 流动资金 working capital | I16: =J16/假设及结论!$F$13/1000 -> 0.02 | J16: =财务计划!$C$25 -> 1500
D17: d | E17: 融资费 Financing fee | I17: =J17/假设及结论!$F$13/1000 -> 0.14921052 | J17: =RIGHT($K$17,3)*资金筹措!$F$16 -> 11190.789 | K17: ="国内融资担保公司要求Requirements for domestic financing guarantee companies "&6%*100&"%" -> 国内融资担保公司要求Requirements for domestic financing guarantee companies 6%
D18: e | I18: =J18/假设及结论!$F$13/1000 -> 0
E19: 结余 balance = (1) - (2) = | G19: =J12-J19 -> 247044.78 | H19: =MID($C$14,6,63)&" 合计（2）" -> 利息和业主管理费 Construction period interest and owner management fees 合计（2） | J19: =SUM(J14:J18) -> 20902.576 | K19: ="总包合同金额 & 造价"&"General Contract Amount & Cost "&ROUND(G19/假设及结论!$F$13/1000,2)&"yuan/w" -> 总包合同金额 & 造价General Contract Amount & Cost 3.29yuan/w
C21: 3 前期开发阶段 pre-development stage | E21: 内容 | I21: 单价 Price | K21: 备注 Note
D22: a | E22: 负责项目在吉尔吉斯斯坦境内的所有审批手续办理 Responsible for all approvals and formalities for the project in Kyrgyzstan | I22: 0.15 | J22: =I22*假设及结论!$F$13*1000 -> 11250 | K22: 技术开发费 Technology development fee
D23: b | E23: 协助阿克然公司办理手续，提供商务、经济分析支撑 Assist Akran Company to handle procedures and provide business and economic analysis support | I23: 0.05 | J23: =I23*假设及结论!$F$13*1000 -> 3750 | K23: 技术开发费 Technology development fee
D24: c | J24: =I24*假设及结论!$F$13*1000 -> 0
D25: d | I25: =J25/假设及结论!$F$13/1000 -> 0
E26: 结余 balance = (1) - (2) - (3) = | G26: =G19-J26 -> 232044.78 | H26: =MID($C$21,2,40)&" 合计（3）" -> 前期开发阶段 pre-development stage 合计（3） | J26: =SUM(J22:J25) -> 15000 | K26: 技术开发费总额 Total of Technology development fee
C28: 4 EPC 总包工程部分 EPC general contracting project part | D28: a | E28: 光伏组件 Photovoltaic modules PV modules | I28: 0.71 | J28: =I28*假设及结论!$F$13*1000 -> 53250
D29: b | E29: 箱变 Box transformer | I29: 0.1 | J29: =I29*假设及结论!$F$13*1000 -> 7500
D30: c | E30: 逆变器 inverter | I30: 0.11 | J30: =I30*假设及结论!$F$13*1000 -> 8250
D31: d | E31: 支架 Bracket | I31: 0.13 | J31: =I31*假设及结论!$F$13*1000 -> 9750
D32: e | E32: 桩基础 pile foundation | I32: 0.09 | J32: =I32*假设及结论!$F$13*1000 -> 6750
D33: f | E33: 电缆 Cable | I33: 0.2 | J33: =I33*假设及结论!$F$13*1000 -> 15000
D34: g | E34: 通讯及监控 Communication and monitoring | I34: 0.01 | J34: =I34*假设及结论!$F$13*1000 -> 750
D35: h | E35: 设备安装 、Equipment installation | I35: 0.145 | J35: =I35*假设及结论!$F$13*1000 -> 10875
D36: i | E36: 电气安装 Electrical installation | I36: 0.1 | J36: =I36*假设及结论!$F$13*1000 -> 7500
D37: j | E37: 调试及试验 Debugging and testing | I37: 0.005 | J37: =I37*假设及结论!$F$13*1000 -> 375
D38: k | E38: 设备基础等土建工程 Equipment foundation and other civil engineering projects | I38: 0.008 | J38: =I38*假设及结论!$F$13*1000 -> 600
D39: l | E39: 光伏区围栏 Photovoltaic area fence | I39: 0.008 | J39: =I39*假设及结论!$F$13*1000 -> 600
D40: m | E40: 升压站 booster station | I40: 0.346 | J40: =I40*假设及结论!$F$13*1000 -> 25950
D41: n | E41: 储能系统和工程 Energy Storage Systems and Engineering | I41: 0.747 | J41: =I41*假设及结论!$F$13*1000*LEFT(G8,3) -> 16807.5
D42: o | E42: 勘察设计 survey and design | I42: 0.05 | J42: =I42*假设及结论!$F$13*1000 -> 3750
D43: p | E43: 运费 freight | I43: 0.2 | J43: =I43*假设及结论!$F$13*1000 -> 15000
D44: q | E44: 境内税务成本 Domestic tax costs | I44: 0.047 | J44: =I44*假设及结论!$F$13*1000 -> 3525
D45: r | E45: 其他 others | I45: 0.458 | J45: =I45*假设及结论!$F$13*1000 -> 34350
D46: s | J46: =I46*假设及结论!$F$13*1000 -> 0
E47: 结余 balance= (1) - (2) - (3) - (4) = | G47: =G26-J47 -> 11462.281 | H47: =MID($C$28,2,50)&" 合计（4）" -> EPC 总包工程部分 EPC general contracting project part 合计（4） | J47: =SUM(J28:J46) -> 220582.5 | K47: ="总包工程金额 Total project contract amount& 造价 construction cost "&ROUND(J47/假设及结论!$F$13/1000,2)&"yuan/w" -> 总包工程金额 Total project contract amount& 造价 construction cost 2.94yuan/w

Sheet 决策信息模版 (2)
C5: ="吉尔吉斯斯坦共和国 - "&假设及结论!E13*10&"MW光伏发电项目投资构成情况 Kyrgyzstan Investment composition of photovoltaic power generation projects "&"IRR="&TEXT($E$11*100,"#,##.#0")&"%, 电价持续 Electricity prices continue= "&假设及结论!G15&" 年" -> 吉尔吉斯斯坦共和国 - 600MW光伏发电项目投资构成情况 Kyrgyzstan Investment composition of photovoltaic power generation projects IRR=11.60%, 电价持续 Electricity prices continue= 25 年
C6: unit：Chinese Yuan/￥ USD 1= 7 Yuan
C7: 1 项目测算情况 Project measurements | D7: ="交流/直流容量 （MW） 容配比 "&"AC/DC capacity "&TEXT(假设及结论!$F$13/假设及结论!$E$13,"#.##") -> 交流/直流容量 （MW） 容配比 AC/DC capacity 1.25 | E7: ="电价 Electrictity Prie "&IF(假设及结论!$Q$7="NO","(不含税)","(含税)")&" (US$/kwh)" -> 电价 Electrictity Prie (不含税) (US$/kwh) | F7: 首年小时数 The rist hours of Electricity (小时) | G7: 储能比例 EnergyStorageRatio /配置小时数 Hours | H7: DSCR need >1.25 偿债备付率 （min/average） | I7: 项目占地 lands （Hectare 公顷） | J7: 年租金标准 Aanual Rent Fee (US$/Hectare) | K7: 土地补偿标准 Land compensation （US$ /Hectare）
D8: =假设及结论!$C$7 -> 600 / 750 | E8: =假设及结论!$I$15/假设及结论!$I$21 -> 0.05 | F8: =假设及结论!$B$9 -> 1545 | G8: =假设及结论!$C$9 -> 30% / 1小时 | H8: {=ROUND(SMALL(IF(还本付息!$E$33:$AD$33<>0,还本付息!$E$33:$AD$33),1),3)&" / "&ROUND(SUM(还本付息!$E$33:$AD$33)/DebtPeriod,3)} -> 1.898 / 2.131 | I8: =假设及结论!$G$21 -> 1232.7 | J8: =假设及结论!$H$21 -> 180 | K8: =假设及结论!$J$21 -> 272
D10: 项目总投资 total project investment (￥1,000 千元) | E10: 全投资 Total Investment IRR | F10: 资本金 Equity IRR | G10: 其中： 电站总投资 Total Investment (￥1,000 千元) | H10: 其中： 储能总投资 Battery Energy Storage System Investment （￥1,000 千元） | I10: 储能动态投资造价 Energy storage dynamic investment cost (￥/wh) | J10: 电站动态 投资造价 电站动态 （￥/W） | K10: 平均运维成本 Average operation and maintenance cost （￥/KW）
D11: =假设及结论!$B$7*10 -> 2679473.6 | E11: =全部投资现金流!$E$27 -> 0.11599219 | F11: =资本金现金流!$E$27 -> 0.21052865 | G11: =假设及结论!$E$7*10 -> 2516496 | H11: =假设及结论!$E$9*10 -> 158510.32 | I11: =假设及结论!$D$9 -> 0.70449032 | J11: =假设及结论!$D$7 -> 3.355328 | K11: =总成本!C24 -> 47.539198
D12: ="测算总投资 Estimated total investment：当收益率为Calculate the total investment: when the rate of return is "&TEXT($E$11*100,"##0.00")&"% ，总投资为The total investment is（1）" -> 测算总投资 Estimated total investment：当收益率为Calculate the total investment: when the rate of return is 11.60% ，总投资为The total investment is（1） | J12: =D11 -> 2679473.6
C14: 2 建设期利息和业主管理费 Construction period interest and owner management fees | D14: a | E14: 建设期利息 Interest during construction period | I14: =J14/假设及结论!$F$13/1000 -> 0.44206158 | J14: =资金筹措!C8*10 -> 33154.619 | K14: k yuan=￥1,000=CNY 1,000
D15: b | E15: 业主管理费（含电站+储能）Owner management fee (including power station + energy storage) | I15: =J15/假设及结论!$F$13/1000 -> 0.65284332 | J15: =(假设及结论!B15+假设及结论!D15)*10 -> 48963.249
D16: c | E16: 流动资金 working capital | I16: =J16/假设及结论!$F$13/1000 -> 0.2 | J16: =财务计划!$C$25*10 -> 15000
D17: d | E17: 融资费 Financing fee | I17: =J17/假设及结论!$F$13/1000 -> 1.4921052 | J17: =RIGHT($K$17,3)*资金筹措!$F$16*10 -> 111907.89 | K17: ="融资担保公司要求Requirements for financing guarantee companies "&6%*100&"%" -> 融资担保公司要求Requirements for financing guarantee companies 6%
D18: e | I18: =J18/假设及结论!$F$13/1000 -> 0
E19: 结余 balance = (1) - (2) = | G19: =J12-J19 -> 2470447.8 | H19: =MID($C$14,6,63)&" 合计（2）" -> 利息和业主管理费 Construction period interest and owner management fees 合计（2） | J19: =SUM(J14:J18) -> 209025.76 | K19: ="总包合同金额 & 造价"&"General Contract Amount & Cost "&ROUND(G19/假设及结论!$F$13/10000,2)&"yuan/w" -> 总包合同金额 & 造价General Contract Amount & Cost 3.29yuan/w
C21: 3 前期开发阶段 pre-development stage | E21: 内容 | I21: 单价 Price | K21: 备注 Note
D22: a | E22: 负责项目在吉尔吉斯斯坦境内的所有审批手续办理 Responsible for all approvals and formalities for the project in Kyrgyzstan | I22: 0.0285 | J22: =I22*假设及结论!$F$13*10000 -> 21375 | K22: 项目技术开发费 Project Technology development fee
D23: b
E24: 结余 balance = (1) - (2) - (3) = | G24: =G19-J24 -> 2449072.8 | H24: =MID($C$21,2,40)&" 合计（3）" -> 前期开发阶段 pre-development stage 合计（3） | J24: =SUM(J22:J23) -> 21375 | K24: 项目技术开发费总额 Total of Project Technology development fee
C26: 4 EPC 总包工程部分 EPC general contracting project part | D26: a | E26: 光伏组件 Photovoltaic modules PV modules | I26: 0.8 | J26: =I26*假设及结论!$F$13*10000 -> 600000
D27: b | E27: 箱变 Box transformer | I27: 0.1 | J27: =I27*假设及结论!$F$13*10000 -> 75000
D28: c | E28: 逆变器 inverter | I28: 0.11 | J28: =I28*假设及结论!$F$13*10000 -> 82500
D29: d | E29: 支架 Bracket | I29: 0.13 | J29: =I29*假设及结论!$F$13*10000 -> 97500
D30: e | E30: 桩基础 pile foundation | I30: 0.09 | J30: =I30*假设及结论!$F$13*10000 -> 67500
D31: f | E31: 电缆 Cable | I31: 0.2 | J31: =I31*假设及结论!$F$13*10000 -> 150000
D32: g | E32: 通讯及监控 Communication and monitoring | I32: 0.01 | J32: =I32*假设及结论!$F$13*10000 -> 7500
D33: h | E33: 设备安装 、Equipment installation | I33: 0.145 | J33: =I33*假设及结论!$F$13*1000 -> 10875
D34: i | E34: 电气安装 Electrical installation | I34: 0.1 | J34: =I34*假设及结论!$F$13*10000 -> 75000
D35: j | E35: 调试及试验 Debugging and testing | I35: 0.005 | J35: =I35*假设及结论!$F$13*1000 -> 375
D36: k | E36: 设备基础等土建工程 Equipment foundation and other civil engineering projects | I36: 0.008 | J36: =I36*假设及结论!$F$13*10000 -> 6000
D37: l | E37: 光伏区围栏 Photovoltaic area fence | I37: 0.008 | J37: =I37*假设及结论!$F$13*1000 -> 600
D38: m | E38: 升压站 booster station | I38: 0.346 | J38: =I38*假设及结论!$F$13*10000 -> 259500
D39: n | E39: 储能系统和工程 Energy Storage Systems and Engineering | I39: 0.747 | J39: =I39*假设及结论!$F$13*1000*LEFT(G8,3)*10 -> 168075
D40: o | E40: 勘察设计 survey and design | I40: 0.05 | J40: =I40*假设及结论!$F$13*10000 -> 37500
D41: p | E41: 运费 freight | I41: 0.2 | J41: =I41*假设及结论!$F$13*10000 -> 150000
D42: q | E42: 境内税务成本 Domestic tax costs | I42: 0.047 | J42: =I42*假设及结论!$F$13*10000 -> 35250
D43: r | E43: 其他 others | I43: 0.98 | J43: =I43*假设及结论!$F$13*10000 -> 735000 | K43: Adjustable Room
D44: s | J44: =I44*假设及结论!$F$13*1000 -> 0
E45: 结余 balance= (1) - (2) - (3) - (4) = | G45: =G24-J45 -> -109102.19 | H45: =MID($C$26,2,50)&" 合计（4）" -> EPC 总包工程部分 EPC general contracting project part 合计（4） | J45: =SUM(J26:J44) -> 2558175 | K45: ="总包工程金额 Total project contract amount& 造价 construction cost "&ROUND(J45/假设及结论!$F$13/10000,2)&"yuan/w" -> 总包工程金额 Total project contract amount& 造价 construction cost 3.41yuan/w

Sheet 决策信息1
C5: ="吉尔吉斯斯坦共和国-巴特肯州巴特肯区阿克塔特尔600兆瓦光伏发电项目投资构成情况 "&"IRR="&TEXT($E$10*100,"#,##.#0")&"%"&"（电价优惠期=15年）" -> 吉尔吉斯斯坦共和国-巴特肯州巴特肯区阿克塔特尔600兆瓦光伏发电项目投资构成情况 IRR=8.50%（电价优惠期=15年）
C6: 1 项目测算情况 | D6: 交流/直流容量 （MW） 容配比 1.3 | E6: 电价 (不含税) (US$/kwh) | F6: 首年小时数 (小时) | G6: 储能比例/配置小时数 | H6: 电力辅助服务费 (元/kwh) | I6: 项目占地 （公顷） | J6: 年租金标准 (美元/公顷) | K6: 土地补偿标准 （US$ /公顷） | O6: =I7*J7 -> 438841.2 | P6: =O6*25 -> 10971030
D7: 600 / 780 | E7: 0.05 | F7: 1529.92 | G7: 30% / 1小时 | H7: 0 | I7: 1232.7 | J7: 356 | K7: 544
D9: 项目总投资 (万元) | E9: 全投资 IRR | F9: 资本金 IRR | G9: 其中： 电站总投资 (万元) | H9: 其中： 储能总投资 （万元） | I9: 储能动态投资造价 (元/wh) | J9: 电站动态 投资造价 （元/W） | K9: 所得税 销售税 土地税
D10: 322750.51 | E10: 0.085026309 | F10: 0.20910161 | G10: 302891 | H10: 19315.16 | I10: 0.82543418 | J10: 3.8832179 | K10: 豁免
D11: 测算总投资：当收益率为 8.50% 时，总投资为（1） | J11: 322750.51
C13: 2 建设期利息和业主管理费 | D13: a | E13: 建设期利息 | I13: 0.058525937 | J13: 4565.0231 | K13: 投资分析 | M13: =J18+J26+J36 -> 322750.26
D14: b | E14: 业主管理费（含电站+储能） | I14: 0.075640897 | J14: 5899.9899 | K14: 投资分析
D15: c | E15: 流动资金 | I15: 0.015 | J15: 1170 | K15: 投资分析
D16: d | E16: 融资费 | I16: 0.32982617 | J16: 25726.441 | K16: 0.1
D17: e | I17: 0
D18: 结余 | E18: （1）-（2）： | G18: 285389.06 | H18: 利息和业主管理费 合计（3） | J18: 37361.454
C20: 2 前期阶段 | E20: 内容 | I20: 电价 | K20: 来源
D21: a | E21: 征林征地和青苗补偿工作委托协议 | I21: 0.6 | J21: 46800 | K21: 合同
D22: b | E22: 接入系统方案及接入系统批复 | I22: 0 | K22: 预估
D23: c | E23: 项目委托开发协议（包含从开发、建设、并网全过程中，可能涉及的各项文件的编制、审批、协调：地勘、环评、水保、压覆矿、文物、地灾、安全评估、职业健康、军事消防、电磁辐射等） | I23: 0 | K23: 11院概算中的“手续审批”（包含在征林征地中）
D24: d | I24: 0
D25: e | I25: 0
D26: 结余 | E26: （1）-（2）-（3）： | G26: 238589.06 | H26: 前期阶段 合计（2） | J26: 46800
C28: 4 工程 EPC 总包 | D28: a | E28: 主要设备材料采购费 | I28: 1.6 | J28: 124800 | K28: 11院
D29: b | E29: 光伏区施工 | I29: 0.51202564 | J29: 39938 | K29: 11院
D30: c | E30: 升压站及送出工程 | I30: 0.32051282 | J30: 25000 | K30: 11院的73.42%
D31: d | E31: 其他 （扣除：手续审批、征林征地及补偿、水土保持、场外道路） | I31: 0.11384615 | J31: 8880 | K31: 11院的73.69%
D32: e | E32: 勘察设计与项目管理合同 | I32: 0.14358974 | J32: 11200 | K32: 已签订
D33: f | E33: 运费 | I33: 0.12820513 | J33: 10000 | K33: 11院的40.24%
D34: g | J34: 0
D35: h | E35: 储能 EPC 总包 | I35: 0.24065136 | J35: 18770.806 | K35: 预估
D36: 结余 | E36: （1）-（2）-（3）-（4）： | G36: 0.25272991 | H36: 工程 EPC 总包 合计（4） | J36: 238588.81

Sheet 决策信息2
C5: 吉尔吉斯斯坦共和国-巴特肯州巴特肯区阿克塔特尔600兆瓦光伏发电项目投资构成情况 IRR=10.35%（电价优惠期=25年）
C6: 1 项目测算情况 | D6: 交流/直流容量 （MW） 容配比 1.3 | E6: 电价 (不含税) (US$/kwh) | F6: 首年小时数 (小时) | G6: 储能比例/配置小时数 | H6: 电力辅助服务费 (元/kwh) | I6: 项目占地 （公顷） | J6: 年租金标准 (美元/公顷) | K6: 土地补偿标准 （US$ /公顷）
D7: 600 / 780 | E7: 0.05 | F7: 1529.92 | G7: 30% / 1小时 | H7: 0 | I7: 1232.7 | J7: 356 | K7: 544
D9: 项目总投资 (万元) | E9: 全投资 IRR | F9: 资本金 IRR | G9: 其中： 电站总投资 (万元) | H9: 其中： 储能总投资 （万元） | I9: 储能动态投资造价 (元/wh) | J9: 电站动态 投资造价 （元/W） | K9: 所得税 销售税 土地税
D10: 339201.51 | E10: 0.10348355 | F10: 0.2066421 | G10: 319342 | H10: 19315.16 | I10: 0.82543418 | J10: 4.0941282 | K10: 豁免
D11: 测算总投资：当收益率为 10.35% 时，总投资为（1） | J11: 339201.51
C13: 2 建设期利息和业主管理费 | D13: a | E13: 建设期利息 | I13: 0.061519931 | J13: 4798.5546 | K13: 投资分析 | M13: =J18+J26+J36 -> 339201.75
D14: b | E14: 业主管理费（含电站+储能） | I14: 0.079370154 | J14: 6190.8721 | K14: 投资分析
D15: c | E15: 流动资金 | I15: 0.015 | J15: 1170 | K15: 投资分析
D16: d | E16: 融资费 | I16: 0.34669899 | J16: 27042.521 | K16: 0.1
D17: e | I17: 0
D18: 结余 | E18: （1）-（2）： | G18: 299999.57 | H18: 利息和业主管理费 合计（3） | J18: 39201.948
C20: 2 前期阶段 | E20: 内容 | I20: 电价 | K20: 来源
D21: a | E21: 征林征地和青苗补偿工作委托协议 | I21: 0.6 | J21: 46800 | K21: 合同
D22: b | E22: 接入系统方案及接入系统批复 | I22: 0 | K22: 预估
D23: c | E23: 项目委托开发协议（包含从开发、建设、并网全过程中，可能涉及的各项文件的编制、审批、协调：地勘、环评、水保、压覆矿、文物、地灾、安全评估、职业健康、军事消防、电磁辐射等） | I23: 0 | K23: 11院概算中的“手续审批”（包含在征林征地中）
D24: d | I24: 0
D25: e | I25: 0
D26: 结余 | E26: （1）-（2）-（3）： | G26: 253199.57 | H26: 前期阶段 合计（2） | J26: 46800
C28: 4 工程 EPC 总包 | D28: a | E28: 主要设备材料采购费 | I28: 1.6 | J28: 124800 | K28: 11院
D29: b | E29: 光伏区施工 | I29: 0.51202564 | J29: 39938 | K29: 11院
D30: c | E30: 升压站及送出工程 | I30: 0.43653846 | J30: 34050 | K30: 11院
D31: d | E31: 其他 （扣除：手续审批、征林征地及补偿、水土保持、场外道路） | I31: 0.15448718 | J31: 12050 | K31: 11院
D32: e | E32: 勘察设计与项目管理合同 | I32: 0.14358974 | J32: 11200 | K32: 已签订
D33: f | E33: 运费 | I33: 0.15885897 | J33: 12391 | K33: 11院的49.86%
D34: g
D35: h | E35: 储能 EPC 总包 | I35: 0.24065136 | J35: 18770.806 | K35: 预估
D36: 结余 | E36: （1）-（2）-（3）-（4）： | G36: -0.24093764 | H36: 工程 EPC 总包 合计（4） | J36: 253199.81

Sheet 决策信息（反算）
C5: ="吉尔吉斯斯坦共和国-巴特肯州巴特肯区阿克塔特尔600兆瓦光伏发电项目投资构成情况 "&"IRR="&TEXT($E$10*100,"#,##.#0")&"%"&"（电价优惠期=25年）" -> 吉尔吉斯斯坦共和国-巴特肯州巴特肯区阿克塔特尔600兆瓦光伏发电项目投资构成情况 IRR=11.60%（电价优惠期=25年）
C6: 1 项目测算情况 | D6: ="交流/直流容量 （MW） 容配比 "&TEXT(假设及结论!$F$13/假设及结论!$E$13,"#.##") -> 交流/直流容量 （MW） 容配比 1.25 | E6: ="电价 "&IF(假设及结论!$Q$7="NO","(不含税)","(含税)")&" (US$/kwh)" -> 电价 (不含税) (US$/kwh) | F6: 首年小时数 (小时) | G6: 储能比例/配置小时数 | H6: 电力辅助服务费 (元/kwh) | I6: 项目占地 （公顷） | J6: 年租金标准 (美元/公顷) | K6: 土地补偿标准 （US$ /公顷）
D7: =假设及结论!$C$7 -> 600 / 750 | E7: =假设及结论!$I$15/假设及结论!$I$21 -> 0.05 | F7: =假设及结论!$B$9 -> 1545 | G7: =假设及结论!$C$9 -> 30% / 1小时 | H7: =假设及结论!$M$13 -> 0 | I7: =假设及结论!$G$21 -> 1232.7 | J7: =假设及结论!$H$21 -> 180 | K7: =假设及结论!$J$21 -> 272
D9: 项目总投资 (万元) | E9: 全投资 IRR | F9: 资本金 IRR | G9: 其中： 电站总投资 (万元) | H9: 其中： 储能总投资 （万元） | I9: 储能动态投资造价 (元/wh) | J9: 电站动态 投资造价 （元/W） | K9: 所得税 销售税 土地税
D10: =假设及结论!B7 -> 267947.36 | E10: =全部投资现金流!$E$27 -> 0.11599219 | F10: =资本金现金流!$E$27 -> 0.21052865 | G10: =假设及结论!$E$7 -> 251649.6 | H10: =假设及结论!$E$9 -> 15851.032 | I10: =假设及结论!$D$9 -> 0.70449032 | J10: =假设及结论!$D$7 -> 3.355328 | K10: 豁免
D11: ="测算总投资：当收益率为 "&TEXT($E$10*100,"##0.00")&"% 时，总投资为（1）" -> 测算总投资：当收益率为 11.60% 时，总投资为（1） | J11: =D10 -> 267947.36
C13: 2 建设期利息和业主管理费 | D13: a | E13: 建设期利息 | I13: =J13/假设及结论!$F$13/1000 -> 0.044206158 | J13: =资金筹措!C8 -> 3315.4619 | K13: 投资分析 | M13: =J18+J26+J36 -> 311627.41
D14: b | E14: 业主管理费（含电站+储能） | I14: =J14/假设及结论!$F$13/1000 -> 0.065284332 | J14: =假设及结论!B15+假设及结论!D15 -> 4896.3249 | K14: 投资分析
D15: c | E15: 流动资金 | I15: =J15/假设及结论!$F$13/1000 -> 0.02 | J15: =财务计划!$C$25 -> 1500 | K15: 投资分析
D16: d | E16: 融资费 | I16: =J16/假设及结论!$F$13/1000 -> 0.2486842 | J16: =$K$16*资金筹措!$F$16 -> 18651.315 | K16: 0.1
D17: e | I17: =J17/假设及结论!$F$13/1000 -> 0
D18: 结余 | E18: （1）-（2）： | G18: =J11-J18 -> 239584.26 | H18: =MID($C$13,6,20)&" 合计（3）" -> 利息和业主管理费 合计（3） | J18: =SUM(J13:J17) -> 28363.102
C20: 2 前期阶段 | E20: 内容 | I20: 电价 | K20: 来源
D21: a | E21: 征林征地和青苗补偿工作委托协议 | I21: =J21/假设及结论!$F$13/1000 -> 0.624 | J21: 46800 | K21: 合同
D22: b | E22: 接入系统方案及接入系统批复 | I22: =J22/假设及结论!$F$13/1000 -> 0 | K22: 预估
D23: c | E23: 项目委托开发协议（包含从开发、建设、并网全过程中，可能涉及的各项文件的编制、审批、协调：地勘、环评、水保、压覆矿、文物、地灾、安全评估、职业健康、军事消防、电磁辐射等） | I23: =J23/假设及结论!$F$13/1000 -> 0 | K23: 11院概算中的“手续审批”（包含在征林征地中）
D24: d | I24: =J24/假设及结论!$F$13/1000 -> 0
D25: e | I25: =J25/假设及结论!$F$13/1000 -> 0
D26: 结余 | E26: （1）-（2）-（3）： | G26: =G18-J26 -> 192784.26 | H26: =MID($C$20,2,20)&" 合计（2）" -> 前期阶段 合计（2） | J26: =SUM(J21:J25) -> 46800
C28: 4 工程 EPC 总包 | D28: a | E28: 主要设备材料采购费 | I28: =J28/假设及结论!$F$13/1000 -> 1.7 | J28: ='11院EPC价'!G11 -> 127500 | K28: 11院
D29: b | E29: 光伏区施工 | I29: =J29/假设及结论!$F$13/1000 -> 0.51306667 | J29: ='11院EPC价'!G25 -> 38480 | K29: 11院
D30: c | E30: 升压站及送出工程 | I30: =J30/假设及结论!$F$13/1000 -> 0.33333333 | J30: 25000 | K30: ="11院的"&TEXT(J30/'11院EPC价'!G32*100,"##.##")&"%" -> 11院的84.1%
D31: d | E31: 其他 （扣除：手续审批、征林征地及补偿、水土保持、场外道路） | I31: =J31/假设及结论!$F$13/1000 -> 0.1184 | J31: 8880 | K31: ="11院的"&TEXT(J31/('11院EPC价'!G51-SUM('11院EPC价'!G41:G44))*100,"##.##")&"%" -> 11院的73.69%
D32: e | E32: 勘察设计与项目管理合同 | I32: =J32/假设及结论!$F$13/1000 -> 0.14933333 | J32: 11200 | K32: 已签订
D33: f | E33: 运费 | I33: =J33/假设及结论!$F$13/1000 -> 0.13333333 | J33: 10000 | K33: ="11院的"&TEXT(J33/'11院EPC价'!G53*100,"##.##")&"%" -> 11院的40.24%
D34: g | J34: 0
D35: h | E35: 储能 EPC 总包 | I35: =J35/假设及结论!$F$13/1000 -> 0.20539076 | J35: =假设及结论!F9 -> 15404.307 | K35: 预估
D36: 结余 | E36: （1）-（2）-（3）-（4）： | G36: =G26-J36 -> -43680.052 | H36: =MID($C$28,2,20)&" 合计（4）" -> 工程 EPC 总包 合计（4） | J36: =SUM(J28:J35) -> 236464.31

Sheet 销售收入
A2: 营业收入、营业税金及附加和增值税估算表
X3: 单位:万元
A4: 序 | B4: 年份 名称 | C4: 合计 | D4: 建设经营期
A5: 号 | D5: 1 | E5: 2 | F5: 3 | G5: 4 | H5: 5 | I5: 6 | J5: 7 | K5: 8 | L5: 9 | M5: 10 | N5: 11 | O5: 12 | P5: 13 | Q5: 14 | R5: 15 | S5: 16 | T5: 17 | U5: 18 | V5: 19 | W5: 20 | X5: 21 | Y5: 22 | Z5: 23 | AA5: 24 | AB5: 25 | AC5: 26 | AD5: 27
A6: 1 | B6: 营业收入 （不含增值税和销售税） | C6: =SUM(E6:AD6) -> 940024.39 | E6: =E7 -> 39737.25 | F6: =F7 -> 39339.878 | G6: =G7 -> 39180.929 | H6: =H7 -> 39021.98 | I6: =I7 -> 38863.031 | J6: =J7 -> 38704.082 | K6: =K7 -> 38545.132 | L6: =L7 -> 38386.183 | ... AD6: =AD7 -> 0
A7: 1.1 | B7: 电力销售 | C7: =SUM(E7:AD7) -> 940024.39 | D7: =IF(D5<=ConstructPeriod,0,IF(SubsidyLossMonths>=(D5-ConstructPeriod)*12,BasicPrice/(1+假设及结论!$H$30)*D14,IF(D5=OperationPeriod+ConstructPeriod,D9*D14+(D9-BasicPrice/(1+假设及结论!$H$30))*D14*ROUNDDOWN(SubsidyLossMonths/12,0),D9*D14))) -> 0 | E7: =E8+E12+E16+E20+E23 -> 39737.25 | F7: =F8+F12+F16+F20+F23 -> 39339.878 | G7: =G8+G12+G16+G20+G23 -> 39180.929 | H7: =H8+H12+H16+H20+H23 -> 39021.98 | I7: =I8+I12+I16+I20+I23 -> 38863.031 | J7: =J8+J12+J16+J20+J23 -> 38704.082 | K7: =K8+K12+K16+K20+K23 -> 38545.132 | L7: =L8+L12+L16+L20+L23 -> 38386.183 | ... AD7: =AD8+AD12+AD16+AD20+AD23 -> 0
A8: 1.1.1 | B8: 保障标杆收入 | E8: =IF(E5-1<假设及结论!$F$15,0,IF(E5-1-假设及结论!$F$15<=假设及结论!$G$15,E9*E11,0)) -> 37394.438 | F8: =IF(F5-1<假设及结论!$F$15,0,IF(F5-1-假设及结论!$F$15<=假设及结论!$G$15,F9*F11,0)) -> 37020.493 | G8: =IF(G5-1<假设及结论!$F$15,0,IF(G5-1-假设及结论!$F$15<=假设及结论!$G$15,G9*G11,0)) -> 36870.915 | H8: =IF(H5-1<假设及结论!$F$15,0,IF(H5-1-假设及结论!$F$15<=假设及结论!$G$15,H9*H11,0)) -> 36721.338 | I8: =IF(I5-1<假设及结论!$F$15,0,IF(I5-1-假设及结论!$F$15<=假设及结论!$G$15,I9*I11,0)) -> 36571.76 | J8: =IF(J5-1<假设及结论!$F$15,0,IF(J5-1-假设及结论!$F$15<=假设及结论!$G$15,J9*J11,0)) -> 36422.182 | K8: =IF(K5-1<假设及结论!$F$15,0,IF(K5-1-假设及结论!$F$15<=假设及结论!$G$15,K9*K11,0)) -> 36272.604 | L8: =IF(L5-1<假设及结论!$F$15,0,IF(L5-1-假设及结论!$F$15<=假设及结论!$G$15,L9*L11,0)) -> 36123.027 | ... AD8: =IF(AD5-1<假设及结论!$F$15,0,IF(AD5-1-假设及结论!$F$15<=假设及结论!$G$15,AD9*AD11,0)) -> 0
B9: 保障标杆单价（元/kWh） | E9: =IF(E10=0,0,IF(假设及结论!$Q$7="NO",IF(E5-1>假设及结论!$G$15,假设及结论!$J$15,假设及结论!$L$15),IF(E5-1>假设及结论!$G$15,假设及结论!$J$15,假设及结论!$L$15)/(1+假设及结论!$H$30+假设及结论!$K$30))) -> 0.35 | F9: =IF(F10=0,0,IF(假设及结论!$Q$7="NO",IF(F5-1>假设及结论!$G$15,假设及结论!$J$15,假设及结论!$L$15),IF(F5-1>假设及结论!$G$15,假设及结论!$J$15,假设及结论!$L$15)/(1+假设及结论!$H$30+假设及结论!$K$30))) -> 0.35 | G9: =IF(G10=0,0,IF(假设及结论!$Q$7="NO",IF(G5-1>假设及结论!$G$15,假设及结论!$J$15,假设及结论!$L$15),IF(G5-1>假设及结论!$G$15,假设及结论!$J$15,假设及结论!$L$15)/(1+假设及结论!$H$30+假设及结论!$K$30))) -> 0.35 | H9: =IF(H10=0,0,IF(假设及结论!$Q$7="NO",IF(H5-1>假设及结论!$G$15,假设及结论!$J$15,假设及结论!$L$15),IF(H5-1>假设及结论!$G$15,假设及结论!$J$15,假设及结论!$L$15)/(1+假设及结论!$H$30+假设及结论!$K$30))) -> 0.35 | I9: =IF(I10=0,0,IF(假设及结论!$Q$7="NO",IF(I5-1>假设及结论!$G$15,假设及结论!$J$15,假设及结论!$L$15),IF(I5-1>假设及结论!$G$15,假设及结论!$J$15,假设及结论!$L$15)/(1+假设及结论!$H$30+假设及结论!$K$30))) -> 0.35 | J9: =IF(J10=0,0,IF(假设及结论!$Q$7="NO",IF(J5-1>假设及结论!$G$15,假设及结论!$J$15,假设及结论!$L$15),IF(J5-1>假设及结论!$G$15,假设及结论!$J$15,假设及结论!$L$15)/(1+假设及结论!$H$30+假设及结论!$K$30))) -> 0.35 | K9: =IF(K10=0,0,IF(假设及结论!$Q$7="NO",IF(K5-1>假设及结论!$G$15,假设及结论!$J$15,假设及结论!$L$15),IF(K5-1>假设及结论!$G$15,假设及结论!$J$15,假设及结论!$L$15)/(1+假设及结论!$H$30+假设及结论!$K$30))) -> 0.35 | L9: =IF(L10=0,0,IF(假设及结论!$Q$7="NO",IF(L5-1>假设及结论!$G$15,假设及结论!$J$15,假设及结论!$L$15),IF(L5-1>假设及结论!$G$15,假设及结论!$J$15,假设及结论!$L$15)/(1+假设及结论!$H$30+假设及结论!$K$30))) -> 0.35 | ... AD9: =IF(AD10=0,0,IF(假设及结论!$Q$7="NO",IF(AD5-1>假设及结论!$G$15,假设及结论!$J$15,假设及结论!$L$15),IF(AD5-1>假设及结论!$G$15,假设及结论!$J$15,假设及结论!$L$15)/(1+假设及结论!$H$30+假设及结论!$K$30))) -> 0
B10: 保障小时数 | E10: =IF(E5<=ConstructPeriod,0,IF(E5-ConstructPeriod<=OperationPeriod,假设及结论!$L$13,0)) -> 1424.55 | F10: =IF(F5<=ConstructPeriod,0,IF(F5-ConstructPeriod<=OperationPeriod,假设及结论!$L$13,0)*(1-假设及结论!$N$21)) -> 1410.3045 | G10: =IF(G5<=ConstructPeriod,0,IF(G5-ConstructPeriod<=OperationPeriod,假设及结论!$L$13,0)*(1-假设及结论!$N$21-假设及结论!$O$21*(G5-3))) -> 1404.6063 | H10: =IF(H5<=ConstructPeriod,0,IF(H5-ConstructPeriod<=OperationPeriod,假设及结论!$L$13,0)*(1-假设及结论!$N$21-假设及结论!$O$21*(H5-3))) -> 1398.9081 | I10: =IF(I5<=ConstructPeriod,0,IF(I5-ConstructPeriod<=OperationPeriod,假设及结论!$L$13,0)*(1-假设及结论!$N$21-假设及结论!$O$21*(I5-3))) -> 1393.2099 | J10: =IF(J5<=ConstructPeriod,0,IF(J5-ConstructPeriod<=OperationPeriod,假设及结论!$L$13,0)*(1-假设及结论!$N$21-假设及结论!$O$21*(J5-3))) -> 1387.5117 | K10: =IF(K5<=ConstructPeriod,0,IF(K5-ConstructPeriod<=OperationPeriod,假设及结论!$L$13,0)*(1-假设及结论!$N$21-假设及结论!$O$21*(K5-3))) -> 1381.8135 | L10: =IF(L5<=ConstructPeriod,0,IF(L5-ConstructPeriod<=OperationPeriod,假设及结论!$L$13,0)*(1-假设及结论!$N$21-假设及结论!$O$21*(L5-3))) -> 1376.1153 | M10: =IF(M5<=ConstructPeriod,0,IF(M5-ConstructPeriod<=OperationPeriod,假设及结论!$L$13,0)*(1-假设及结论!$N$21-假设及结论!$O$21*(M5-3))) -> 1370.4171 | N10: =IF(N5<=ConstructPeriod,0,IF(N5-ConstructPeriod<=OperationPeriod,假设及结论!$L$13,0)*(1-假设及结论!$N$21-假设及结论!$O$21*(N5-3))) -> 1364.7189 | ... AD10: =IF(AD5<=ConstructPeriod,0,IF(AD5-ConstructPeriod<=OperationPeriod,假设及结论!$L$13,0)*(1-假设及结论!$N$21-假设及结论!$O$21*(AD5-3))) -> 0
B11: 保障电量 | E11: =E10*假设及结论!$F$13 -> 106841.25 | F11: =F10*假设及结论!$F$13 -> 105772.84 | G11: =G10*假设及结论!$F$13 -> 105345.47 | H11: =H10*假设及结论!$F$13 -> 104918.11 | I11: =I10*假设及结论!$F$13 -> 104490.74 | J11: =J10*假设及结论!$F$13 -> 104063.38 | K11: =K10*假设及结论!$F$13 -> 103636.01 | L11: =L10*假设及结论!$F$13 -> 103208.65 | ... AD11: =AD10*假设及结论!$F$13 -> 0
A12: 1.1.2 | B12: 超发外收入 | E12: =IF(E9-1<假设及结论!$F$15,0,IF(E9-1-假设及结论!$F$15<=假设及结论!$G$15,E13*E15,0)) -> 0 | F12: =IF(F9-1<假设及结论!$F$15,0,IF(F9-1-假设及结论!$F$15<=假设及结论!$G$15,F13*F15,0)) -> 0 | G12: =IF(G9-1<假设及结论!$F$15,0,IF(G9-1-假设及结论!$F$15<=假设及结论!$G$15,G13*G15,0)) -> 0 | H12: =IF(H9-1<假设及结论!$F$15,0,IF(H9-1-假设及结论!$F$15<=假设及结论!$G$15,H13*H15,0)) -> 0 | I12: =IF(I9-1<假设及结论!$F$15,0,IF(I9-1-假设及结论!$F$15<=假设及结论!$G$15,I13*I15,0)) -> 0 | J12: =IF(J9-1<假设及结论!$F$15,0,IF(J9-1-假设及结论!$F$15<=假设及结论!$G$15,J13*J15,0)) -> 0 | K12: =IF(K9-1<假设及结论!$F$15,0,IF(K9-1-假设及结论!$F$15<=假设及结论!$G$15,K13*K15,0)) -> 0 | L12: =IF(L9-1<假设及结论!$F$15,0,IF(L9-1-假设及结论!$F$15<=假设及结论!$G$15,L13*L15,0)) -> 0 | ... AD12: =IF(AD9-1<假设及结论!$F$15,0,IF(AD9-1-假设及结论!$F$15<=假设及结论!$G$15,AD13*AD15,0)) -> 0
B13: 超发单价（元/kWh） | E13: =IF(E14=0,0,IF(假设及结论!$Q$7="NO",假设及结论!$P$15,假设及结论!$P$15/(1+假设及结论!$H$30+假设及结论!$K$30))) -> 0 | F13: =IF(F14=0,0,IF(假设及结论!$Q$7="NO",假设及结论!$P$15,假设及结论!$P$15/(1+假设及结论!$H$30+假设及结论!$K$30))) -> 0 | G13: =IF(G14=0,0,IF(假设及结论!$Q$7="NO",假设及结论!$P$15,假设及结论!$P$15/(1+假设及结论!$H$30+假设及结论!$K$30))) -> 0 | H13: =IF(H14=0,0,IF(假设及结论!$Q$7="NO",假设及结论!$P$15,假设及结论!$P$15/(1+假设及结论!$H$30+假设及结论!$K$30))) -> 0 | I13: =IF(I14=0,0,IF(假设及结论!$Q$7="NO",假设及结论!$P$15,假设及结论!$P$15/(1+假设及结论!$H$30+假设及结论!$K$30))) -> 0 | J13: =IF(J14=0,0,IF(假设及结论!$Q$7="NO",假设及结论!$P$15,假设及结论!$P$15/(1+假设及结论!$H$30+假设及结论!$K$30))) -> 0 | K13: =IF(K14=0,0,IF(假设及结论!$Q$7="NO",假设及结论!$P$15,假设及结论!$P$15/(1+假设及结论!$H$30+假设及结论!$K$30))) -> 0 | L13: =IF(L14=0,0,IF(假设及结论!$Q$7="NO",假设及结论!$P$15,假设及结论!$P$15/(1+假设及结论!$H$30+假设及结论!$K$30))) -> 0 | ... AD13: =IF(AD14=0,0,IF(假设及结论!$Q$7="NO",假设及结论!$P$15,假设及结论!$P$15/(1+假设及结论!$H$30+假设及结论!$K$30))) -> 0
B14: 超发小时数 | C14: =SUM(E14:AD14) -> 0 | E14: =IF(E5<=ConstructPeriod,0,IF(E5-ConstructPeriod<=OperationPeriod,假设及结论!$P$13,0)) -> 0 | F14: =IF(F5<=ConstructPeriod,0,IF(F5-ConstructPeriod<=OperationPeriod,假设及结论!$P$13,0)*(1-假设及结论!$N$21)) -> 0 | G14: =IF(G5<=ConstructPeriod,0,IF(G5-ConstructPeriod<=OperationPeriod,假设及结论!$P$13,0)*(1-假设及结论!$N$21-假设及结论!$O$21*(G5-3))) -> 0 | H14: =IF(H5<=ConstructPeriod,0,IF(H5-ConstructPeriod<=OperationPeriod,假设及结论!$P$13,0)*(1-假设及结论!$N$21-假设及结论!$O$21*(H5-3))) -> 0 | I14: =IF(I5<=ConstructPeriod,0,IF(I5-ConstructPeriod<=OperationPeriod,假设及结论!$P$13,0)*(1-假设及结论!$N$21-假设及结论!$O$21*(I5-3))) -> 0 | J14: =IF(J5<=ConstructPeriod,0,IF(J5-ConstructPeriod<=OperationPeriod,假设及结论!$P$13,0)*(1-假设及结论!$N$21-假设及结论!$O$21*(J5-3))) -> 0 | K14: =IF(K5<=ConstructPeriod,0,IF(K5-ConstructPeriod<=OperationPeriod,假设及结论!$P$13,0)*(1-假设及结论!$N$21-假设及结论!$O$21*(K5-3))) -> 0 | L14: =IF(L5<=ConstructPeriod,0,IF(L5-ConstructPeriod<=OperationPeriod,假设及结论!$P$13,0)*(1-假设及结论!$N$21-假设及结论!$O$21*(L5-3))) -> 0 | M14: =IF(M5<=ConstructPeriod,0,IF(M5-ConstructPeriod<=OperationPeriod,假设及结论!$P$13,0)*(1-假设及结论!$N$21-假设及结论!$O$21*(M5-3))) -> 0 | N14: =IF(N5<=ConstructPeriod,0,IF(N5-ConstructPeriod<=OperationPeriod,假设及结论!$P$13,0)*(1-假设及结论!$N$21-假设及结论!$O$21*(N5-3))) -> 0 | ... AD14: =IF(AD5<=ConstructPeriod,0,IF(AD5-ConstructPeriod<=OperationPeriod,假设及结论!$P$13,0)*(1-假设及结论!$N$21-假设及结论!$O$21*(AD5-3))) -> 0
B15: 超发电量 | E15: =E14*假设及结论!$F$13 -> 0 | F15: =F14*假设及结论!$F$13 -> 0 | G15: =G14*假设及结论!$F$13 -> 0 | H15: =H14*假设及结论!$F$13 -> 0 | I15: =I14*假设及结论!$F$13 -> 0 | J15: =J14*假设及结论!$F$13 -> 0 | K15: =K14*假设及结论!$F$13 -> 0 | L15: =L14*假设及结论!$F$13 -> 0 | ... AD15: =AD14*假设及结论!$F$13 -> 0
A16: 1.1.3 | B16: =假设及结论!O13&"小时市场化交易收入" -> 0小时市场化交易收入 | E16: =IF(E13-1<假设及结论!$F$15,0,IF(E13-1-假设及结论!$F$15<=假设及结论!$G$15,E17*E19,0)) -> 0 | F16: =IF(F13-1<假设及结论!$F$15,0,IF(F13-1-假设及结论!$F$15<=假设及结论!$G$15,F17*F19,0)) -> 0 | G16: =IF(G13-1<假设及结论!$F$15,0,IF(G13-1-假设及结论!$F$15<=假设及结论!$G$15,G17*G19,0)) -> 0 | H16: =IF(H13-1<假设及结论!$F$15,0,IF(H13-1-假设及结论!$F$15<=假设及结论!$G$15,H17*H19,0)) -> 0 | I16: =IF(I13-1<假设及结论!$F$15,0,IF(I13-1-假设及结论!$F$15<=假设及结论!$G$15,I17*I19,0)) -> 0 | J16: =IF(J13-1<假设及结论!$F$15,0,IF(J13-1-假设及结论!$F$15<=假设及结论!$G$15,J17*J19,0)) -> 0 | K16: =IF(K13-1<假设及结论!$F$15,0,IF(K13-1-假设及结论!$F$15<=假设及结论!$G$15,K17*K19,0)) -> 0 | L16: =IF(L13-1<假设及结论!$F$15,0,IF(L13-1-假设及结论!$F$15<=假设及结论!$G$15,L17*L19,0)) -> 0 | ... AD16: =IF(AD13-1<假设及结论!$F$15,0,IF(AD13-1-假设及结论!$F$15<=假设及结论!$G$15,AD17*AD19,0)) -> 0
B17: =假设及结论!O13&"小时市场化交易电价(元/kWh)" -> 0小时市场化交易电价(元/kWh) | E17: =IF(E18=0,0,IF(假设及结论!$Q$7="NO",假设及结论!$O$15,假设及结论!$O$15/(1+假设及结论!$H$30+假设及结论!$K$30))) -> 0 | F17: =IF(F18=0,0,IF(假设及结论!$Q$7="NO",假设及结论!$O$15,假设及结论!$O$15/(1+假设及结论!$H$30+假设及结论!$K$30))) -> 0 | G17: =IF(G18=0,0,IF(假设及结论!$Q$7="NO",假设及结论!$O$15,假设及结论!$O$15/(1+假设及结论!$H$30+假设及结论!$K$30))) -> 0 | H17: =IF(H18=0,0,IF(假设及结论!$Q$7="NO",假设及结论!$O$15,假设及结论!$O$15/(1+假设及结论!$H$30+假设及结论!$K$30))) -> 0 | I17: =IF(I18=0,0,IF(假设及结论!$Q$7="NO",假设及结论!$O$15,假设及结论!$O$15/(1+假设及结论!$H$30+假设及结论!$K$30))) -> 0 | J17: =IF(J18=0,0,IF(假设及结论!$Q$7="NO",假设及结论!$O$15,假设及结论!$O$15/(1+假设及结论!$H$30+假设及结论!$K$30))) -> 0 | K17: =IF(K18=0,0,IF(假设及结论!$Q$7="NO",假设及结论!$O$15,假设及结论!$O$15/(1+假设及结论!$H$30+假设及结论!$K$30))) -> 0 | L17: =IF(L18=0,0,IF(假设及结论!$Q$7="NO",假设及结论!$O$15,假设及结论!$O$15/(1+假设及结论!$H$30+假设及结论!$K$30))) -> 0 | ... AD17: =IF(AD18=0,0,IF(假设及结论!$Q$7="NO",假设及结论!$O$15,假设及结论!$O$15/(1+假设及结论!$H$30+假设及结论!$K$30))) -> 0
B18: =假设及结论!O13&"小时市场化交易小时数" -> 0小时市场化交易小时数 | C18: =SUM(E18:AD18) -> 0 | E18: =IF(E5<=ConstructPeriod,0,IF(E5-ConstructPeriod<=OperationPeriod,假设及结论!$O$13,0)) -> 0 | F18: =IF(F5<=ConstructPeriod,0,IF(F5-ConstructPeriod<=OperationPeriod,假设及结论!$O$13,0)*(1-假设及结论!$N$21)) -> 0 | G18: =IF(G5<=ConstructPeriod,0,IF(G5-ConstructPeriod<=OperationPeriod,假设及结论!$O$13,0)*(1-假设及结论!$N$21-假设及结论!$O$21*(G5-3))) -> 0 | H18: =IF(H5<=ConstructPeriod,0,IF(H5-ConstructPeriod<=OperationPeriod,假设及结论!$O$13,0)*(1-假设及结论!$N$21-假设及结论!$O$21*(H5-3))) -> 0 | I18: =IF(I5<=ConstructPeriod,0,IF(I5-ConstructPeriod<=OperationPeriod,假设及结论!$O$13,0)*(1-假设及结论!$N$21-假设及结论!$O$21*(I5-3))) -> 0 | J18: =IF(J5<=ConstructPeriod,0,IF(J5-ConstructPeriod<=OperationPeriod,假设及结论!$O$13,0)*(1-假设及结论!$N$21-假设及结论!$O$21*(J5-3))) -> 0 | K18: =IF(K5<=ConstructPeriod,0,IF(K5-ConstructPeriod<=OperationPeriod,假设及结论!$O$13,0)*(1-假设及结论!$N$21-假设及结论!$O$21*(K5-3))) -> 0 | L18: =IF(L5<=ConstructPeriod,0,IF(L5-ConstructPeriod<=OperationPeriod,假设及结论!$O$13,0)*(1-假设及结论!$N$21-假设及结论!$O$21*(L5-3))) -> 0 | M18: =IF(M5<=ConstructPeriod,0,IF(M5-ConstructPeriod<=OperationPeriod,假设及结论!$O$13,0)*(1-假设及结论!$N$21-假设及结论!$O$21*(M5-3))) -> 0 | N18: =IF(N5<=ConstructPeriod,0,IF(N5-ConstructPeriod<=OperationPeriod,假设及结论!$O$13,0)*(1-假设及结论!$N$21-假设及结论!$O$21*(N5-3))) -> 0 | ... AD18: =IF(AD5<=ConstructPeriod,0,IF(AD5-ConstructPeriod<=OperationPeriod,假设及结论!$O$13,0)*(1-假设及结论!$N$21-假设及结论!$O$21*(AD5-3))) -> 0
B19: =假设及结论!O13&"小时市场化交易电量" -> 0小时市场化交易电量 | C19: =SUM(E19:AD19) -> 0 | E19: =E18*假设及结论!$F$13 -> 0 | F19: =F18*假设及结论!$F$13 -> 0 | G19: =G18*假设及结论!$F$13 -> 0 | H19: =H18*假设及结论!$F$13 -> 0 | I19: =I18*假设及结论!$F$13 -> 0 | J19: =J18*假设及结论!$F$13 -> 0 | K19: =K18*假设及结论!$F$13 -> 0 | L19: =L18*假设及结论!$F$13 -> 0 | ... AD19: =AD18*假设及结论!$F$13 -> 0
A20: 1.1.4 | B20: 储能容量租赁收入 | E20: =E21*E22/10 -> 0 | F20: =F21*F22/10 -> 0 | G20: =G21*G22/10 -> 0 | H20: =H21*H22/10 -> 0 | I20: =I21*I22/10 -> 0 | J20: =J21*J22/10 -> 0 | K20: =K21*K22/10 -> 0 | L20: =L21*L22/10 -> 0 | ... AD20: =AD21*AD22/10 -> 0
B21: 租赁价格(元/wh) | E21: =IF(E25=0,0,IF(假设及结论!$Q$7="NO",假设及结论!$Q$18,假设及结论!$Q$18/(1+假设及结论!$H$30+假设及结论!$K$30))) -> 0 | F21: =IF(F25=0,0,IF(假设及结论!$Q$7="NO",假设及结论!$Q$18,假设及结论!$Q$18/(1+假设及结论!$H$30+假设及结论!$K$30))) -> 0 | G21: =IF(G25=0,0,IF(假设及结论!$Q$7="NO",假设及结论!$Q$18,假设及结论!$Q$18/(1+假设及结论!$H$30+假设及结论!$K$30))) -> 0 | H21: =IF(H25=0,0,IF(假设及结论!$Q$7="NO",假设及结论!$Q$18,假设及结论!$Q$18/(1+假设及结论!$H$30+假设及结论!$K$30))) -> 0 | I21: =IF(I25=0,0,IF(假设及结论!$Q$7="NO",假设及结论!$Q$18,假设及结论!$Q$18/(1+假设及结论!$H$30+假设及结论!$K$30))) -> 0 | J21: =IF(J25=0,0,IF(假设及结论!$Q$7="NO",假设及结论!$Q$18,假设及结论!$Q$18/(1+假设及结论!$H$30+假设及结论!$K$30))) -> 0 | K21: =IF(K25=0,0,IF(假设及结论!$Q$7="NO",假设及结论!$Q$18,假设及结论!$Q$18/(1+假设及结论!$H$30+假设及结论!$K$30))) -> 0 | L21: =IF(L25=0,0,IF(假设及结论!$Q$7="NO",假设及结论!$Q$18,假设及结论!$Q$18/(1+假设及结论!$H$30+假设及结论!$K$30))) -> 0 | ... AD21: =IF(AD25=0,0,IF(假设及结论!$Q$7="NO",假设及结论!$Q$18,假设及结论!$Q$18/(1+假设及结论!$H$30+假设及结论!$K$30))) -> 0
B22: 租赁容量（kw） | E22: =IF(E25=0,0,假设及结论!$P$18*假设及结论!$F$13*假设及结论!$E$18*假设及结论!$D$18*10000) -> 191250 | F22: =IF(F25=0,0,假设及结论!$P$18*假设及结论!$F$13*假设及结论!$E$18*假设及结论!$D$18*10000) -> 191250 | G22: =IF(G25=0,0,假设及结论!$P$18*假设及结论!$F$13*假设及结论!$E$18*假设及结论!$D$18*10000) -> 191250 | H22: =IF(H25=0,0,假设及结论!$P$18*假设及结论!$F$13*假设及结论!$E$18*假设及结论!$D$18*10000) -> 191250 | I22: =IF(I25=0,0,假设及结论!$P$18*假设及结论!$F$13*假设及结论!$E$18*假设及结论!$D$18*10000) -> 191250 | J22: =IF(J25=0,0,假设及结论!$P$18*假设及结论!$F$13*假设及结论!$E$18*假设及结论!$D$18*10000) -> 191250 | K22: =IF(K25=0,0,假设及结论!$P$18*假设及结论!$F$13*假设及结论!$E$18*假设及结论!$D$18*10000) -> 191250 | L22: =IF(L25=0,0,假设及结论!$P$18*假设及结论!$F$13*假设及结论!$E$18*假设及结论!$D$18*10000) -> 191250 | ... AD22: =IF(AD25=0,0,假设及结论!$P$18*假设及结论!$F$13*假设及结论!$E$18*假设及结论!$D$18*10000) -> 0
A23: 1.1.5 | B23: 储能收入/一般纳入市场化交易考虑 | E23: =IF(E5-1<假设及结论!$F$15,0,IF(E5-1-假设及结论!$F$15<=假设及结论!$G$15,E24*E25*E26,0)/10) -> 2342.8125 | F23: =IF(F5-1<假设及结论!$F$15,0,IF(F5-1-假设及结论!$F$15<=假设及结论!$G$15,F24*F25*F26,0)/10) -> 2319.3844 | G23: =IF(G5-1<假设及结论!$F$15,0,IF(G5-1-假设及结论!$F$15<=假设及结论!$G$15,G24*G25*G26,0)/10) -> 2310.0131 | H23: =IF(H5-1<假设及结论!$F$15,0,IF(H5-1-假设及结论!$F$15<=假设及结论!$G$15,H24*H25*H26,0)/10) -> 2300.6419 | I23: =IF(I5-1<假设及结论!$F$15,0,IF(I5-1-假设及结论!$F$15<=假设及结论!$G$15,I24*I25*I26,0)/10) -> 2291.2706 | J23: =IF(J5-1<假设及结论!$F$15,0,IF(J5-1-假设及结论!$F$15<=假设及结论!$G$15,J24*J25*J26,0)/10) -> 2281.8994 | K23: =IF(K5-1<假设及结论!$F$15,0,IF(K5-1-假设及结论!$F$15<=假设及结论!$G$15,K24*K25*K26,0)/10) -> 2272.5281 | L23: =IF(L5-1<假设及结论!$F$15,0,IF(L5-1-假设及结论!$F$15<=假设及结论!$G$15,L24*L25*L26,0)/10) -> 2263.1569 | ... AD23: =IF(AD5-1<假设及结论!$F$15,0,IF(AD5-1-假设及结论!$F$15<=假设及结论!$G$15,AD24*AD25*AD26,0)/10) -> 0
B24: 储能电价(元/kWh)/一般按市场化交易价格考虑 | E24: =IF(E25=0,0,IF(假设及结论!$Q$7="NO",IF(E5-1>假设及结论!$G$15,假设及结论!$J$15,假设及结论!$N$18),IF(E5-1>假设及结论!$G$15,假设及结论!$J$15,假设及结论!$N$18)/(1+假设及结论!$H$30+假设及结论!$K$30))) -> 0.35 | F24: =IF(F25=0,0,IF(假设及结论!$Q$7="NO",IF(F5-1>假设及结论!$G$15,假设及结论!$J$15,假设及结论!$N$18),IF(F5-1>假设及结论!$G$15,假设及结论!$J$15,假设及结论!$N$18)/(1+假设及结论!$H$30+假设及结论!$K$30))) -> 0.35 | G24: =IF(G25=0,0,IF(假设及结论!$Q$7="NO",IF(G5-1>假设及结论!$G$15,假设及结论!$J$15,假设及结论!$N$18),IF(G5-1>假设及结论!$G$15,假设及结论!$J$15,假设及结论!$N$18)/(1+假设及结论!$H$30+假设及结论!$K$30))) -> 0.35 | H24: =IF(H25=0,0,IF(假设及结论!$Q$7="NO",IF(H5-1>假设及结论!$G$15,假设及结论!$J$15,假设及结论!$N$18),IF(H5-1>假设及结论!$G$15,假设及结论!$J$15,假设及结论!$N$18)/(1+假设及结论!$H$30+假设及结论!$K$30))) -> 0.35 | I24: =IF(I25=0,0,IF(假设及结论!$Q$7="NO",IF(I5-1>假设及结论!$G$15,假设及结论!$J$15,假设及结论!$N$18),IF(I5-1>假设及结论!$G$15,假设及结论!$J$15,假设及结论!$N$18)/(1+假设及结论!$H$30+假设及结论!$K$30))) -> 0.35 | J24: =IF(J25=0,0,IF(假设及结论!$Q$7="NO",IF(J5-1>假设及结论!$G$15,假设及结论!$J$15,假设及结论!$N$18),IF(J5-1>假设及结论!$G$15,假设及结论!$J$15,假设及结论!$N$18)/(1+假设及结论!$H$30+假设及结论!$K$30))) -> 0.35 | K24: =IF(K25=0,0,IF(假设及结论!$Q$7="NO",IF(K5-1>假设及结论!$G$15,假设及结论!$J$15,假设及结论!$N$18),IF(K5-1>假设及结论!$G$15,假设及结论!$J$15,假设及结论!$N$18)/(1+假设及结论!$H$30+假设及结论!$K$30))) -> 0.35 | L24: =IF(L25=0,0,IF(假设及结论!$Q$7="NO",IF(L5-1>假设及结论!$G$15,假设及结论!$J$15,假设及结论!$N$18),IF(L5-1>假设及结论!$G$15,假设及结论!$J$15,假设及结论!$N$18)/(1+假设及结论!$H$30+假设及结论!$K$30))) -> 0.35 | ... AD24: =IF(AD25=0,0,IF(假设及结论!$Q$7="NO",IF(AD5-1>假设及结论!$G$15,假设及结论!$J$15,假设及结论!$N$18),IF(AD5-1>假设及结论!$G$15,假设及结论!$J$15,假设及结论!$N$18)/(1+假设及结论!$H$30+假设及结论!$K$30))) -> 0
B25: 储能小时数 | C25: =SUM(E25:AD25) -> 8750 | E25: =IF(E5<=ConstructPeriod,0,IF(E5-ConstructPeriod<=OperationPeriod,假设及结论!$I$18,0)) -> 350 | F25: =IF(F5<=ConstructPeriod,0,IF(F5-ConstructPeriod<=OperationPeriod,假设及结论!$I$18,0)) -> 350 | G25: =IF(G5<=ConstructPeriod,0,IF(G5-ConstructPeriod<=OperationPeriod,假设及结论!$I$18,0)) -> 350 | H25: =IF(H5<=ConstructPeriod,0,IF(H5-ConstructPeriod<=OperationPeriod,假设及结论!$I$18,0)) -> 350 | I25: =IF(I5<=ConstructPeriod,0,IF(I5-ConstructPeriod<=OperationPeriod,假设及结论!$I$18,0)) -> 350 | J25: =IF(J5<=ConstructPeriod,0,IF(J5-ConstructPeriod<=OperationPeriod,假设及结论!$I$18,0)) -> 350 | K25: =IF(K5<=ConstructPeriod,0,IF(K5-ConstructPeriod<=OperationPeriod,假设及结论!$I$18,0)) -> 350 | L25: =IF(L5<=ConstructPeriod,0,IF(L5-ConstructPeriod<=OperationPeriod,假设及结论!$I$18,0)) -> 350 | ... AD25: =IF(AD5<=ConstructPeriod,0,IF(AD5-ConstructPeriod<=OperationPeriod,假设及结论!$I$18,0)) -> 0
B26: 储能电量(MW) | E26: =IF(E5<=ConstructPeriod,0,IF(E5-ConstructPeriod<=OperationPeriod,假设及结论!$F$13*10*假设及结论!$E$18*假设及结论!$O$18)) -> 191.25 | F26: =IF(F5<=ConstructPeriod,0,IF(F5-ConstructPeriod<=OperationPeriod,假设及结论!$F$13*10*假设及结论!$E$18*假设及结论!$O$18*(1-假设及结论!$N$21))) -> 189.3375 | G26: =IF(G5<=ConstructPeriod,0,IF(G5-ConstructPeriod<=OperationPeriod,假设及结论!$F$13*10*假设及结论!$E$18*假设及结论!$O$18*(1-假设及结论!$N$21-假设及结论!$O$21*(G5-3)))) -> 188.5725 | H26: =IF(H5<=ConstructPeriod,0,IF(H5-ConstructPeriod<=OperationPeriod,假设及结论!$F$13*10*假设及结论!$E$18*假设及结论!$O$18*(1-假设及结论!$N$21-假设及结论!$O$21*(H5-3)))) -> 187.8075 | I26: =IF(I5<=ConstructPeriod,0,IF(I5-ConstructPeriod<=OperationPeriod,假设及结论!$F$13*10*假设及结论!$E$18*假设及结论!$O$18*(1-假设及结论!$N$21-假设及结论!$O$21*(I5-3)))) -> 187.0425 | J26: =IF(J5<=ConstructPeriod,0,IF(J5-ConstructPeriod<=OperationPeriod,假设及结论!$F$13*10*假设及结论!$E$18*假设及结论!$O$18*(1-假设及结论!$N$21-假设及结论!$O$21*(J5-3)))) -> 186.2775 | K26: =IF(K5<=ConstructPeriod,0,IF(K5-ConstructPeriod<=OperationPeriod,假设及结论!$F$13*10*假设及结论!$E$18*假设及结论!$O$18*(1-假设及结论!$N$21-假设及结论!$O$21*(K5-3)))) -> 185.5125 | L26: =IF(L5<=ConstructPeriod,0,IF(L5-ConstructPeriod<=OperationPeriod,假设及结论!$F$13*10*假设及结论!$E$18*假设及结论!$O$18*(1-假设及结论!$N$21-假设及结论!$O$21*(L5-3)))) -> 184.7475 | M26: =IF(M5<=ConstructPeriod,0,IF(M5-ConstructPeriod<=OperationPeriod,假设及结论!$F$13*10*假设及结论!$E$18*假设及结论!$O$18*(1-假设及结论!$N$21-假设及结论!$O$21*(M5-3)))) -> 183.9825 | N26: =IF(N5<=ConstructPeriod,0,IF(N5-ConstructPeriod<=OperationPeriod,假设及结论!$F$13*10*假设及结论!$E$18*假设及结论!$O$18*(1-假设及结论!$N$21-假设及结论!$O$21*(N5-3)))) -> 183.2175 | ... AC26: =IF(AC5<=ConstructPeriod,0,IF(AC5-ConstructPeriod<=OperationPeriod,假设及结论!$F$13*10*假设及结论!$E$18*假设及结论!$O$18*(1-假设及结论!$N$21-假设及结论!$O$21*(AC5-3)))) -> 171.7425
B28: 销项税额 | C28: =SUM(E28:AD28) -> 0 | D28: =D7*17% -> 0 | E28: =IF(假设及结论!$Q$7="NO",0,(E10*假设及结论!$L$15+E14*假设及结论!$P$15+E18*假设及结论!$O$15)*假设及结论!$F$13+假设及结论!$F$13*假设及结论!$E$18*假设及结论!$P$18*假设及结论!$D$18*假设及结论!$Q$18*1000-E7) -> 0 | F28: =IF(假设及结论!$Q$7="NO",0,(F10*假设及结论!$L$15+F14*假设及结论!$P$15+F18*假设及结论!$O$15)*假设及结论!$F$13+假设及结论!$F$13*假设及结论!$E$18*假设及结论!$P$18*假设及结论!$D$18*假设及结论!$Q$18*1000-F7) -> 0 | G28: =IF(假设及结论!$Q$7="NO",0,(G10*假设及结论!$L$15+G14*假设及结论!$P$15+G18*假设及结论!$O$15)*假设及结论!$F$13+假设及结论!$F$13*假设及结论!$E$18*假设及结论!$P$18*假设及结论!$D$18*假设及结论!$Q$18*1000-G7) -> 0 | H28: =IF(假设及结论!$Q$7="NO",0,(H10*假设及结论!$L$15+H14*假设及结论!$P$15+H18*假设及结论!$O$15)*假设及结论!$F$13+假设及结论!$F$13*假设及结论!$E$18*假设及结论!$P$18*假设及结论!$D$18*假设及结论!$Q$18*1000-H7) -> 0 | I28: =IF(假设及结论!$Q$7="NO",0,(I10*假设及结论!$L$15+I14*假设及结论!$P$15+I18*假设及结论!$O$15)*假设及结论!$F$13+假设及结论!$F$13*假设及结论!$E$18*假设及结论!$P$18*假设及结论!$D$18*假设及结论!$Q$18*1000-I7) -> 0 | J28: =IF(假设及结论!$Q$7="NO",0,(J10*假设及结论!$L$15+J14*假设及结论!$P$15+J18*假设及结论!$O$15)*假设及结论!$F$13+假设及结论!$F$13*假设及结论!$E$18*假设及结论!$P$18*假设及结论!$D$18*假设及结论!$Q$18*1000-J7) -> 0 | K28: =IF(假设及结论!$Q$7="NO",0,(K10*假设及结论!$L$15+K14*假设及结论!$P$15+K18*假设及结论!$O$15)*假设及结论!$F$13+假设及结论!$F$13*假设及结论!$E$18*假设及结论!$P$18*假设及结论!$D$18*假设及结论!$Q$18*1000-K7) -> 0 | L28: =IF(假设及结论!$Q$7="NO",0,(L10*假设及结论!$L$15+L14*假设及结论!$P$15+L18*假设及结论!$O$15)*假设及结论!$F$13+假设及结论!$F$13*假设及结论!$E$18*假设及结论!$P$18*假设及结论!$D$18*假设及结论!$Q$18*1000-L7) -> 0 | ... AD28: =IF(假设及结论!$Q$7="NO",0,(AD10*假设及结论!$L$15+AD14*假设及结论!$P$15+AD18*假设及结论!$O$15)*假设及结论!$F$13+假设及结论!$F$13*假设及结论!$E$18*假设及结论!$P$18*假设及结论!$D$18*假设及结论!$Q$18*1000-AD7) -> 0
A30: 2 | B30: 营业税金及附加 | C30: =SUM(E30:AD30) -> 9400.2439 | D30: =SUM(D31:D32) -> 0 | E30: =SUM(E31:E33) -> 397.3725 | F30: =SUM(F31:F33) -> 393.39878 | G30: =SUM(G31:G33) -> 391.80928 | H30: =SUM(H31:H33) -> 390.21979 | I30: =SUM(I31:I33) -> 388.63031 | J30: =SUM(J31:J33) -> 387.04082 | K30: =SUM(K31:K33) -> 385.45132 | L30: =SUM(L31:L33) -> 383.86183 | ... AD30: =SUM(AD31:AD33) -> 0
A31: 2.1 | B31: ="城市维护建设费（"&假设及结论!F30*100&"%）" -> 城市维护建设费（0%） | C31: =SUM(E31:AD31) -> 0 | E31: =IF(E39=0,0,E39*假设及结论!$F$30) -> 0 | F31: =IF(F39=0,0,F39*假设及结论!$F$30) -> 0 | G31: =IF(G39=0,0,G39*假设及结论!$F$30) -> 0 | H31: =IF(H39=0,0,H39*假设及结论!$F$30) -> 0 | I31: =IF(I39=0,0,I39*假设及结论!$F$30) -> 0 | J31: =IF(J39=0,0,J39*假设及结论!$F$30) -> 0 | K31: =IF(K39=0,0,K39*假设及结论!$F$30) -> 0 | L31: =IF(L39=0,0,L39*假设及结论!$F$30) -> 0 | ... AD31: =IF(AD39=0,0,AD39*假设及结论!$F$30) -> 0
A32: 2.2 | B32: ="教育附加（"&假设及结论!G30*100&"%）" -> 教育附加（0%） | C32: =SUM(E32:AD32) -> 0 | D32: =D35*3% -> 0 | E32: =IF(E39=0,0,E39*假设及结论!$G$30) -> 0 | F32: =IF(F39=0,0,F39*假设及结论!$G$30) -> 0 | G32: =IF(G39=0,0,G39*假设及结论!$G$30) -> 0 | H32: =IF(H39=0,0,H39*假设及结论!$G$30) -> 0 | I32: =IF(I39=0,0,I39*假设及结论!$G$30) -> 0 | J32: =IF(J39=0,0,J39*假设及结论!$G$30) -> 0 | K32: =IF(K39=0,0,K39*假设及结论!$G$30) -> 0 | L32: =IF(L39=0,0,L39*假设及结论!$G$30) -> 0 | ... AD32: =IF(AD39=0,0,AD39*假设及结论!$G$30) -> 0
A33: 2.3 | B33: ="销售税（"&假设及结论!K30*100&"%）" -> 销售税（1%） | C33: =SUM(E33:AD33) -> 9400.2439 | E33: =E6*假设及结论!$K$30 -> 397.3725 | F33: =F6*假设及结论!$K$30 -> 393.39878 | G33: =G6*假设及结论!$K$30 -> 391.80928 | H33: =H6*假设及结论!$K$30 -> 390.21979 | I33: =I6*假设及结论!$K$30 -> 388.63031 | J33: =J6*假设及结论!$K$30 -> 387.04082 | K33: =K6*假设及结论!$K$30 -> 385.45132 | L33: =L6*假设及结论!$K$30 -> 383.86183 | ... AD33: =AD6*假设及结论!$K$30 -> 0
A35: 3 | B35: 增值税初始 | C35: =SUM(E35:AD35) -> 0 | D35: =(D36-D37)/2 -> 0 | E35: =E36-E37 -> 0 | F35: =F36-F37 -> 0 | G35: =G36-G37 -> 0 | H35: =H36-H37 -> 0 | I35: =I36-I37 -> 0 | J35: =J36-J37 -> 0 | K35: =K36-K37 -> 0 | L35: =L36-L37 -> 0 | ... AD35: =AD36-AD37 -> 0
B36: 销项税额 | D36: =D29 -> 0 | E36: =E28 -> 0 | F36: =F28 -> 0 | G36: =G28 -> 0 | H36: =H28 -> 0 | I36: =I28 -> 0 | J36: =J28 -> 0 | K36: =K28 -> 0 | L36: =L28 -> 0 | ... AD36: =AD28 -> 0
B37: 进项税额 | F37: =IF(E37-E36<0,0,E37-E36) -> 0 | G37: =IF(F37-F36<0,0,F37-F36) -> 0 | H37: =IF(G37-G36<0,0,G37-G36) -> 0 | I37: =IF(H37-H36<0,0,H37-H36) -> 0 | J37: =IF(I37-I36<0,0,I37-I36) -> 0 | K37: =IF(J37-J36<0,0,J37-J36) -> 0 | L37: =IF(K37-K36<0,0,K37-K36) -> 0 | M37: =IF(L37-L36<0,0,L37-L36) -> 0 | ... AD37: =IF(AC37-AC36<0,0,AC37-AC36) -> 0
B38: 递延抵扣前余额 | C38: =IF(假设及结论!$Q$7="NO",0,FixedAssets/(1+假设及结论!$H$30)*假设及结论!$H$30) -> 0 | E38: =IF(E5<=ConstructPeriod,0,IF($C$38-SUM($D$35:D35)<0,0,$C$38-SUM($D$35:D35))) -> 0 | F38: =IF(F5<=ConstructPeriod,0,IF($C$38-SUM($D$35:E35)<0,0,$C$38-SUM($D$35:E35))) -> 0 | G38: =IF(G5<=ConstructPeriod,0,IF($C$38-SUM($D$35:F35)<0,0,$C$38-SUM($D$35:F35))) -> 0 | H38: =IF(H5<=ConstructPeriod,0,IF($C$38-SUM($D$35:G35)<0,0,$C$38-SUM($D$35:G35))) -> 0 | I38: =IF(I5<=ConstructPeriod,0,IF($C$38-SUM($D$35:H35)<0,0,$C$38-SUM($D$35:H35))) -> 0 | J38: =IF(J5<=ConstructPeriod,0,IF($C$38-SUM($D$35:I35)<0,0,$C$38-SUM($D$35:I35))) -> 0 | K38: =IF(K5<=ConstructPeriod,0,IF($C$38-SUM($D$35:J35)<0,0,$C$38-SUM($D$35:J35))) -> 0 | L38: =IF(L5<=ConstructPeriod,0,IF($C$38-SUM($D$35:K35)<0,0,$C$38-SUM($D$35:K35))) -> 0 | ... AD38: =IF(AD5<=ConstructPeriod,0,IF($C$38-SUM($D$35:AC35)<0,0,$C$38-SUM($D$35:AC35))) -> 0
B39: 增值税缴纳 | C39: =SUM(E39:AD39) -> 0 | E39: =IF(E35<E38,0,(E35-E38)/IF(假设及结论!$J$30="NO",1,2)) -> 0 | F39: =IF(F35<F38,0,(F35-F38)/IF(假设及结论!$J$30="NO",1,2)) -> 0 | G39: =IF(G35<G38,0,(G35-G38)/IF(假设及结论!$J$30="NO",1,2)) -> 0 | H39: =IF(H35<H38,0,(H35-H38)/IF(假设及结论!$J$30="NO",1,2)) -> 0 | I39: =IF(I35<I38,0,(I35-I38)/IF(假设及结论!$J$30="NO",1,2)) -> 0 | J39: =IF(J35<J38,0,(J35-J38)/IF(假设及结论!$J$30="NO",1,2)) -> 0 | K39: =IF(K35<K38,0,(K35-K38)/IF(假设及结论!$J$30="NO",1,2)) -> 0 | L39: =IF(L35<L38,0,(L35-L38)*IF(假设及结论!$J$30="NO",100%,MID(假设及结论!$J$29,8,3))) -> 0 | M39: =IF(M35<M38,0,(M35-M38)/IF(假设及结论!$J$30="NO",1,2)) -> 0 | N39: =IF(N35<N38,0,(N35-N38)/IF(假设及结论!$J$30="NO",1,2)) -> 0 | O39: =IF(O35<O38,0,(O35-O38)/IF(假设及结论!$J$30="NO",1,2)) -> 0 | P39: =IF(P35<P38,0,(P35-P38)/IF(假设及结论!$J$30="NO",1,2)) -> 0 | Q39: =IF(Q35<Q38,0,(Q35-Q38)/IF(假设及结论!$J$30="NO",1,2)) -> 0 | R39: =IF(R35<R38,0,(R35-R38)/IF(假设及结论!$J$30="NO",1,2)) -> 0 | S39: =IF(S35<S38,0,(S35-S38)/IF(假设及结论!$J$30="NO",1,2)) -> 0 | T39: =IF(T35<T38,0,(T35-T38)/IF(假设及结论!$J$30="NO",1,2)) -> 0 | ... AD39: =IF(AD35<AD38,0,(AD35-AD38)/IF(假设及结论!$J$30="NO",1,2)) -> 0
B40: 增值税减免 | C40: =SUM(E40:AD40) -> 0 | E40: =E28-E39 -> 0 | F40: =F28-F39 -> 0 | G40: =G28-G39 -> 0 | H40: =H28-H39 -> 0 | I40: =I28-I39 -> 0 | J40: =J28-J39 -> 0 | K40: =K28-K39 -> 0 | L40: =L28-L39 -> 0 | ... AD40: =AD28-AD39 -> 0
B41: 递延抵扣后余额 | E41: =F38 -> 0 | F41: =G38 -> 0 | G41: =H38 -> 0 | H41: =I38 -> 0 | I41: =J38 -> 0 | J41: =K38 -> 0 | K41: =L38 -> 0 | L41: =M38 -> 0 | ... AD41: =AE38 -> 0
B42: 增值税返还时的实际收入 | E42: =IF(E35<E38,0,E35-E38-E39) -> 0 | F42: =IF(F35<F38,0,F35-F38-F39) -> 0 | G42: =IF(G35<G38,0,G35-G38-G39) -> 0 | H42: =IF(H35<H38,0,H35-H38-H39) -> 0 | I42: =IF(I35<I38,0,I35-I38-I39) -> 0 | J42: =IF(J35<J38,0,J35-J38-J39) -> 0 | K42: =IF(K35<K38,0,K35-K38-K39) -> 0 | L42: =IF(L35<L38,0,L35-L38-L39) -> 0 | ... AD42: =IF(AD35<AD38,0,AD35-AD38-AD39) -> 0

Sheet 财务计划
A2: 财 务 计 划 现 金 流 量 表
W3: 单位:万元
A4: 序 | B4: 年份 名称 | C4: 建设经营期
A5: 号 | C5: 1 | D5: 2 | E5: 3 | F5: 4 | G5: 5 | H5: 6 | I5: 7 | J5: 8 | K5: 9 | L5: 10 | M5: 11 | N5: 12 | O5: 13 | P5: 14 | Q5: 15 | R5: 16 | S5: 17 | T5: 18 | U5: 19 | V5: 20 | W5: 21 | X5: 22 | Y5: 23 | Z5: 24 | AA5: 25 | AB5: 26 | AC5: 27
A6: 1 | B6: 经营活动净现金流量(1.1-1.2) | C6: =C7-C11 -> 0 | D6: =D7-D11 -> 35363.731 | E6: =E7-E11 -> 34965.645 | F6: =F7-F11 -> 34791.795 | G6: =G7-G11 -> 34617.942 | H6: =H7-H11 -> 34444.087 | I6: =I7-I11 -> 34017.106 | J6: =J7-J11 -> 33843.247 | ... AC6: =AC7-AC11 -> -147.55419
A7: 1.1 | B7: 现金流入 | C7: =SUM(C8:C10) -> 0 | D7: =SUM(D8:D10) -> 39737.25 | E7: =SUM(E8:E10) -> 39339.878 | F7: =SUM(F8:F10) -> 39180.929 | G7: =SUM(G8:G10) -> 39021.98 | H7: =SUM(H8:H10) -> 38863.031 | I7: =SUM(I8:I10) -> 38704.082 | J7: =SUM(J8:J10) -> 38545.132 | ... AC7: =SUM(AC8:AC10) -> 0
A8: 1.1.1 | B8: 营业收入 | C8: =损益表!D6 -> 0 | D8: =销售收入!E6 -> 39737.25 | E8: =销售收入!F6 -> 39339.878 | F8: =销售收入!G6 -> 39180.929 | G8: =销售收入!H6 -> 39021.98 | H8: =销售收入!I6 -> 38863.031 | I8: =销售收入!J6 -> 38704.082 | J8: =销售收入!K6 -> 38545.132 | K8: =销售收入!L6 -> 38386.183 | ... AC8: =销售收入!AD6 -> 0
A9: 1.1.2 | B9: 增值税销项税额 | C9: =销售收入!D36 -> 0 | D9: =销售收入!E28 -> 0 | E9: =销售收入!F28 -> 0 | F9: =销售收入!G28 -> 0 | G9: =销售收入!H28 -> 0 | H9: =销售收入!I28 -> 0 | I9: =销售收入!J28 -> 0 | J9: =销售收入!K28 -> 0 | K9: =销售收入!L28 -> 0 | ... AC9: =销售收入!AD28 -> 0
A10: 1.1.4 | B10: 其他流入
A11: 1.2 | B11: 现金流出 | C11: =SUM(C12:C18) -> 0 | D11: =SUM(D12:D18) -> 4373.5185 | E11: =SUM(E12:E18) -> 4374.232 | F11: =SUM(F12:F18) -> 4389.1337 | G11: =SUM(G12:G18) -> 4404.0374 | H11: =SUM(H12:H18) -> 4418.943 | I11: =SUM(I12:I18) -> 4686.9757 | J11: =SUM(J12:J18) -> 4701.8853 | ... AC11: =SUM(AC12:AC18) -> 147.55419
A12: 1.2.1 | B12: 经营成本 | C12: =总成本!D17 -> 0 | D12: =总成本!E17 -> 3001.1851 | E12: =总成本!F17 -> 3003.2646 | F12: =总成本!G17 -> 3005.3463 | G12: =总成本!H17 -> 3007.43 | H12: =总成本!I17 -> 3009.5159 | I12: =总成本!J17 -> 3278.0511 | J12: =总成本!K17 -> 3280.1411 | ... AC12: =总成本!AD17 -> 155.3202
A13: 1.2.2 | B13: 增值税进项税额 | C13: =销售收入!D37 -> 0 | D13: =销售收入!E37 -> 0 | E13: =销售收入!F37 -> 0 | F13: =销售收入!G37 -> 0 | G13: =销售收入!H37 -> 0 | H13: =销售收入!I37 -> 0 | I13: =销售收入!J37 -> 0 | J13: =销售收入!K37 -> 0 | ... AC13: =销售收入!AD37 -> 0
A14: 1.2.3 | B14: 营业税金及附加 | C14: =销售收入!D30 -> 0 | D14: =销售收入!E30 -> 397.3725 | E14: =销售收入!F30 -> 393.39878 | F14: =销售收入!G30 -> 391.80928 | G14: =销售收入!H30 -> 390.21979 | H14: =销售收入!I30 -> 388.63031 | I14: =销售收入!J30 -> 387.04082 | J14: =销售收入!K30 -> 385.45132 | ... AC14: =销售收入!AD30 -> 0
A15: 1.2.4 | B15: 增值税缴纳 | C15: =销售收入!D35 -> 0 | D15: =销售收入!E39 -> 0 | E15: =销售收入!F39 -> 0 | F15: =销售收入!G39 -> 0 | G15: =销售收入!H39 -> 0 | H15: =销售收入!I39 -> 0 | I15: =销售收入!J39 -> 0 | J15: =销售收入!K39 -> 0 | K15: =销售收入!L39 -> 0 | ... AC15: =销售收入!AD39 -> 0
A16: 1.2.5 | B16: 所得税 | C16: =损益表!D13 -> 0 | D16: =损益表!E13 -> 0 | E16: =损益表!F13 -> 0 | F16: =损益表!G13 -> 0 | G16: =损益表!H13 -> 0 | H16: =损益表!I13 -> 0 | I16: =损益表!J13 -> 0 | J16: =损益表!K13 -> 0 | ... AC16: =损益表!AD13 -> 0
A17: 1.2.6 | B17: 预提税 | D17: =损益表!E19 -> 974.96097 | E17: =损益表!F19 -> 977.56863 | F17: =损益表!G19 -> 991.97815 | G17: =损益表!H19 -> 1006.3876 | H17: =损益表!I19 -> 1020.7969 | I17: =损益表!J19 -> 1021.8837 | J17: =损益表!K19 -> 1036.2928 | K17: =损益表!L19 -> 1050.7018 | ... AC17: =损益表!AD19 -> -7.76601
A18: 1.2.7 | B18: 其他流出
A20: 2 | B20: 投资活动净现金流量(2.1-2.2) | C20: =C21-C22 -> -267947.36 | D20: =D21-D22 -> 0 | E20: =E21-E22 -> 0 | F20: =F21-F22 -> 0 | G20: =G21-G22 -> 0 | H20: =H21-H22 -> 0 | I20: =I21-I22 -> 0 | J20: =J21-J22 -> 0 | ... AC20: =AC21-AC22 -> 0
A21: 2.1 | B21: 现金流入
A22: 2.2 | B22: 现金流出 | C22: =SUM(C23:C26) -> 267947.36 | D22: =SUM(D23:D26) -> 0 | E22: =SUM(E23:E26) -> 0 | F22: =SUM(F23:F26) -> 0 | G22: =SUM(G23:G26) -> 0 | H22: =SUM(H23:H26) -> 0 | I22: =SUM(I23:I26) -> 0 | J22: =SUM(J23:J26) -> 0 | ... AC22: =SUM(AC23:AC26) -> 0
A23: 2.2.1 | B23: 建设投资 | C23: =资金筹措!C7 -> 263131.9 | D23: =资金筹措!D7 -> 0 | E23: =资金筹措!E7 -> 0
A24: 2.2.2 | B24: 维持运营投资 | C24: =资金筹措!C8 -> 3315.4619
A25: 2.2.3 | B25: 流动资金 | C25: =资金筹措!C9 -> 1500 | D25: =资金筹措!D9 -> 0 | E25: =资金筹措!E9 -> 0
A26: 2.2.4 | B26: 其他流出
A28: 3 | B28: 筹资活动净现金流量(3.1-3.2) | C28: =C29-C36 -> 267947.36 | D28: =D29-D36 -> -19148.683 | E28: =E29-E36 -> -18701.052 | F28: =F29-F36 -> -18253.42 | G28: =G29-G36 -> -17805.789 | H28: =H29-H36 -> -17358.157 | I28: =I29-I36 -> -16910.526 | J28: =J29-J36 -> -16462.894 | ... AC28: =AC29-AC36 -> 1.7025741e-12
A29: 3.1 | B29: 现金流入 | C29: =SUM(C30:C35) -> 267947.36 | D29: =SUM(D30:D35) -> 0 | E29: =SUM(E30:E35) -> 0 | F29: =SUM(F30:F35) -> 0 | G29: =SUM(G30:G35) -> 0 | H29: =SUM(H30:H35) -> 0 | I29: =SUM(I30:I35) -> 0 | J29: =SUM(J30:J35) -> 0 | ... AC29: =SUM(AC30:AC35) -> 0
A30: 3.1.1 | B30: 项目资本金投入 | C30: =资金筹措!C12 -> 81434.207 | D30: =资金筹措!D12 -> 0 | E30: =资金筹措!E12 -> 0
A31: 3.1.2 | B31: 建设投资借款 | C31: =资金筹措!C17+资金筹措!C19 -> 186513.15 | D31: =资金筹措!D17+资金筹措!D19 -> 0 | E31: =资金筹措!E17 -> 0
A32: 3.1.3 | B32: 流动资金借款 | C32: =资金筹措!C18 -> 0
A33: 3.1.4 | B33: 债券
A34: 3.1.5 | B34: 短期借款
A35: 3.1.6 | B35: 其他流出
A36: 3.2 | B36: 现金流出 | C36: =SUM(C37:C40) -> 0 | D36: =SUM(D37:D40) -> 19148.683 | E36: =SUM(E37:E40) -> 18701.052 | F36: =SUM(F37:F40) -> 18253.42 | G36: =SUM(G37:G40) -> 17805.789 | H36: =SUM(H37:H40) -> 17358.157 | I36: =SUM(I37:I40) -> 16910.526 | J36: =SUM(J37:J40) -> 16462.894 | ... AC36: =SUM(AC37:AC40) -> -1.7025741e-12
A37: 3.2.1 | B37: 各种利息支出 | C37: =还本付息!D29 -> 0 | D37: =还本付息!E29 -> 6714.4734 | E37: =还本付息!F29 -> 6266.8418 | F37: =还本付息!G29 -> 5819.2103 | G37: =还本付息!H29 -> 5371.5787 | H37: =还本付息!I29 -> 4923.9472 | I37: =还本付息!J29 -> 4476.3156 | J37: =还本付息!K29 -> 4028.684 | ... AC37: =还本付息!AD29 -> -1.7025741e-12
A38: 3.2.2 | B38: 偿还债务本金 | C38: =还本付息!D28 -> 0 | D38: =还本付息!E28 -> 12434.21 | E38: =还本付息!F28 -> 12434.21 | F38: =还本付息!G28 -> 12434.21 | G38: =还本付息!H28 -> 12434.21 | H38: =还本付息!I28 -> 12434.21 | I38: =还本付息!J28 -> 12434.21 | J38: =还本付息!K28 -> 12434.21 | ... AC38: =还本付息!AD28 -> 0
A39: 3.2.3 | B39: 应付利润
A40: 3.2.4 | B40: 其他流出
A42: 4 | B42: 净现金流量(1+2+3) | C42: =SUM(C6,C20,C28) -> 0 | D42: =SUM(D6,D20,D28) -> 16215.048 | E42: =SUM(E6,E20,E28) -> 16264.594 | F42: =SUM(F6,F20,F28) -> 16538.374 | G42: =SUM(G6,G20,G28) -> 16812.153 | H42: =SUM(H6,H20,H28) -> 17085.93 | I42: =SUM(I6,I20,I28) -> 17106.58 | J42: =SUM(J6,J20,J28) -> 17380.353 | ... AC42: =SUM(AC6,AC20,AC28) -> -147.55419
A43: 5 | B43: 累计盈余资金 | C43: =C42 -> 0 | D43: =IF(C5-ConstructPeriod<OperationPeriod,D42+C43,0) -> 16215.048 | E43: =IF(D5-ConstructPeriod<OperationPeriod,E42+D43,0) -> 32479.642 | F43: =IF(E5-ConstructPeriod<OperationPeriod,F42+E43,0) -> 49018.016 | G43: =IF(F5-ConstructPeriod<OperationPeriod,G42+F43,0) -> 65830.17 | H43: =IF(G5-ConstructPeriod<OperationPeriod,H42+G43,0) -> 82916.1 | I43: =IF(H5-ConstructPeriod<OperationPeriod,I42+H43,0) -> 100022.68 | J43: =IF(I5-ConstructPeriod<OperationPeriod,J42+I43,0) -> 117403.03 | K43: =IF(J5-ConstructPeriod<OperationPeriod,K42+J43,0) -> 135057.16 | ... AC43: =IF(AB5-ConstructPeriod<OperationPeriod,AC42+AB43,0) -> 0

Sheet 还本付息
A2: 借 款 还 本 付 息 计 划 表
B3: ="还款方式为:"&IF(假设及结论!R30=1,"等额本息","等额本金") -> 还款方式为:等额本金 | D3: ="贷款年限为："&假设及结论!O30&" 年" -> 贷款年限为：15 年 | Y3: 单位:万元
A4: 序 | B4: 年份 名称 | C4: 利率 | D4: 建设运营期
A5: 号 | D5: 1 | E5: 2 | F5: 3 | G5: 4 | H5: 5 | I5: 6 | J5: 7 | K5: 8 | L5: 9 | M5: 10 | N5: 11 | O5: 12 | P5: 13 | Q5: 14 | R5: 15 | S5: 16 | T5: 17 | U5: 18 | V5: 19 | W5: 20 | X5: 21 | Y5: 22 | Z5: 23 | AA5: 24 | AB5: 25 | AC5: 26 | AD5: 27
A6: 1 | B6: 原有借款
A7: 1.1 | B7: 期初借款余额 | F7: =E11 -> 0 | G7: =F11 -> 0 | H7: =G11 -> 0 | I7: =H11 -> 0
A8: 1.2 | B8: 当期还本付息 | E8: =SUM(E9:E10) -> 0 | G8: =SUM(G9:G10) -> 0 | H8: =SUM(H9:H10) -> 0 | I8: =SUM(I9:I10) -> 0
B9: 其中：还本 | G9: =F9*3 -> 0 | H9: =G9 -> 0 | I9: =H9 -> 0 | J9: =I9 -> 0 | K9: =J9 -> 0 | L9: =K9 -> 0 | M9: =L9 -> 0 | N9: =M9 -> 0 | O9: =N9 -> 0 | ... Y9: =X9 -> 0
B10: 付息 | E10: =E7*C6 -> 0 | F10: =F7*C6 -> 0 | G10: =G7*C6 -> 0 | H10: =H7*C6 -> 0 | I10: =I7*C6 -> 0
A11: 1.3 | B11: 期末借款余额 | E11: =E7-E9 -> 0 | F11: =F7-F9 -> 0 | G11: =G7-G9 -> 0 | H11: =H7-H9 -> 0 | I11: =I7-I9 -> 0
A13: 2 | B13: 新增长期借款 | C13: =DebtRate -> 0.036 | D13: =资金筹措!C16-资金筹措!C18 -> 186513.15 | E13: =IF(ConstructPeriod=2,资金筹措!D16-资金筹措!D18,0) -> 0
A14: 2.1 | B14: 期初借款余额 | D14: =D13 -> 186513.15 | E14: =D14+E13 -> 186513.15 | F14: =E18 -> 174078.94 | G14: =F18 -> 161644.73 | H14: =G18 -> 149210.52 | I14: =H18 -> 136776.31 | J14: =I18 -> 124342.1 | K14: =J18 -> 111907.89 | L14: =K18 -> 99473.68 | M14: =L18 -> 87039.47 | ... AD14: =AC18 -> -4.7293724e-11
